Workbook
Name AER: 'GREECE Markowitz'!$R$2:$W$2
Name anscount: 22
Name comments: 'ΟΜΟΛΟΓΑ USA'!#REF!
Name COV: 'GREECE Markowitz'!$M$11:$R$16
Name COVij: 'GREECE Markowitz'!$M$20:$R$25
Name COVij: 'USA Markowitz'!$M$20:$R$25
Name ER: #REF!
Name n: #REF!
Name opap: ΧΑΑ!#REF!
Name R_1: #REF!
Name R_2: #REF!
Name Rij: #REF!
Name USaeg: 'USA Markowitz'!$R$2:$W$2
Name UScovij: 'USA Markowitz'!$M$20:$R$25
Name USw: 'USA Markowitz'!$T$20:$T$25
Name USwr: 'USA Markowitz'!$R$2:$W$2
Name v: 'GREECE Markowitz'!$T$20:$T$25
Name VarRm: 'GREECE Sharpe'!$D$27
Name VarRm: 'USA Sharpe'!$D$27
Name W: #REF!
Name w_c: #REF!
Name Wr: 'GREECE Markowitz'!$T$20:$T$25

Sheet Ερωτηματολόγιο
C1: ΑΝΑΛΥΣΗ ΠΡΟΦΙΛ ΕΠΕΝΔΥΤΟΥ
C2: ΕΡΩΤΗΜΑΤΟΛΟΓΙΟ
C4: ΟΔΗΓΙΕΣ: Παρακαλεισθε να σημειωσετε με ενα Χ την απαντηση η
C5: οποια αφορα την οικογενεια σας. Αφου γραψετε δε τον αριθμο στο
C6: κενο δεξια πρεπει να αθροισετε τους αριθμους και να διαιρεσετε το
C7: αθροισμα αυτο με το 9 (αριθμός ερωτήσεων). Ο μεσος αυτος θα σας δειξει τον
C8: βαθμό κινδυνου που σας χαρακρηριζει, σε μια κλιμακα κινδυνου απο 1
C9: (μικρος βαθμος αποφυγής κινδυνου ή επενδυτής υψηλου κινδυνου)
C10: εως 9 (υψηλος βαθμος αποφυγης κινδυνου ή επενδυτης χαμηλου κινδυνου).
C11: Με βαση τελος τoν βαθμο κινδυνου αυτο θα συγκροτηθει
C12: χαρτοφυλακιο επενδυσεως απο τιτλους χωρίς κινδυνο και με κίνδυνο
B14: A. | C14: ΗΛΙΚΙΑ - Η ηλικια μου ειναι πλησιεστερη στα:
C16: (1) 30 | D16: (3) 40 | E16: (5) 50 | F16: (7) 60 | G16: (9) 70
C18: ΑΠΑΝΤΗΣΗ | D18: [ | E18: 1 | F18: ]
B20: Β. | C20: ΕΙΣΟΔΗΜΑ - Το παρον ετησιο εισοδημα μου απο ολες τις πηγες
C21: σε χιλιάδες ευρώ ειναι:
C23: (2) 41 και ανω | D23: (4) 31-40 | E23: (5) 21-30 | F23: (6) 10-20 | G23: (8)6-9
C25: ΑΠΑΝΤΗΣΗ | D25: [ | E25: 2 | F25: ]
B27: Γ. | C27: ΕΤΗΣΙΑ ΕΞΟΔΑ - Σε σχεση με τα εσοδα μου τα εξοδα μου
C28: ανερχονται σε ποσοστο:
C30: (1) 40% | D30: (3) 70% | E30: (5) 80% | F30: (7) 90% | G30: (9)100%
C32: ΑΠΑΝΤΗΣΗ | D32: [ | E32: 3 | F32: ]
B34: Δ. | C34: ΑΡΙΘΜΟΣ ΕΞΑΡΤΟΝΕΝΩΝ ΜΕΛΩΝ ΟΙΚΟΓΕΝΕΙΑΣ - Προς το παρον εχω
C35: αυτα τα μελη οικογενειας που εξαρτωνται
C37: (1) 0 | D37: (4) 1 | E37: (6) 2-3 | F37: (8) 4-5 | G37: (9) 6
G38: και ανω
C39: ΑΠΑΝΤΗΣΗ | D39: [ | E39: 6 | F39: ]
B41: Ε. | C41: ΕΚΤΙΜΗΣΗ ΑΞΙΑΣ ΠΕΡΙΟΥΣΙΑΚΩΝ ΣΤΟΙΧΕΙΩΝ -
C42: Το σπιτιμου, οι καταθεσεις, οι επενδυσεις και η ασφαλιση μου
C43: αθροιζονται σε χιλιάδες ευρώ:
C45: (1) 151 και ανω | D45: (3) 91-150 | E45: (5) 51-90 | F45: (7) 16-50 | G45: (9) 15
C47: ΑΠΑΝΤΗΣΗ | D47: [ | E47: 1 | F47: ]
B49: Ζ. | C49: ΕΚΤΙΜΗΣΗ ΥΠΟΧΡΕΩΣΕΩΝ - ΟΙ βραχυπροθεσμες ωφειλες μου, τα
C50: τα ενυποθηκα δανεια, οι δοσεις και λοιπες ωφειλες
C51: σε σχεση με τα περιουσιακα μου στοιχεια
C53: (1) 30% | D53: (3) 50% | E53: (5) 75% | F53: (7) 90% | G53: (9) 100%
C55: ΑΠΑΝΤΗΣΗ | D55: [ | E55: 1 | F55: ]
B57: ΣΤ. | C57: ΑΠΟΤΑΜΙΕΥΣΕΙΣ - Εχω ρευστο, καταθεσεις η αλλα ρευστοποιησιμα
C58: περιουσιακα στοιχεια για καλυψη των παραπανω υποχρεωσεων:
C60: (1) 6 μηνες | D60: (3) 4 μηνες | E60: (5) 3 μηνες | F60: (7) 2 μηνες | G60: (9) 1 μηνα
C61: και ανω
C62: ΑΠΑΝΤΗΣΗ | D62: [ | E62: 1 | F62: ]
B64: Η. | C64: ΑΣΦΑΛΕΙΕΣ ΖΩΗΣ - Οι ασφαλειες ζωης μου ανερχοντα σε χιλιάδες ευρώ:
C66: (1) 30 | D66: (3) 60 | E66: (5) 150 | F66: (7) 180 | G66: (9) 250
C68: ΑΠΑΝΤΗΣΗ | D68: [ | E68: 3 | F68: ]
B70: Θ. | C70: ΙΑΤΡΙΚΗ ΑΣΦΑΛΙΣΗ - Η ιατρικη μου ασφαλιση περιλαμβανει:
C72: (1) Βασικη | E72: (5) Βασικη/Iατρικη | G72: (9) Βασικη/Iατρικη /Kαταστροφων
C74: ΑΠΑΝΤΗΣΗ | D74: [ | E74: 5 | F74: ]
C77: ΓΕΝΙΚΗ ΒΑΘΜΟΛΟΓΙΑ | D77: [ | E77: 21 | F77: ]
C79: ΜΕΣΟΣ ΟΡΟΣ ΒΑΘΜΟΛΟΓΙΑΣ | D79: [ | E79: 2.3 | F79: ]
C80: ΚΛΙΜΑΚΑ ΑΠΟ 1 ΕΩΣ 9
B83: 1 | C83: ΒΑΘΜΟΣ ΑΠΟΦΥΓΗΣ ΚΙΝΔΥΝΟΥ (%) | E83: =E79/9 -> 0.25555556 | G83: ΣΕ ΧΡΕΟΓΡΑΦΑ ΜΗΔΕΝΙΚΟΥ ΚΙΝΔΥΝΟΥ
C84: RISK AVERSION
C85: ΟΣΟ ΜΕΓΑΛΥΤΕΡΟ ΣΗΜΑΙΝΕΙ ΕΠΕΝΔΥΤΗΣ ΛΙΓΟΤΕΡΟ ΡΙΨΟΚΙΝΔΥΝΟΣ
B87: 2 | C87: ΑΝΟΧΗ ΣΤΟΝ ΚΙΝΔΥΝΟ (%) | E87: =1-E83 -> 0.74444444 | G87: ΣΕ ΧΡΕΟΓΡΑΦΑ ΜΕ ΚΙΝΔΥΝΟ
C88: RISK TOLERANCE
C89: ΟΣΟ MΕΓΑΛΥΤΕΡΟ ΣΗΜΑΙΝΕΙ ΕΠΕΝΔΥΤΗΣ ΠΕΡΙΣΣΟΤΕΡΟ ΡΙΨΟΚΙΝΔΥΝΟΣ

Sheet Screenshots
B15: ΠΑΡΕΥΡΕΘΗΚΑ ΣΤΟ ΜΑΘΗΜΑ ΑΛΛΑ ΕΙΧΑ ΠΡΟΒΛΗΜΑ ΜΕ ΤΟ EXCEL ΟΠΟΤΕ ΤΟ ΟΛΟΚΛΗΡΩΣΑ ΜΕ ΑΛΛΟΝ ΥΠΟΛΟΓΙΣΤΗ ΤΗΝ ΕΠΟΜΕΝΗ ΜΕΡΑ

Sheet ΟΜΟΛΟΓΑ ΧΑΑ
A1: GREECE 10 YEAR BOND YIELD | B1: Date | C1: Price | D1: Open | E1: High | F1: Low | G1: Change % | J1: https://www.investing.com/rates-bonds/greece-10-year-bond-yield-historical-data
B2: 23/10/2025 | C2: 0.03242 | E2: 0.03257 | F2: 0.03229
B3: 45960 | C3: 0.03295 | E3: 0.03317 | F3: 0.03281 | I3: ΔΙΑΔΙΚΑΣΙΑ YΠΟΛΟΓΙΣΜΟΥ ΑΞΙΑΣ ΟΜOΛΟΓΩΝ και ΟΜΟΛΟΓΙΩΝ
B4: 45967 | C4: 0.0319 | E4: 0.03339 | F4: 0.03302 | I4: [ΖΗΤΟΥΜΕΝΟ Η ΤΙΜΗ ΠΩΛΗΣΗΣ]
B5: 45974 | C5: 0.03321 | E5: 0.0331 | F5: 0.03262 | O5: ΤΙΜΗ ΟΜΟΛΟΓΙΑΣ (ΥΠΟΘΕΤΟΥΜΕ ΣΤΗΝ ΟΝΟΜΑΣΤΙΚΗ ΑΞΙΑ ΤΗΝ ΗΜΕΡΟΜΗΝΙΑ ΑΓΟΡΑΣ 100%)
B6: 45981 | C6: 0.03351 | E6: 0.0389 | F6: 0.0334 | I6: V | J6: 1000 | K6: ΤΙΜΗ ΣΤΟ ΑΡΤΙΟ ή ΟΝΟΜΑΣΤΙΚΗ ΑΞΙΑ ΟΜΟΛΟΓΙΑΣ | L6: [Face Value or Par value]
B7: 45988 | C7: 0.0331 | E7: 0.0323 | F7: 0.03293 | I7: n | J7: 10 | K7: ΧΡΟΝΟΣ ΓΙΑ ΝΑ ΛΗΞΗ | L7: [Life to Maturity] | O7: ΕΠΙΤΟΚΙΟ-ΑΠΟΔΟΣΗ ΤΗΝ ΗΜΕΡΟΜΗΝΙΑ ΑΓΟΡΑΣ ΤΟΥ ΟΜΟΛΟΓΙΑΣ
I8: nm | J8: =J7*J9 -> 10 | O8: πχ ΕΔΩ 1/3/2018
I9: m | J9: 1 | K9: ΚΑΘΕ ΠΕΡΙΟΔΟΣ (1 ΕΤΟΣ, 2 ΕΞΑΜΗΜΟ, 12 ΜΗΝΕΣ) | L9: [every period] | O9: ΕΠΙΤΟΚΙΟ-ΑΠΟΔΟΣΗ ΤΗΝ ΗΜΕΡΟΜΗΝΙΑ ΑΠΟΤΙΜΗΣΗΣ ΤΟΥ ΟΜΟΛΟΓΟΥ
I10: Ct | J10: =J6*J11 -> 32.42 | K10: ΤΟΚΟΣ ΚΟΥΠΟΝΙΟΥ ΣΤΟ ΧΡΟΝΟ t | L10: [Coupon Interest] | O10: πχ ΕΔΏ 24/5/2018 | Q10: (ΑΡΓΟΤΕΡΑ ΗΜΕΡΟΜΗΝΙΑ ΡΕΥΣΤΟΠΟΙΗΣΗΣ ΧΑΡΤΟΦΥΛΑΚΙΟΥ Ή ΕΚΤΙΜΗΣΗΣ ΤΙΜΩΝ ΜΕΤΑ ΈΝΑ ΕΤΟΣ)
I11: %C | J11: =C2 -> 0.03242 | K11: ΕΠΙΤΟΚΙΟ ΚΟΥΠΟΝΙΟΥ | L11: [Coupon Rate]
I12: i | J12: =C3 -> 0.03295 | K12: ΕΠΙΤΟΚΙΟ ΑΓΟΡΑΣ | L12: [Market Rate]
I14: Pt | J14: =-PV(J12/J9,J8,J10,J6) -> 995.5463 | K14: ΚΑΘΑΡΗ ΤΙΜΗ ΑΓΟΡΑΣ | L14: [Bond Price]
J15: =J14/J6 -> 0.9955463 | K15: =IF(J14<J6,"ΥΠΟ ΤΟ ΑΡΤΙΟ",IF(J14>J6,"ΥΠΕΡ ΤΟ ΑΡΤΙΟ","ΣΤΟ ΑΡΤΙΟ")) -> ΥΠΟ ΤΟ ΑΡΤΙΟ
I17: ΑΝΑΛΥΤΙΚΑ
I18: ΠΛΗΡΩΜΕΣ ΠΕΡΙΟΔΟΥ (ΕΤΗΣΙΕΣ)
I19: ΠΑΡΟΥΣΑ ΑΞΙΑ ΤΟΚΟΜΕΡΙΔΙΩΝ
L20: ΠΑΡΟΥΣΑ ΑΞΙΑ ΤΙΜΗΣ ΚΑΤΑ ΤΗΝ ΛΗΞΗ
I21: ΡΟΕΣ | K21: PVIFA(r,n) | L21: ΡΟΕΣ | N21: PVIF(r,n)
I22: =J10 -> 32.42 | J22: x | K22: =PV(J12/J9,J8,-1) -> 8.4032054 | L22: =J6 -> 1000 | M22: x | N22: =1/(1+J12)^J8 -> 0.72311438
J23: =I22*K22 -> 272.43192 | M23: =L22*N22 -> 723.11438
J25: παρουσα αξια τοκομεριδιων | M25: =J23 -> 272.43192
J26: παρουσα αξια τιμης ληξης | M26: =M23 -> 723.11438
J28: αγοραια τιμη ομολ. | L28: Pt | M28: =M25+M26 -> 995.5463
J29: πωληση υπο(-), υπερ(+) το αρτιο | M29: =M28/J6 -> 0.9955463 | O29: ΤΙΜΗ ΟΜΟΛΟΓΙΑΣ ΤΗΝ ΗΜΕΡΟΜΗΝΙΑ ΑΠΟΤΙΜΗΣΗΣ ΤΟΥ ΟΜΟΛΟΓΟΥ
J30: απόδοση-στη-λήξη | O30: πχ ΕΔΏ 24/5/2018 | Q30: (ΑΡΓΟΤΕΡΑ ΗΜΕΡΟΜΗΝΙΑ ΡΕΥΣΤΟΠΟΙΗΣΗΣ ΧΑΡΤΟΦΥΛΑΚΙΟΥ Ή ΕΚΤΙΜΗΣΗΣ ΤΙΜΩΝ ΜΕΤΑ ΈΝΑ ΕΤΟΣ)
L34: ΥΠΟΛΟΓΙΣΜΟΣ ΤΙΜΗΣ ΟΜΟΛΟΓΙΑΣ
L37: ΥΠΟΛΟΓΙΣΜΟΣ ΑΠΟΔΟΣΗΣ ΣΤΗ ΛΗΞΗ

Sheet ΟΜΟΛΟΓΑ USA
A1: USA 10 YEAR BOND YIELD | B1: Date | C1: Price | D1: Open | E1: High | F1: Low | G1: Change % | I1: https://www.investing.com/rates-bonds/u.s.-10-year-bond-yield-historical-data
B2: 23/10/2025 | C2: 0.03983 | E2: 0.0397 | F2: 0.03949
B3: 45960 | C3: 0.04071 | E3: 0.04118 | F3: 0.0406 | I3: ΔΙΑΔΙΚΑΣΙΑ YΠΟΛΟΓΙΣΜΟΥ ΑΞΙΑΣ ΟΜOΛΟΓΩΝ και ΟΜΟΛΟΓΙΩΝ
B4: 45967 | C4: 0.04083 | E4: 0.04153 | F4: 0.04077 | I4: [ΖΗΤΟΥΜΕΝΟ Η ΤΙΜΗ ΠΩΛΗΣΗΣ]
B5: 45974 | C5: 0.04088 | E5: 0.04104 | F5: 0.04056 | O5: ΤΙΜΗ ΟΜΟΛΟΓΙΑΣ (ΥΠΟΘΕΤΟΥΜΕ ΣΤΗΝ ΟΝΟΜΑΣΤΙΚΗ ΑΞΙΑ ΤΗΝ ΗΜΕΡΟΜΗΝΙΑ ΑΓΟΡΑΣ 100%)
B6: 45981 | C6: 0.04098 | E6: 0.04168 | F6: 0.04094 | I6: V | J6: 1000 | K6: ΤΙΜΗ ΣΤΟ ΑΡΤΙΟ ή ΟΝΟΜΑΣΤΙΚΗ ΑΞΙΑ ΟΜΟΛΟΓΙΑΣ | L6: [Face Value or Par value]
B7: 45988 | C7: 0.04001 | E7: 0.04015 | F7: 0.03996 | I7: n | J7: 10 | K7: ΧΡΟΝΟΣ ΓΙΑ ΝΑ ΛΗΞΗ | L7: [Life to Maturity] | O7: ΕΠΙΤΟΚΙΟ-ΑΠΟΔΟΣΗ ΤΗΝ ΗΜΕΡΟΜΗΝΙΑ ΑΓΟΡΑΣ ΤΟΥ ΟΜΟΛΟΓΙΑΣ
I8: nm | J8: =J7*J9 -> 10 | O8: πχ ΕΔΏ 1/3/2018
I9: m | J9: 1 | K9: ΚΑΘΕ ΠΕΡΙΟΔΟΣ (1 ΕΤΟΣ, 2 ΕΞΑΜΗΜΟ, 12 ΜΗΝΕΣ) | L9: [every period] | O9: ΕΠΙΤΟΚΙΟ-ΑΠΟΔΟΣΗ ΤΗΝ ΗΜΕΡΟΜΗΝΙΑ ΑΠΟΤΙΜΗΣΗΣ ΤΟΥ ΟΜΟΛΟΓΟΥ
I10: Ct | J10: =J6*J11 -> 39.83 | K10: ΤΟΚΟΣ ΚΟΥΠΟΝΙΟΥ ΣΤΟ ΧΡΟΝΟ t | L10: [Coupon Interest] | O10: πχ ΕΔΏ 31/5/2017
I11: %C | J11: =C2 -> 0.03983 | K11: ΕΠΙΤΟΚΙΟ ΚΟΥΠΟΝΙΟΥ | L11: [Coupon Rate]
I12: i | J12: =C3 -> 0.04071 | K12: ΕΠΙΤΟΚΙΟ ΑΓΟΡΑΣ | L12: [Market Rate]
I14: Pt | J14: =-PV(J12/J9,J8,J10,J6) -> 992.88757 | K14: ΚΑΘΑΡΗ ΤΙΜΗ ΑΓΟΡΑΣ | L14: [Bond Price]
J15: =J14/J6 -> 0.99288757 | K15: =IF(J14<J6,"ΥΠΟ ΤΟ ΑΡΤΙΟ",IF(J14>J6,"ΥΠΕΡ ΤΟ ΑΡΤΙΟ","ΣΤΟ ΑΡΤΙΟ")) -> ΥΠΟ ΤΟ ΑΡΤΙΟ
I17: ΑΝΑΛΥΤΙΚΑ
I18: ΠΛΗΡΩΜΕΣ ΠΕΡΙΟΔΟΥ (ΕΤΗΣΙΕΣ)
I19: ΠΑΡΟΥΣΑ ΑΞΙΑ ΤΟΚΟΜΕΡΙΔΙΩΝ
L20: ΠΑΡΟΥΣΑ ΑΞΙΑ ΤΙΜΗΣ ΚΑΤΑ ΤΗΝ ΛΗΞΗ
I21: ΡΟΕΣ | K21: PVIFA(r,n) | L21: ΡΟΕΣ | N21: PVIF(r,n)
I22: =J10 -> 39.83 | J22: x | K22: =PV(J12/J9,J8,-1) -> 8.0823038 | L22: =J6 -> 1000 | M22: x | N22: =1/(1+J12/J9)^J8 -> 0.67096941
J23: =I22*K22 -> 321.91816 | M23: =L22*N22 -> 670.96941
J25: παρουσα αξια τοκομεριδιων | M25: =J23 -> 321.91816
J26: παρουσα αξια τιμης ληξης | M26: =M23 -> 670.96941
J28: αγοραια τιμη ομολ. | L28: Pt | M28: =M25+M26 -> 992.88757
J29: πωληση υπο(-), υπερ(+) το αρτιο | M29: =M28/J6 -> 0.99288757 | O29: ΤΙΜΗ ΟΜΟΛΟΓΙΑΣ ΤΗΝ ΗΜΕΡΟΜΗΝΙΑ ΑΠΟΤΙΜΗΣΗΣ ΤΟΥ ΟΜΟΛΟΓΟΥ
J30: απόδοση-στη-λήξη | O30: πχ ΕΔΏ 24/5/2018
L34: ΥΠΟΛΟΓΙΣΜΟΣ ΤΙΜΗΣ ΟΜΟΛΟΓΙΑΣ
L37: ΥΠΟΛΟΓΙΣΜΟΣ ΑΠΟΔΟΣΗΣ ΣΤΗ ΛΗΞΗ

Sheet Ομολογα
A1: 1 | B1: Spreads 10ετών κρατικών ομολόγων
B2: 23/10/2025
B3: ΣΕ ΕΤΗΣΙΑ ΒΑΣΗ
B4: Χώρα | C4: Απόδοση | D4: Spread έναντι Bund | E4: Spread έναντι T-bond
B5: Γερμανία | C5: 0.025782 | E5: =C5-C7 -> -0.014048 | H5: ETΗΣΙΟΠOIHMENO ΣΕ ΠΕΡΙΟΔΙΚΟ
B6: Ελλάδα | C6: 0.03242 | D6: =C6-C5 -> 0.006638 | E6: =C6-C7 -> -0.00741 | H6: ΙΣΧΥΕΙ Η ΣΧΕΣΗ
B7: ΗΠΑ | C7: 0.03983 | D7: =C7-C5 -> 0.014048
B9: n= Αριθμός Ετών | D9: 1
B10: m= περίοδοι ανα Ετος | D10: 250 | H10: R το Ετησιο Επιτοκιο
H11: r=R/m το Περιοδικο Επιτοκιο
B12: ΣΕ ΗΜΕΡΗΣΙΑ ΒΑΣΗ
B13: Χώρα | C13: Απόδοση | D13: Spread έναντι Bund | E13: Spread έναντι T-bond
B14: Γερμανία | C14: =(1+C5)^(1/($D$10*$D$9))-1 -> 0.00010182618 | E14: =(1+E5)^(1/($D$10*$D$9))-1 -> -5.6588827e-05
B15: Ελλάδα | C15: =(1+C6)^(1/($D$10*$D$9))-1 -> 0.00012763039 | D15: =(1+D6)^(1/($D$10*$D$9))-1 -> 2.6464612e-05 | E15: =(1+E6)^(1/($D$10*$D$9))-1 -> -2.9749919e-05
B16: ΗΠΑ | C16: =(1+C7)^(1/($D$10*$D$9))-1 -> 0.00015624116 | D16: =(1+D7)^(1/($D$10*$D$9))-1 -> 5.5802522e-05
B18: http://www.naftemporiki.gr/finance/spreads
B19: https://www.investing.com/rates-bonds/
A21: 2 | B21: EURIBOR
B22: 43160

Sheet Εκτίμηση Ομολόγου
A2: XAA | B2: ΔΙΑΔΙΚΑΣΙΑ YΠΟΛΟΓΙΣΜΟΥ ΑΞΙΑΣ ΟΜOΛΟΓΩΝ και ΟΜΟΛΟΓΙΩΝ
B3: [ΖΗΤΟΥΜΕΝΟ Η ΤΙΜΗ ΠΩΛΗΣΗΣ]
H4: ΤΙΜΗ ΟΜΟΛΟΓΙΑΣ (ΥΠΟΘΕΤΟΥΜΕ ΣΤΗΝ ΟΝΟΜΑΣΤΙΚΗ ΑΞΙΑ ΤΗΝ ΗΜΕΡΟΜΗΝΙΑ ΑΓΟΡΑΣ 100%)
B5: V | C5: 1000 | D5: ΤΙΜΗ ΣΤΟ ΑΡΤΙΟ ή ΟΝΟΜΑΣΤΙΚΗ ΑΞΙΑ ΟΜΟΛΟΓΙΑΣ | E5: [Face Value or Par value]
B6: n | C6: 10 | D6: ΧΡΟΝΟΣ ΓΙΑ ΝΑ ΛΗΞΗ | E6: [Life to Maturity] | H6: ΕΠΙΤΟΚΙΟ-ΑΠΟΔΟΣΗ ΤΗΝ ΗΜΕΡΟΜΗΝΙΑ ΑΓΟΡΑΣ ΤΟΥ ΟΜΟΛΟΓΟΥ
B7: nm | C7: =C6*C8 -> 10 | H7: πχ ΕΔΏ 16/5/2018
B8: m | C8: 1 | D8: ΚΑΘΕ ΠΕΡΙΟΔΟΣ (1 ΕΤΟΣ, 2 ΕΞΑΜΗΜΟ, 12 ΜΗΝΕΣ) | E8: [every period] | H8: ΕΠΙΤΟΚΙΟ-ΑΠΟΔΟΣΗ ΤΗΝ ΗΜΕΡΟΜΗΝΙΑ ΑΠΟΤΙΜΗΣΗΣ ΤΟΥ ΟΜΟΛΟΓΟΥ
B9: Ct | C9: =C5*C10 -> 33.51 | D9: ΤΟΚΟΣ ΚΟΥΠΟΝΙΟΥ ΣΤΟ ΧΡΟΝΟ t | E9: [Coupon Interest] | H9: πχ ΕΔΏ 16/5/2019
B10: %C | C10: ='ΟΜΟΛΟΓΑ ΧΑΑ'!C6 -> 0.03351 | D10: ΕΠΙΤΟΚΙΟ ΚΟΥΠΟΝΙΟΥ | E10: [Coupon Rate]
B11: i | C11: ='Forecasts Greece'!C20 -> 0 | D11: ΕΠΙΤΟΚΙΟ ΑΓΟΡΑΣ | E11: [Market Rate]
A13: XAA | B13: Pt | C13: =-PV(C11/C8,C7,C9,C5) -> 1335.1 | D13: ΚΑΘΑΡΗ ΤΙΜΗ ΑΓΟΡΑΣ | E13: [Bond Price]
C14: =C13/C5 -> 1.3351 | D14: =IF(C13<C5,"ΥΠΟ ΤΟ ΑΡΤΙΟ",IF(C13>C5,"ΥΠΕΡ ΤΟ ΑΡΤΙΟ","ΣΤΟ ΑΡΤΙΟ")) -> ΥΠΕΡ ΤΟ ΑΡΤΙΟ
B16: ΑΝΑΛΥΤΙΚΑ
B17: ΠΛΗΡΩΜΕΣ ΠΕΡΙΟΔΟΥ (ΕΤΗΣΙΕΣ)
B18: ΠΑΡΟΥΣΑ ΑΞΙΑ ΤΟΚΟΜΕΡΙΔΙΩΝ
E19: ΠΑΡΟΥΣΑ ΑΞΙΑ ΤΙΜΗΣ ΚΑΤΑ ΤΗΝ ΛΗΞΗ
B20: ΡΟΕΣ | D20: PVIFA(r,n) | E20: ΡΟΕΣ | G20: PVIF(r,n)
B21: =C9 -> 33.51 | C21: x | D21: =PV(C11/C8,C7,-1) -> 10 | E21: =C5 -> 1000 | F21: x | G21: =1/(1+C11/C8)^C7 -> 1
C22: =B21*D21 -> 335.1 | F22: =E21*G21 -> 1000
C24: παρουσα αξια τοκομεριδιων | F24: =C22 -> 335.1
C25: παρουσα αξια τιμης ληξης | F25: =F22 -> 1000
C27: αγοραια τιμη ομολ. | E27: Pt | F27: =F24+F25 -> 1335.1
A28: XAA | C28: πωληση υπο(-), υπερ(+) το αρτιο | F28: =F27/C5 -> 1.3351 | H28: ΤΙΜΗ ΟΜΟΛΟΓΙΑΣ ΤΗΝ ΗΜΕΡΟΜΗΝΙΑ ΑΠΟΤΙΜΗΣΗΣ ΤΟΥ ΟΜΟΛΟΓΟΥ
C29: απόδοση-στη-λήξη | H29: πχ ΕΔΏ 24/5/2019
A33: USA | B33: ΔΙΑΔΙΚΑΣΙΑ YΠΟΛΟΓΙΣΜΟΥ ΑΞΙΑΣ ΟΜOΛΟΓΩΝ και ΟΜΟΛΟΓΙΩΝ
B34: [ΖΗΤΟΥΜΕΝΟ Η ΤΙΜΗ ΠΩΛΗΣΗΣ]
H35: ΤΙΜΗ ΟΜΟΛΟΓΙΑΣ (ΥΠΟΘΕΤΟΥΜΕ ΣΤΗΝ ΟΝΟΜΑΣΤΙΚΗ ΑΞΙΑ ΤΗΝ ΗΜΕΡΟΜΗΝΙΑ ΑΓΟΡΑΣ 100%)
B36: V | C36: 1000 | D36: ΤΙΜΗ ΣΤΟ ΑΡΤΙΟ ή ΟΝΟΜΑΣΤΙΚΗ ΑΞΙΑ ΟΜΟΛΟΓΙΑΣ | E36: [Face Value or Par value]
B37: n | C37: 10 | D37: ΧΡΟΝΟΣ ΓΙΑ ΝΑ ΛΗΞΗ | E37: [Life to Maturity] | H37: ΕΠΙΤΟΚΙΟ-ΑΠΟΔΟΣΗ ΤΗΝ ΗΜΕΡΟΜΗΝΙΑ ΑΓΟΡΑΣ ΤΟΥ ΟΜΟΛΟΓΙΑΣ
B38: nm | C38: =C37*C39 -> 10 | H38: πχ ΕΔΏ 16/5/2018
B39: m | C39: 1 | D39: ΚΑΘΕ ΠΕΡΙΟΔΟΣ (1 ΕΤΟΣ, 2 ΕΞΑΜΗΜΟ, 12 ΜΗΝΕΣ) | E39: [every period] | H39: ΕΠΙΤΟΚΙΟ-ΑΠΟΔΟΣΗ ΤΗΝ ΗΜΕΡΟΜΗΝΙΑ ΑΠΟΤΙΜΗΣΗΣ ΤΟΥ ΟΜΟΛΟΓΟΥ
B40: Ct | C40: =C36*C41 -> 40.98 | D40: ΤΟΚΟΣ ΚΟΥΠΟΝΙΟΥ ΣΤΟ ΧΡΟΝΟ t | E40: [Coupon Interest] | H40: πχ ΕΔΏ 16/5/2019
B41: %C | C41: ='ΟΜΟΛΟΓΑ USA'!C6 -> 0.04098 | D41: ΕΠΙΤΟΚΙΟ ΚΟΥΠΟΝΙΟΥ | E41: [Coupon Rate]
B42: i | C42: ='Forecasts USA'!C20 -> 0 | D42: ΕΠΙΤΟΚΙΟ ΑΓΟΡΑΣ | E42: [Market Rate]
A44: USA | B44: Pt | C44: =-PV(C42/C39,C38,C40,C36) -> 1409.8 | D44: ΚΑΘΑΡΗ ΤΙΜΗ ΑΓΟΡΑΣ | E44: [Bond Price]
C45: =C44/C36 -> 1.4098 | D45: =IF(C44<C36,"ΥΠΟ ΤΟ ΑΡΤΙΟ",IF(C44>C36,"ΥΠΕΡ ΤΟ ΑΡΤΙΟ","ΣΤΟ ΑΡΤΙΟ")) -> ΥΠΕΡ ΤΟ ΑΡΤΙΟ
B47: ΑΝΑΛΥΤΙΚΑ
B48: ΠΛΗΡΩΜΕΣ ΠΕΡΙΟΔΟΥ (ΕΤΗΣΙΕΣ)
B49: ΠΑΡΟΥΣΑ ΑΞΙΑ ΤΟΚΟΜΕΡΙΔΙΩΝ
E50: ΠΑΡΟΥΣΑ ΑΞΙΑ ΤΙΜΗΣ ΚΑΤΑ ΤΗΝ ΛΗΞΗ
B51: ΡΟΕΣ | D51: PVIFA(r,n) | E51: ΡΟΕΣ | G51: PVIF(r,n)
B52: =C40 -> 40.98 | C52: x | D52: =PV(C42/C39,C38,-1) -> 10 | E52: =C36 -> 1000 | F52: x | G52: =1/(1+C42/C39)^C38 -> 1
C53: =B52*D52 -> 409.8 | F53: =E52*G52 -> 1000
C55: παρουσα αξια τοκομεριδιων | F55: =C53 -> 409.8
C56: παρουσα αξια τιμης ληξης | F56: =F53 -> 1000
C58: αγοραια τιμη ομολ. | E58: Pt | F58: =F55+F56 -> 1409.8
A59: USA | C59: πωληση υπο(-), υπερ(+) το αρτιο | F59: =F58/C36 -> 1.4098 | H59: ΤΙΜΗ ΟΜΟΛΟΓΙΑΣ ΤΗΝ ΗΜΕΡΟΜΗΝΙΑ ΑΠΟΤΙΜΗΣΗΣ ΤΟΥ ΟΜΟΛΟΓΟΥ
C60: απόδοση-στη-λήξη | H60: πχ ΕΔΏ 24/5/2019

Sheet ΧΑΑ
C1: ATG | K1: OPAr | S1: AGNr | AA1: ACBr | AI1: HRMr | AQ1: MTLNr | AY1: EURBr
A2: Ημ/νία | B2: Τελευταία | C2: Άνοιγμα | D2: Υψηλό | E2: Χαμηλό | F2: Όγκος | G2: Αλλ.% | I2: Ημ/νία | J2: Τελευταία | K2: Άνοιγμα | L2: Υψηλό | M2: Χαμηλό | N2: Όγκος | O2: Αλλ.% | Q2: Ημ/νία | R2: Τελευταία | S2: Άνοιγμα | T2: Υψηλό | U2: Χαμηλό | V2: Όγκος | W2: Αλλ.% | Y2: Ημ/νία | Z2: Τελευταία | AA2: Άνοιγμα | AB2: Υψηλό | AC2: Χαμηλό | AD2: Όγκος | AE2: Αλλ.% | AG2: Ημ/νία | AH2: Τελευταία | AI2: Άνοιγμα | AJ2: Υψηλό | AK2: Χαμηλό | AL2: Όγκος | AM2: Αλλ.% | AO2: Ημ/νία | AP2: Τελευταία | AQ2: Άνοιγμα | AR2: Υψηλό | AS2: Χαμηλό | AT2: Όγκος | AU2: Αλλ.% | AW2: Ημ/νία | AX2: Τελευταία | AY2: Άνοιγμα | AZ2: Υψηλό | BA2: Χαμηλό | BB2: Όγκος | BC2: Αλλ.%
A3: 23.10.2024 | B3: 1407.14 | C3: 1418.39 | D3: 1419.95 | E3: 1405.39 | F3: 30,90M | G3: -0.0053 | I3: 23.10.2024 | J3: 15.76 | K3: 15.92 | L3: 15.95 | M3: 15.76 | N3: 305,19K | O3: -0.0044 | Q3: 23.10.2024 | R3: 10.34 | S3: 10.42 | T3: 10.42 | U3: 10.26 | V3: 46,27K | W3: 0.0039 | Y3: 23.10.2024 | Z3: 1.438 | AA3: 1.475 | AB3: 1.478 | AC3: 1.431 | AD3: 9,14M | AE3: -0.0191 | AG3: 22.10.2025 | AH3: 22.84 | AI3: 22.72 | AJ3: 22.96 | AK3: 22.64 | AL3: 113,10K | AM3: 0.0053 | AO3: 23.10.2024 | AP3: 32.9 | AQ3: 33.4 | AR3: 33.52 | AS3: 32.84 | AT3: 217,93K | AU3: -0.0108 | AW3: 23.10.2024 | AX3: 1.8905 | AY3: 1.958 | AZ3: 1.958 | BA3: 1.881 | BB3: 11,21M | BC3: -0.0305
A4: 24.10.2024 | B4: 1402.6 | C4: 1406.09 | D4: 1415.71 | E4: 1398.58 | F4: 30,38M | G4: -0.0032 | I4: 24.10.2024 | J4: 15.73 | K4: 15.76 | L4: 15.87 | M4: 15.72 | N4: 291,30K | O4: -0.0019 | Q4: 24.10.2024 | R4: 10.4 | S4: 10.25 | T4: 10.44 | U4: 10.25 | V4: 35,96K | W4: 0.0058 | Y4: 24.10.2024 | Z4: 1.413 | AA4: 1.438 | AB4: 1.447 | AC4: 1.412 | AD4: 6,74M | AE4: -0.017 | AG4: 21.10.2025 | AH4: 22.72 | AI4: 22.8 | AJ4: 22.92 | AK4: 22.5 | AL4: 100,18K | AM4: -0.0035 | AO4: 24.10.2024 | AP4: 33.26 | AQ4: 32.84 | AR4: 33.32 | AS4: 32.84 | AT4: 136,10K | AU4: 0.0109 | AW4: 24.10.2024 | AX4: 1.9 | AY4: 1.89 | AZ4: 1.9065 | BA4: 1.861 | BB4: 8,56M | BC4: 0.005
A5: 25.10.2024 | B5: 1390.25 | C5: 1401.71 | D5: 1404.54 | E5: 1387.42 | F5: 27,93M | G5: -0.0088 | I5: 25.10.2024 | J5: 15.67 | K5: 15.77 | L5: 15.85 | M5: 15.6 | N5: 575,33K | O5: -0.0038 | Q5: 25.10.2024 | R5: 10.15 | S5: 10.27 | T5: 10.44 | U5: 10.15 | V5: 24,20K | W5: -0.024 | Y5: 25.10.2024 | Z5: 1.401 | AA5: 1.411 | AB5: 1.421 | AC5: 1.391 | AD5: 6,01M | AE5: -0.0092 | AG5: 20.10.2025 | AH5: 22.8 | AI5: 22.8 | AJ5: 23.04 | AK5: 22.5 | AL5: 83,05K | AM5: 0 | AO5: 25.10.2024 | AP5: 32.3 | AQ5: 33.26 | AR5: 33.3 | AS5: 32.3 | AT5: 224,18K | AU5: -0.0289 | AW5: 25.10.2024 | AX5: 1.88 | AY5: 1.9 | AZ5: 1.9 | BA5: 1.845 | BB5: 5,63M | BC5: -0.0105
A6: 29.10.2024 | B6: 1401.18 | C6: 1397.45 | D6: 1409.71 | E6: 1397.45 | F6: 51,64M | G6: 0.0079 | I6: 29.10.2024 | J6: 15.78 | K6: 15.88 | L6: 15.9 | M6: 15.67 | N6: 387,31K | O6: 0.007 | Q6: 29.10.2024 | R6: 10.13 | S6: 10.26 | T6: 10.3 | U6: 10.1 | V6: 55,59K | W6: -0.002 | Y6: 29.10.2024 | Z6: 1.422 | AA6: 1.425 | AB6: 1.443 | AC6: 1.413 | AD6: 26,92M | AE6: 0.0154 | AG6: 17.10.2025 | AH6: 22.8 | AI6: 23.08 | AJ6: 23.08 | AK6: 22.24 | AL6: 349,02K | AM6: -0.013 | AO6: 29.10.2024 | AP6: 32.4 | AQ6: 32.68 | AR6: 33.12 | AS6: 32.38 | AT6: 190,93K | AU6: 0.0031 | AW6: 29.10.2024 | AX6: 1.928 | AY6: 1.89 | AZ6: 1.9295 | BA6: 1.89 | BB6: 6,40M | BC6: 0.0255
A7: 30.10.2024 | B7: 1381.83 | C7: 1402.33 | D7: 1402.77 | E7: 1377.23 | F7: 31,21M | G7: -0.0138 | I7: 30.10.2024 | J7: 15.52 | K7: 15.78 | L7: 15.83 | M7: 15.52 | N7: 290,37K | O7: -0.0165 | Q7: 30.10.2024 | R7: 9.93 | S7: 10.11 | T7: 10.2 | U7: 9.9 | V7: 74,26K | W7: -0.0197 | Y7: 30.10.2024 | Z7: 1.37 | AA7: 1.42 | AB7: 1.434 | AC7: 1.37 | AD7: 7,38M | AE7: -0.0366 | AG7: 16.10.2025 | AH7: 23.1 | AI7: 23.42 | AJ7: 23.42 | AK7: 22.64 | AL7: 196,70K | AM7: -0.0137 | AO7: 30.10.2024 | AP7: 32.8 | AQ7: 32.4 | AR7: 32.8 | AS7: 31.84 | AT7: 347,25K | AU7: 0.0123 | AW7: 30.10.2024 | AX7: 1.901 | AY7: 1.936 | AZ7: 1.9385 | BA7: 1.871 | BB7: 8,64M | BC7: -0.014
A8: 31.10.2024 | B8: 1382.68 | C8: 1382.09 | D8: 1392.41 | E8: 1378.36 | F8: 32,63M | G8: 0.0006 | I8: 31.10.2024 | J8: 15.68 | K8: 15.6 | L8: 15.84 | M8: 15.6 | N8: 457,05K | O8: 0.0103 | Q8: 31.10.2024 | R8: 9.97 | S8: 9.93 | T8: 10 | U8: 9.9 | V8: 60,12K | W8: 0.0035 | Y8: 31.10.2024 | Z8: 1.38 | AA8: 1.375 | AB8: 1.398 | AC8: 1.367 | AD8: 6,70M | AE8: 0.0069 | AG8: 15.10.2025 | AH8: 23.42 | AI8: 23.5 | AJ8: 23.52 | AK8: 23.26 | AL8: 198,08K | AM8: 0.0009 | AO8: 31.10.2024 | AP8: 32.06 | AQ8: 32.42 | AR8: 32.8 | AS8: 32.06 | AT8: 299,04K | AU8: -0.0226 | AW8: 31.10.2024 | AX8: 1.89 | AY8: 1.9 | AZ8: 1.9175 | BA8: 1.8775 | BB8: 7,17M | BC8: -0.0058
A9: 01.11.2024 | B9: 1390.49 | C9: 1383.89 | D9: 1396 | E9: 1383.89 | F9: 27,55M | G9: 0.0056 | I9: 01.11.2024 | J9: 15.69 | K9: 15.75 | L9: 15.81 | M9: 15.68 | N9: 380,56K | O9: 0.0006 | Q9: 01.11.2024 | R9: 9.9 | S9: 9.93 | T9: 10.1 | U9: 9.9 | V9: 28,59K | W9: -0.0065 | Y9: 01.11.2024 | Z9: 1.401 | AA9: 1.39 | AB9: 1.422 | AC9: 1.39 | AD9: 5,53M | AE9: 0.0152 | AG9: 14.10.2025 | AH9: 23.4 | AI9: 23.36 | AJ9: 23.44 | AK9: 23.12 | AL9: 145,35K | AM9: 0.0017 | AO9: 01.11.2024 | AP9: 32.04 | AQ9: 32.4 | AR9: 32.44 | AS9: 32.04 | AT9: 159,98K | AU9: -0.0006 | AW9: 01.11.2024 | AX9: 1.919 | AY9: 1.882 | AZ9: 1.9285 | BA9: 1.882 | BB9: 6,21M | BC9: 0.0153 | BF9: =AZ9+AZ8 -> 3.846
A10: 04.11.2024 | B10: 1390.65 | C10: 1386.72 | D10: 1392.09 | E10: 1385.63 | F10: 15,31M | G10: 0.0001 | I10: 04.11.2024 | J10: 15.25 | K10: 15.35 | L10: 15.35 | M10: 15.19 | N10: 270,60K | O10: -0.028 | Q10: 04.11.2024 | R10: 9.76 | S10: 9.9 | T10: 10.08 | U10: 9.73 | V10: 47,64K | W10: -0.0146 | Y10: 04.11.2024 | Z10: 1.401 | AA10: 1.401 | AB10: 1.414 | AC10: 1.392 | AD10: 2,30M | AE10: 0 | AG10: 13.10.2025 | AH10: 23.36 | AI10: 22.72 | AJ10: 23.6 | AK10: 22.72 | AL10: 283,42K | AM10: 0.0165 | AO10: 04.11.2024 | AP10: 31.94 | AQ10: 32 | AR10: 32.2 | AS10: 31.62 | AT10: 191,73K | AU10: -0.0031 | AW10: 04.11.2024 | AX10: 1.94 | AY10: 1.8915 | AZ10: 1.948 | BA10: 1.8915 | BB10: 4,15M | BC10: 0.0109
A11: 05.11.2024 | B11: 1399.66 | C11: 1391.86 | D11: 1399.73 | E11: 1391.66 | F11: 29,20M | G11: 0.0065 | I11: 05.11.2024 | J11: 15.28 | K11: 15.25 | L11: 15.31 | M11: 15.1 | N11: 251,11K | O11: 0.002 | Q11: 05.11.2024 | R11: 9.8 | S11: 9.72 | T11: 9.86 | U11: 9.7 | V11: 21,50K | W11: 0.0046 | Y11: 05.11.2024 | Z11: 1.414 | AA11: 1.401 | AB11: 1.433 | AC11: 1.401 | AD11: 4,40M | AE11: 0.0096 | AG11: 10.10.2025 | AH11: 22.98 | AI11: 23 | AJ11: 23.02 | AK11: 22.8 | AL11: 132,96K | AM11: 0.0017 | AO11: 05.11.2024 | AP11: 32.1 | AQ11: 32 | AR11: 32.34 | AS11: 31.92 | AT11: 151,45K | AU11: 0.005 | AW11: 05.11.2024 | AX11: 1.97 | AY11: 1.948 | AZ11: 1.97 | BA11: 1.9405 | BB11: 3,80M | BC11: 0.0155
A12: 06.11.2024 | B12: 1408.57 | C12: 1412.85 | D12: 1424.79 | E12: 1406.12 | F12: 34,61M | G12: 0.0064 | I12: 06.11.2024 | J12: 15.1 | K12: 15.34 | L12: 15.39 | M12: 15.1 | N12: 247,89K | O12: -0.0118 | Q12: 06.11.2024 | R12: 9.79 | S12: 9.8 | T12: 10 | U12: 9.79 | V12: 39,49K | W12: -0.001 | Y12: 06.11.2024 | Z12: 1.431 | AA12: 1.45 | AB12: 1.465 | AC12: 1.431 | AD12: 9,22M | AE12: 0.0117 | AG12: 09.10.2025 | AH12: 22.94 | AI12: 22.68 | AJ12: 23.06 | AK12: 22.52 | AL12: 138,94K | AM12: 0.0187 | AO12: 06.11.2024 | AP12: 32.2 | AQ12: 32.56 | AR12: 32.64 | AS12: 32.2 | AT12: 205,99K | AU12: 0.0031 | AW12: 06.11.2024 | AX12: 1.9915 | AY12: 2 | AZ12: 2.038 | BA12: 1.991 | BB12: 5,32M | BC12: 0.0109
A13: 07.11.2024 | B13: 1408.5 | C13: 1408.79 | D13: 1412.73 | E13: 1404.77 | F13: 19,72M | G13: 0 | I13: 07.11.2024 | J13: 15.1 | K13: 15.1 | L13: 15.2 | M13: 15.02 | N13: 589,82K | O13: 0 | Q13: 07.11.2024 | R13: 9.8 | S13: 9.73 | T13: 9.85 | U13: 9.73 | V13: 21,81K | W13: 0.001 | Y13: 07.11.2024 | Z13: 1.426 | AA13: 1.431 | AB13: 1.447 | AC13: 1.423 | AD13: 3,14M | AE13: -0.0038 | AG13: 08.10.2025 | AH13: 22.52 | AI13: 22.48 | AJ13: 22.62 | AK13: 22.14 | AL13: 149,72K | AM13: 0.0018 | AO13: 07.11.2024 | AP13: 32.1 | AQ13: 32.32 | AR13: 32.4 | AS13: 31.96 | AT13: 130,47K | AU13: -0.0031 | AW13: 07.11.2024 | AX13: 1.988 | AY13: 1.987 | AZ13: 2.02 | BA13: 1.984 | BB13: 3,18M | BC13: -0.0018
A14: 08.11.2024 | B14: 1413.13 | C14: 1408.42 | D14: 1415.83 | E14: 1408.42 | F14: 43,10M | G14: 0.0033 | I14: 08.11.2024 | J14: 15.06 | K14: 15.1 | L14: 15.11 | M14: 15 | N14: 206,39K | O14: -0.0026 | Q14: 08.11.2024 | R14: 9.85 | S14: 9.7 | T14: 9.87 | U14: 9.67 | V14: 43,93K | W14: 0.0046 | Y14: 08.11.2024 | Z14: 1.502 | AA14: 1.426 | AB14: 1.505 | AC14: 1.426 | AD14: 14,66M | AE14: 0.0537 | AG14: 07.10.2025 | AH14: 22.48 | AI14: 22.26 | AJ14: 22.48 | AK14: 21.66 | AL14: 86,10K | AM14: 0.0172 | AO14: 08.11.2024 | AP14: 32.58 | AQ14: 32.1 | AR14: 32.88 | AS14: 31.96 | AT14: 117,96K | AU14: 0.015 | AW14: 08.11.2024 | AX14: 2.045 | AY14: 2.01 | AZ14: 2.05 | BA14: 2.01 | BB14: 13,70M | BC14: 0.0287
A15: 11.11.2024 | B15: 1428.4 | C15: 1415.42 | D15: 1428.4 | E15: 1415.42 | F15: 37,97M | G15: 0.0108 | I15: 11.11.2024 | J15: 15.13 | K15: 15.06 | L15: 15.24 | M15: 15.06 | N15: 430,45K | O15: 0.0046 | Q15: 11.11.2024 | R15: 10.02 | S15: 9.85 | T15: 10.09 | U15: 9.85 | V15: 60,50K | W15: 0.0178 | Y15: 11.11.2024 | Z15: 1.574 | AA15: 1.51 | AB15: 1.578 | AC15: 1.505 | AD15: 14,05M | AE15: 0.0476 | AG15: 06.10.2025 | AH15: 22.1 | AI15: 22.6 | AJ15: 22.7 | AK15: 22.08 | AL15: 100,63K | AM15: -0.0221 | AO15: 11.11.2024 | AP15: 33.22 | AQ15: 32.5 | AR15: 33.26 | AS15: 32.42 | AT15: 223,14K | AU15: 0.0196 | AW15: 11.11.2024 | AX15: 2.035 | AY15: 2.041 | AZ15: 2.06 | BA15: 2.029 | BB15: 12,31M | BC15: -0.0049
A16: 12.11.2024 | B16: 1430.91 | C16: 1426.18 | D16: 1434.28 | E16: 1422.02 | F16: 38,16M | G16: 0.0018 | I16: 12.11.2024 | J16: 15.1 | K16: 15.1 | L16: 15.15 | M16: 15.07 | N16: 656,06K | O16: -0.002 | Q16: 12.11.2024 | R16: 9.9 | S16: 10 | T16: 10.06 | U16: 9.9 | V16: 43,10K | W16: -0.012 | Y16: 12.11.2024 | Z16: 1.62 | AA16: 1.566 | AB16: 1.623 | AC16: 1.562 | AD16: 16,81M | AE16: 0.0292 | AG16: 03.10.2025 | AH16: 22.6 | AI16: 22.68 | AJ16: 22.72 | AK16: 22.4 | AL16: 113,99K | AM16: 0.008 | AO16: 12.11.2024 | AP16: 33 | AQ16: 33.2 | AR16: 33.2 | AS16: 32.82 | AT16: 132,86K | AU16: -0.0066 | AW16: 12.11.2024 | AX16: 2.034 | AY16: 2.03 | AZ16: 2.045 | BA16: 2.02 | BB16: 5,09M | BC16: -0.0005
A17: 13.11.2024 | B17: 1419.51 | C17: 1428.39 | D17: 1430.83 | E17: 1414.99 | F17: 36,87M | G17: -0.008 | I17: 13.11.2024 | J17: 15 | K17: 15.1 | L17: 15.15 | M17: 14.97 | N17: 532,19K | O17: -0.0066 | Q17: 13.11.2024 | R17: 9.8 | S17: 9.9 | T17: 9.91 | U17: 9.78 | V17: 24,49K | W17: -0.0101 | Y17: 13.11.2024 | Z17: 1.605 | AA17: 1.595 | AB17: 1.627 | AC17: 1.583 | AD17: 16,07M | AE17: -0.0093 | AG17: 02.10.2025 | AH17: 22.42 | AI17: 22.78 | AJ17: 22.78 | AK17: 22.18 | AL17: 98,51K | AM17: -0.008 | AO17: 13.11.2024 | AP17: 32.98 | AQ17: 33 | AR17: 33.04 | AS17: 32.5 | AT17: 139,09K | AU17: -0.0006 | AW17: 13.11.2024 | AX17: 2 | AY17: 2.018 | AZ17: 2.03 | BA17: 1.99 | BB17: 5,49M | BC17: -0.0167
A18: 14.11.2024 | B18: 1417.5 | C18: 1419.39 | D18: 1421 | E18: 1414.47 | F18: 32,76M | G18: -0.0014 | I18: 14.11.2024 | J18: 15.09 | K18: 15.07 | L18: 15.31 | M18: 14.98 | N18: 641,00K | O18: 0.006 | Q18: 14.11.2024 | R18: 9.85 | S18: 9.8 | T18: 9.92 | U18: 9.8 | V18: 22,16K | W18: 0.0051 | Y18: 14.11.2024 | Z18: 1.607 | AA18: 1.605 | AB18: 1.618 | AC18: 1.588 | AD18: 7,44M | AE18: 0.0012 | AG18: 01.10.2025 | AH18: 22.6 | AI18: 22.5 | AJ18: 22.64 | AK18: 22.34 | AL18: 89,13K | AM18: 0.0116 | AO18: 14.11.2024 | AP18: 33.2 | AQ18: 33.16 | AR18: 33.2 | AS18: 32.6 | AT18: 178,24K | AU18: 0.0067 | AW18: 14.11.2024 | AX18: 1.9715 | AY18: 2 | AZ18: 2.02 | BA18: 1.964 | BB18: 12,18M | BC18: -0.0142
A19: 15.11.2024 | B19: 1403.87 | C19: 1414.59 | D19: 1414.59 | E19: 1403.23 | F19: 33,59M | G19: -0.0096 | I19: 15.11.2024 | J19: 15.14 | K19: 15 | L19: 15.14 | M19: 14.92 | N19: 348,81K | O19: 0.0033 | Q19: 15.11.2024 | R19: 9.69 | S19: 9.9 | T19: 9.9 | U19: 9.6 | V19: 107,83K | W19: -0.0162 | Y19: 15.11.2024 | Z19: 1.579 | AA19: 1.584 | AB19: 1.6 | AC19: 1.561 | AD19: 7,31M | AE19: -0.0171 | AG19: 30.09.2025 | AH19: 22.34 | AI19: 22.8 | AJ19: 22.92 | AK19: 22.16 | AL19: 123,30K | AM19: -0.021 | AO19: 15.11.2024 | AP19: 33 | AQ19: 32.82 | AR19: 33.12 | AS19: 32.76 | AT19: 116,89K | AU19: -0.006 | AW19: 15.11.2024 | AX19: 1.97 | AY19: 1.97 | AZ19: 1.98 | BA19: 1.9545 | BB19: 13,91M | BC19: -0.0008
A20: 18.11.2024 | B20: 1392.44 | C20: 1399.93 | D20: 1401.06 | E20: 1381.7 | F20: 29,34M | G20: -0.0081 | I20: 18.11.2024 | J20: 14.98 | K20: 15.14 | L20: 15.14 | M20: 14.91 | N20: 214,43K | O20: -0.0106 | Q20: 18.11.2024 | R20: 9.53 | S20: 9.6 | T20: 9.6 | U20: 9.43 | V20: 82,73K | W20: -0.0165 | Y20: 18.11.2024 | Z20: 1.564 | AA20: 1.564 | AB20: 1.569 | AC20: 1.52 | AD20: 8,20M | AE20: -0.0095 | AG20: 29.09.2025 | AH20: 22.82 | AI20: 22.5 | AJ20: 23.06 | AK20: 22.4 | AL20: 134,68K | AM20: 0.0133 | AO20: 18.11.2024 | AP20: 32.32 | AQ20: 32.64 | AR20: 32.66 | AS20: 32.14 | AT20: 123,55K | AU20: -0.0206 | AW20: 18.11.2024 | AX20: 2.006 | AY20: 1.97 | AZ20: 2.006 | BA20: 1.925 | BB20: 6,90M | BC20: 0.0183
A21: 19.11.2024 | B21: 1366.72 | C21: 1392.5 | D21: 1397.53 | E21: 1359.95 | F21: 35,36M | G21: -0.0185 | I21: 19.11.2024 | J21: 14.85 | K21: 15.07 | L21: 15.07 | M21: 14.67 | N21: 395,59K | O21: -0.0087 | Q21: 19.11.2024 | R21: 9.23 | S21: 9.5 | T21: 9.59 | U21: 9.07 | V21: 129,38K | W21: -0.032 | Y21: 19.11.2024 | Z21: 1.537 | AA21: 1.577 | AB21: 1.577 | AC21: 1.495 | AD21: 9,09M | AE21: -0.0173 | AG21: 26.09.2025 | AH21: 22.52 | AI21: 22.3 | AJ21: 22.62 | AK21: 22.06 | AL21: 58,95K | AM21: 0.0099 | AO21: 19.11.2024 | AP21: 30.74 | AQ21: 32.2 | AR21: 32.42 | AS21: 30.7 | AT21: 360,42K | AU21: -0.0489 | AW21: 19.11.2024 | AX21: 1.977 | AY21: 2 | AZ21: 2.009 | BA21: 1.9535 | BB21: 6,56M | BC21: -0.0145
... A247: 17.10.2025 | B247: 1987.52 | C247: 1988.99 | D247: 1990.37 | E247: 1948.59 | F247: 69,29M | G247: -0.013 | I247: 17.10.2025 | J247: 17.97 | K247: 17.55 | L247: 18.03 | M247: 17.33 | N247: 2,43M | O247: 0.0164 | Q247: 17.10.2025 | R247: 13.24 | S247: 13.18 | T247: 13.32 | U247: 12.92 | V247: 216,12K | W247: -0.0105 | Y247: 22.10.2025 | Z247: 3.526 | AA247: 3.462 | AB247: 3.568 | AC247: 3.46 | AD247: 8,72M | AE247: 0.0176 | AG247: 29.10.2024 | AH247: 17.46 | AI247: 17.48 | AJ247: 17.62 | AK247: 17.46 | AL247: 71,74K | AM247: -0.0011 | AO247: 17.10.2025 | AP247: 42.56 | AQ247: 41.96 | AR247: 42.82 | AS247: 41.24 | AT247: 560,05K | AU247: -0.0019 | AW247: 17.10.2025 | AX247: 3.401 | AY247: 3.4 | AZ247: 3.417 | BA247: 3.304 | BB247: 14,05M | BC247: -0.0283
A248: 20.10.2025 | B248: 1996.23 | C248: 2009.67 | D248: 2023.26 | E248: 1989.91 | F248: 44,45M | G248: 0.0044 | I248: 20.10.2025 | J248: 18.06 | K248: 17.97 | L248: 18.22 | M248: 17.95 | N248: 747,53K | O248: 0.005 | Q248: 20.10.2025 | R248: 13.34 | S248: 13.24 | T248: 13.44 | U248: 13.2 | V248: 66,10K | W248: 0.0076 | AG248: 25.10.2024 | AH248: 17.48 | AI248: 17.44 | AJ248: 17.58 | AK248: 17.24 | AL248: 71,33K | AM248: -0.0011 | AO248: 20.10.2025 | AP248: 41.9 | AQ248: 43.02 | AR248: 43.18 | AS248: 41.4 | AT248: 403,05K | AU248: -0.0155 | AW248: 20.10.2025 | AX248: 3.39 | AY248: 3.45 | AZ248: 3.497 | BA248: 3.347 | BB248: 9,81M | BC248: -0.0032
A249: 21.10.2025 | B249: 2019.25 | C249: 1994.55 | D249: 2028.15 | E249: 1991.87 | F249: 36,28M | G249: 0.0115 | I249: 21.10.2025 | J249: 18.14 | K249: 18.03 | L249: 18.4 | M249: 18.03 | N249: 1,04M | O249: 0.0044 | Q249: 21.10.2025 | R249: 13.46 | S249: 13.36 | T249: 13.5 | U249: 13.28 | V249: 112,55K | W249: 0.009 | AG249: 24.10.2024 | AH249: 17.5 | AI249: 17.36 | AJ249: 17.52 | AK249: 17.24 | AL249: 50,40K | AM249: 0.0081 | AO249: 21.10.2025 | AP249: 42.84 | AQ249: 41.98 | AR249: 43.3 | AS249: 41.7 | AT249: 319,65K | AU249: 0.0224 | AW249: 21.10.2025 | AX249: 3.426 | AY249: 3.399 | AZ249: 3.461 | BA249: 3.39 | BB249: 5,36M | BC249: 0.0106
A250: 22.10.2025 | B250: 2033.97 | C250: 2026.38 | D250: 2038.14 | E250: 2021.2 | F250: 30,27M | G250: 0.0073 | I250: 22.10.2025 | J250: 18.42 | K250: 18.5 | L250: 18.71 | M250: 18.22 | N250: 870,67K | O250: 0.0154 | Q250: 22.10.2025 | R250: 13.52 | S250: 13.46 | T250: 13.58 | U250: 13.36 | V250: 79,62K | W250: 0.0045 | AG250: 23.10.2024 | AH250: 17.36 | AI250: 17.46 | AJ250: 17.46 | AK250: 17.16 | AL250: 47,08K | AM250: -0.0046 | AO250: 22.10.2025 | AP250: 44.04 | AQ250: 43.42 | AR250: 44.26 | AS250: 43.2 | AT250: 315,25K | AU250: 0.028 | AW250: 22.10.2025 | AX250: 3.463 | AY250: 3.475 | AZ250: 3.488 | BA250: 3.436 | BB250: 3,99M | BC250: 0.0108

Sheet Αμοιβαία

Sheet NYSE
C1: DOW JONES | K1: V | S1: JNJ | AA1: KO
A2: Ημ/νία | B2: Τελευταία | C2: Άνοιγμα | D2: Υψηλό | E2: Χαμηλό | F2: Όγκος | G2: Αλλ.% | I2: Ημ/νία | J2: Τελευταία | K2: Άνοιγμα | L2: Υψηλό | M2: Χαμηλό | N2: Όγκος | O2: Αλλ.% | Q2: Ημ/νία | R2: Τελευταία | S2: Άνοιγμα | T2: Υψηλό | U2: Χαμηλό | V2: Όγκος | W2: Αλλ.% | Y2: Ημ/νία | Z2: Τελευταία | AA2: Άνοιγμα | AB2: Υψηλό | AC2: Χαμηλό | AD2: Όγκος | AE2: Αλλ.%
A3: 23.10.2024 | B3: 42514.95 | C3: 42834.4 | D3: 42834.4 | E3: 42293.17 | F3: 356,62M | G3: -0.0096 | I3: 23.10.2024 | J3: 283.76 | K3: 286.04 | L3: 286.05 | M3: 283.53 | N3: 5,25M | O3: -0.0036 | Q3: 23.10.2024 | R3: 165.86 | S3: 162.82 | T3: 166 | U3: 162.42 | V3: 7,44M | W3: 0.0147 | Y3: 23.10.2024 | Z3: 68.01 | AA3: 66.99 | AB3: 68.7 | AC3: 66.58 | AD3: 24,66M | AE3: -0.0207
A4: 24.10.2024 | B4: 42374.36 | C4: 42522.55 | D4: 42522.55 | E4: 42191.83 | F4: 282,68M | G4: -0.0033 | I4: 24.10.2024 | J4: 283.22 | K4: 282.39 | L4: 283.62 | M4: 281.73 | N4: 4,68M | O4: -0.0019 | Q4: 24.10.2024 | R4: 163.67 | S4: 165 | T4: 165.51 | U4: 163.34 | V4: 5,39M | W4: -0.0132 | Y4: 24.10.2024 | Z4: 67.3 | AA4: 67.65 | AB4: 68.04 | AC4: 66.95 | AD4: 17,57M | AE4: -0.0104
A5: 25.10.2024 | B5: 42114.4 | C5: 42477.51 | D5: 42594.64 | E5: 42051.39 | F5: 314,00M | G5: -0.0061 | I5: 25.10.2024 | J5: 281.73 | K5: 284 | L5: 285.09 | M5: 280.78 | N5: 4,46M | O5: -0.0053 | Q5: 25.10.2024 | R5: 160.88 | S5: 163.68 | T5: 163.92 | U5: 160.61 | V5: 6,40M | W5: -0.017 | Y5: 25.10.2024 | Z5: 66.92 | AA5: 67.07 | AB5: 67.7 | AC5: 66.79 | AD5: 11,14M | AE5: -0.0056
A6: 28.10.2024 | B6: 42387.57 | C6: 42264.54 | D6: 42476.46 | E6: 42264.54 | F6: 284,78M | G6: 0.0065 | I6: 28.10.2024 | J6: 284.19 | K6: 282.04 | L6: 284.64 | M6: 281.53 | N6: 4,31M | O6: 0.0087 | Q6: 28.10.2024 | R6: 161.6 | S6: 161.13 | T6: 161.97 | U6: 161 | V6: 4,84M | W6: 0.0045 | Y6: 28.10.2024 | Z6: 66.67 | AA6: 66.96 | AB6: 67.39 | AC6: 66.6 | AD6: 10,76M | AE6: -0.0037
A7: 29.10.2024 | B7: 42233.05 | C7: 42323.48 | D7: 42491.86 | E7: 42171.65 | F7: 373,55M | G7: -0.0036 | I7: 29.10.2024 | J7: 281.88 | K7: 284.27 | L7: 285.7 | M7: 281.35 | N7: 7,53M | O7: -0.0081 | Q7: 29.10.2024 | R7: 160.09 | S7: 161.46 | T7: 162.17 | U7: 160.06 | V7: 5,22M | W7: -0.0093 | Y7: 29.10.2024 | Z7: 65.56 | AA7: 66.29 | AB7: 66.34 | AC7: 65.52 | AD7: 16,53M | AE7: -0.0166
A8: 30.10.2024 | B8: 42141.54 | C8: 42249.81 | D8: 42457.92 | E8: 42141.54 | F8: 377,43M | G8: -0.0022 | I8: 30.10.2024 | J8: 290.16 | K8: 292.34 | L8: 295.78 | M8: 288.33 | N8: 9,61M | O8: 0.0294 | Q8: 30.10.2024 | R8: 160.61 | S8: 159.45 | T8: 161.28 | U8: 159.03 | V8: 5,82M | W8: 0.0032 | Y8: 30.10.2024 | Z8: 65.92 | AA8: 65.51 | AB8: 66.54 | AC8: 65.32 | AD8: 14,18M | AE8: 0.0055
A9: 31.10.2024 | B9: 41763.46 | C9: 41956.34 | D9: 41991.91 | E9: 41704.63 | F9: 523,87M | G9: -0.009 | I9: 31.10.2024 | J9: 289.85 | K9: 292.09 | L9: 296.34 | M9: 289.62 | N9: 7,95M | O9: -0.0011 | Q9: 31.10.2024 | R9: 159.86 | S9: 159.99 | T9: 160.87 | U9: 159.46 | V9: 8,61M | W9: -0.0047 | Y9: 31.10.2024 | Z9: 65.31 | AA9: 65.81 | AB9: 65.99 | AC9: 65.25 | AD9: 13,38M | AE9: -0.0093
A10: 01.11.2024 | B10: 42052.19 | C10: 41869.82 | D10: 42326.31 | E10: 41869.82 | F10: 531,36M | G10: 0.0069 | I10: 01.11.2024 | J10: 290.74 | K10: 288.49 | L10: 292.67 | M10: 287.19 | N10: 5,47M | O10: 0.0031 | Q10: 01.11.2024 | R10: 160.13 | S10: 160.58 | T10: 161.06 | U10: 159.88 | V10: 5,26M | W10: 0.0017 | Y10: 01.11.2024 | Z10: 65.01 | AA10: 65.47 | AB10: 65.66 | AC10: 64.89 | AD10: 12,16M | AE10: -0.0046
A11: 04.11.2024 | B11: 41794.6 | C11: 42004.66 | D11: 42035.87 | E11: 41647.3 | F11: 341,51M | G11: -0.0061 | I11: 04.11.2024 | J11: 291.85 | K11: 291.55 | L11: 293.15 | M11: 290.76 | N11: 4,28M | O11: 0.0038 | Q11: 04.11.2024 | R11: 158.24 | S11: 159.7 | T11: 160.28 | U11: 158.07 | V11: 4,64M | W11: -0.0118 | Y11: 04.11.2024 | Z11: 65.11 | AA11: 65.08 | AB11: 65.42 | AC11: 64.65 | AD11: 10,98M | AE11: 0.0015
A12: 05.11.2024 | B12: 42221.88 | C12: 41835.49 | D12: 42258.84 | E12: 41766.96 | F12: 284,00M | G12: 0.0102 | I12: 05.11.2024 | J12: 293.29 | K12: 291.71 | L12: 294.78 | M12: 291.58 | N12: 3,75M | O12: 0.0049 | Q12: 05.11.2024 | R12: 158.35 | S12: 157.67 | T12: 158.59 | U12: 156.35 | V12: 6,55M | W12: 0.0007 | Y12: 05.11.2024 | Z12: 65.37 | AA12: 64.64 | AB12: 65.47 | AC12: 64.64 | AD12: 8,78M | AE12: 0.004
A13: 06.11.2024 | B13: 43729.93 | C13: 42850.4 | D13: 43778.78 | E13: 42850.4 | F13: 555,81M | G13: 0.0357 | I13: 06.11.2024 | J13: 307.4 | K13: 306.32 | L13: 309 | M13: 302.82 | N13: 10,32M | O13: 0.0481 | Q13: 06.11.2024 | R13: 157.88 | S13: 159.9 | T13: 160.85 | U13: 157.35 | V13: 8,93M | W13: -0.003 | Y13: 06.11.2024 | Z13: 63.7 | AA13: 64.42 | AB13: 64.86 | AC13: 63.18 | AD13: 22,90M | AE13: -0.0255
A14: 07.11.2024 | B14: 43729.34 | C14: 43718.92 | D14: 43823.1 | E14: 43641.92 | F14: 437,52M | G14: 0 | I14: 07.11.2024 | J14: 305.8 | K14: 307.5 | L14: 307.63 | M14: 304.42 | N14: 6,24M | O14: -0.0052 | Q14: 07.11.2024 | R14: 156.73 | S14: 158.47 | T14: 158.75 | U14: 156.51 | V14: 7,52M | W14: -0.0073 | Y14: 07.11.2024 | Z14: 63.66 | AA14: 64.29 | AB14: 64.39 | AC14: 63.6 | AD14: 14,86M | AE14: -0.0006
... A46: 24.12.2024 | B46: 43297.03 | C46: 42916.48 | D46: 43297.65 | E46: 42871.76 | F46: 230,41M | G46: 0.0091 | I46: 24.12.2024 | J46: 320.65 | K46: 318.17 | L46: 321.54 | M46: 317.28 | N46: 2,68M | O46: 0.0108 | Q46: 24.12.2024 | R46: 145.85 | S46: 145 | T46: 145.85 | U46: 144.33 | V46: 3,16M | W46: 0.004 | Y46: 24.12.2024 | Z46: 62.84 | AA46: 62.2 | AB46: 62.84 | AC46: 62.01 | AD46: 5,02M | AE46: 0.0074
A47: 25.12.2024 | B47: 43297.03 | C47: 42916.48 | D47: 43297.65 | E47: 42871.76 | G47: 0 | I47: 26.12.2024 | J47: 320.91 | K47: 319.77 | L47: 321.45 | M47: 319.46 | N47: 2,86M | O47: 0.0008 | Q47: 26.12.2024 | R47: 145.58 | S47: 145.51 | T47: 146.37 | U47: 145.09 | V47: 4,66M | W47: -0.0019 | Y47: 26.12.2024 | Z47: 62.57 | AA47: 62.62 | AB47: 62.74 | AC47: 62.4 | AD47: 7,95M | AE47: -0.0043
A48: 26.12.2024 | B48: 43325.8 | C48: 43201.85 | D48: 43373.98 | E48: 43115.09 | F48: 270,36M | G48: 0.0007 | I48: 27.12.2024 | J48: 318.66 | K48: 319.27 | L48: 321.5 | M48: 317.56 | N48: 3,49M | O48: -0.007 | Q48: 27.12.2024 | R48: 145.05 | S48: 144.87 | T48: 146.6 | U48: 144.68 | V48: 5,59M | W48: -0.0036 | Y48: 27.12.2024 | Z48: 62.45 | AA48: 62.45 | AB48: 62.95 | AC48: 62.21 | AD48: 8,54M | AE48: -0.0019
A49: 27.12.2024 | B49: 42992.21 | C49: 43142.37 | D49: 43238.85 | E49: 42761.56 | F49: 376,96M | G49: -0.0077 | I49: 30.12.2024 | J49: 315.31 | K49: 314.68 | L49: 317.11 | M49: 313.23 | N49: 3,48M | O49: -0.0105 | Q49: 30.12.2024 | R49: 143.34 | S49: 144.84 | T49: 144.88 | U49: 142.95 | V49: 6,27M | W49: -0.0118 | Y49: 30.12.2024 | Z49: 62.03 | AA49: 62.34 | AB49: 62.34 | AC49: 61.68 | AD49: 8,97M | AE49: -0.0067
A50: 30.12.2024 | B50: 42573.73 | C50: 42863.86 | D50: 42863.86 | E50: 42263.51 | F50: 383,30M | G50: -0.0097 | I50: 31.12.2024 | J50: 316.04 | K50: 316.12 | L50: 317.66 | M50: 315.19 | N50: 3,96M | O50: 0.0023 | Q50: 31.12.2024 | R50: 144.62 | S50: 143.76 | T50: 144.67 | U50: 143.31 | V50: 5,81M | W50: 0.0089 | Y50: 31.12.2024 | Z50: 62.26 | AA50: 62.02 | AB50: 62.43 | AC50: 61.8 | AD50: 9,26M | AE50: 0.0037
A51: 31.12.2024 | B51: 42544.22 | C51: 42636.7 | D51: 42779.69 | E51: 42421.29 | F51: 359,22M | G51: -0.0007 | I51: 02.01.2025 | J51: 314.4 | K51: 317.78 | L51: 319.68 | M51: 312.41 | N51: 5,37M | O51: -0.0052 | Q51: 02.01.2025 | R51: 144.02 | S51: 145.23 | T51: 145.77 | U51: 143.78 | V51: 6,05M | W51: -0.0041 | Y51: 02.01.2025 | Z51: 61.84 | AA51: 62.35 | AB51: 62.75 | AC51: 61.62 | AD51: 12,99M | AE51: -0.0067
A52: 02.01.2025 | B52: 42392.27 | C52: 42660.09 | D52: 42905.09 | E52: 42174.8 | F52: 459,86M | G52: -0.0036 | I52: 03.01.2025 | J52: 314.91 | K52: 314.18 | L52: 315.92 | M52: 312.01 | N52: 4,27M | O52: 0.0016 | Q52: 03.01.2025 | R52: 144.19 | S52: 144.07 | T52: 144.57 | U52: 143.62 | V52: 5,88M | W52: 0.0012 | Y52: 03.01.2025 | Z52: 61.75 | AA52: 61.9 | AB52: 62.08 | AC52: 61.62 | AD52: 10,40M | AE52: -0.0015
A53: 03.01.2025 | B53: 42732.13 | C53: 42495.76 | D53: 42782.76 | E53: 42436.92 | F53: 455,82M | G53: 0.008 | I53: 06.01.2025 | J53: 313.04 | K53: 315.01 | L53: 315.39 | M53: 312.07 | N53: 6,57M | O53: -0.0059 | Q53: 06.01.2025 | R53: 143.66 | S53: 143.51 | T53: 144.82 | U53: 142.93 | V53: 7,91M | W53: -0.0037 | Y53: 06.01.2025 | Z53: 60.81 | AA53: 61.5 | AB53: 61.56 | AC53: 60.66 | AD53: 17,92M | AE53: -0.0152
A54: 06.01.2025 | B54: 42706.56 | C54: 42835.52 | D54: 43115.31 | E54: 42611.16 | F54: 557,04M | G54: -0.0006 | I54: 07.01.2025 | J54: 311.67 | K54: 312.89 | L54: 315.19 | M54: 311.32 | N54: 4,96M | O54: -0.0044 | Q54: 07.01.2025 | R54: 146.23 | S54: 143.76 | T54: 147.18 | U54: 143.59 | V54: 8,42M | W54: 0.0179 | Y54: 07.01.2025 | Z54: 60.84 | AA54: 61.11 | AB54: 61.72 | AC54: 60.62 | AD54: 17,80M | AE54: 0.0005
A55: 07.01.2025 | B55: 42528.36 | C55: 42809.71 | D55: 42931.54 | E55: 42380.75 | F55: 621,64M | G55: -0.0042 | I55: 08.01.2025 | J55: 312.6 | K55: 311 | L55: 314.04 | M55: 310.21 | N55: 5,16M | O55: 0.003 | Q55: 08.01.2025 | R55: 142.27 | S55: 145.49 | T55: 145.59 | U55: 141.44 | V55: 11,18M | W55: -0.0271 | Y55: 08.01.2025 | Z55: 61.71 | AA55: 60.99 | AB55: 61.77 | AC55: 60.93 | AD55: 14,41M | AE55: 0.0143
A56: 08.01.2025 | B56: 42635.2 | C56: 42542.1 | D56: 42656.22 | E56: 42327.79 | F56: 463,43M | G56: 0.0025 | I56: 10.01.2025 | J56: 307.71 | K56: 311.2 | L56: 311.85 | M56: 305.99 | N56: 6,66M | O56: -0.0156 | Q56: 10.01.2025 | R56: 142.06 | S56: 141 | T56: 143.67 | U56: 140.68 | V56: 8,82M | W56: -0.0015 | Y56: 10.01.2025 | Z56: 61.07 | AA56: 61.58 | AB56: 61.65 | AC56: 60.73 | AD56: 22,42M | AE56: -0.0104
A57: 10.01.2025 | B57: 41938.45 | C57: 42540.29 | D57: 42540.29 | E57: 41877.3 | F57: 543,82M | G57: -0.0163 | I57: 13.01.2025 | J57: 306.92 | K57: 305 | L57: 306.92 | M57: 303.84 | N57: 9,57M | O57: -0.0026 | Q57: 13.01.2025 | R57: 144.47 | S57: 142.98 | T57: 145.07 | U57: 142.31 | V57: 10,38M | W57: 0.017 | Y57: 13.01.2025 | Z57: 61.65 | AA57: 61.13 | AB57: 61.85 | AC57: 60.71 | AD57: 18,02M | AE57: 0.0095
A58: 13.01.2025 | B58: 42297.12 | C58: 41924.68 | D58: 42319.6 | E58: 41844.89 | F58: 500,20M | G58: 0.0086 | I58: 14.01.2025 | J58: 309.09 | K58: 308.75 | L58: 310.16 | M58: 307.52 | N58: 5,11M | O58: 0.0071 | Q58: 14.01.2025 | R58: 144.75 | S58: 144.5 | T58: 144.81 | U58: 142.86 | V58: 8,68M | W58: 0.0019 | Y58: 14.01.2025 | Z58: 62.04 | AA58: 61.65 | AB58: 62.06 | AC58: 61.3 | AD58: 16,66M | AE58: 0.0063
A59: 14.01.2025 | B59: 42518.28 | C59: 42366.42 | D59: 42544.57 | E59: 42157.03 | F59: 454,66M | G59: 0.0052 | I59: 15.01.2025 | J59: 316.28 | K59: 313.68 | L59: 317.19 | M59: 313.13 | N59: 5,22M | O59: 0.0233 | Q59: 15.01.2025 | R59: 144.97 | S59: 145.31 | T59: 146.05 | U59: 144.26 | V59: 7,43M | W59: 0.0015 | Y59: 15.01.2025 | Z59: 61.77 | AA59: 62.33 | AB59: 62.62 | AC59: 61.68 | AD59: 16,19M | AE59: -0.0044
... A252: 21.10.2025 | B252: 46924.74 | C252: 46707.08 | D252: 47125.66 | E252: 46688.25 | F252: 436,74M | G252: 0.0047 | I252: 22.10.2025 | J252: 345.36 | K252: 347.82 | L252: 348.17 | M252: 344.5 | N252: 5,07M | O252: -0.0053 | Q252: 22.10.2025 | R252: 192.94 | S252: 192 | T252: 193.45 | U252: 191.77 | V252: 6,34M | W252: 0.0055 | Y252: 22.10.2025 | Z252: 70.81 | AA252: 71.36 | AB252: 71.61 | AC252: 70.51 | AD252: 18,29M | AE252: -0.0058
A253: 22.10.2025 | B253: 46590.41 | C253: 46941.56 | D253: 46941.56 | E253: 46461.52 | F253: 458,46M | G253: -0.0071

Sheet NASDAQ
C1: NASDAQ | K1: AAPL | S1: TSLA | AA1: MSFT
A2: Ημ/νία | B2: Τελευταία | C2: Άνοιγμα | D2: Υψηλό | E2: Χαμηλό | F2: Όγκος | G2: Αλλ.% | I2: Ημ/νία | J2: Τελευταία | K2: Άνοιγμα | L2: Υψηλό | M2: Χαμηλό | N2: Όγκος | O2: Αλλ.% | Q2: Ημ/νία | R2: Τελευταία | S2: Άνοιγμα | T2: Υψηλό | U2: Χαμηλό | V2: Όγκος | W2: Αλλ.% | Y2: Ημ/νία | Z2: Τελευταία | AA2: Άνοιγμα | AB2: Υψηλό | AC2: Χαμηλό | AD2: Όγκος | AE2: Αλλ.%
A3: 23.10.2024 | B3: 18276.65 | C3: 18502.06 | D3: 18509.19 | E3: 18146.61 | F3: 1,02B | G3: -0.016 | I3: 23.10.2024 | J3: 230.76 | K3: 234.08 | L3: 235.14 | M3: 227.76 | N3: 52,29M | O3: -0.0216 | Q3: 23.10.2024 | R3: 213.65 | S3: 217.13 | T3: 218.72 | U3: 212.11 | V3: 80,94M | W3: -0.0198 | Y3: 23.10.2024 | Z3: 424.6 | AA3: 430.86 | AB3: 431.08 | AC3: 422.53 | AD3: 19,65M | AE3: -0.0068
A4: 24.10.2024 | B4: 18415.49 | C4: 18384.15 | D4: 18435.37 | E4: 18305.42 | F4: 977,77M | G4: 0.0076 | I4: 24.10.2024 | J4: 230.57 | K4: 229.98 | L4: 230.82 | M4: 228.41 | N4: 31,11M | O4: -0.0008 | Q4: 24.10.2024 | R4: 260.48 | S4: 244.68 | T4: 262.12 | U4: 242.65 | V4: 204,49M | W4: 0.2192 | Y4: 24.10.2024 | Z4: 424.73 | AA4: 425.33 | AB4: 425.98 | AC4: 422.4 | AD4: 13,58M | AE4: 0.0003
A5: 25.10.2024 | B5: 18518.61 | C5: 18512.58 | D5: 18690.01 | E5: 18487.06 | F5: 976,29M | G5: 0.0056 | I5: 25.10.2024 | J5: 231.41 | K5: 229.74 | L5: 233.22 | M5: 229.57 | N5: 38,80M | O5: 0.0036 | Q5: 25.10.2024 | R5: 269.19 | S5: 256.01 | T5: 269.49 | U5: 255.32 | V5: 161,61M | W5: 0.0334 | Y5: 25.10.2024 | Z5: 428.15 | AA5: 426.76 | AB5: 432.52 | AC5: 426.57 | AD5: 16,90M | AE5: 0.0081
A6: 28.10.2024 | B6: 18567.19 | C6: 18648.25 | D6: 18671.01 | E6: 18563.02 | F6: 1,03B | G6: 0.0026 | I6: 28.10.2024 | J6: 233.4 | K6: 233.32 | L6: 234.73 | M6: 232.55 | N6: 36,09M | O6: 0.0086 | Q6: 28.10.2024 | R6: 262.51 | S6: 270 | T6: 273.54 | U6: 262.24 | V6: 107,65M | W6: -0.0248 | Y6: 28.10.2024 | Z6: 426.59 | AA6: 431.65 | AB6: 431.94 | AC6: 426.3 | AD6: 14,88M | AE6: -0.0036
A7: 29.10.2024 | B7: 18712.75 | C7: 18576.09 | D7: 18753.19 | E7: 18509.59 | F7: 1,12B | G7: 0.0078 | I7: 29.10.2024 | J7: 233.67 | K7: 233.1 | L7: 234.32 | M7: 232.32 | N7: 35,42M | O7: 0.0012 | Q7: 29.10.2024 | R7: 259.52 | S7: 264.51 | T7: 264.98 | U7: 255.51 | V7: 80,52M | W7: -0.0114 | Y7: 29.10.2024 | Z7: 431.95 | AA7: 428 | AB7: 433.17 | AC7: 425.8 | AD7: 17,64M | AE7: 0.0126
A8: 30.10.2024 | B8: 18607.93 | C8: 18731.69 | D8: 18785.49 | E8: 18598.24 | F8: 1,16B | G8: -0.0056 | I8: 30.10.2024 | J8: 230.1 | K8: 232.61 | L8: 233.47 | M8: 229.55 | N8: 47,07M | O8: -0.0153 | Q8: 30.10.2024 | R8: 257.55 | S8: 258.04 | T8: 263.35 | U8: 255.82 | V8: 53,99M | W8: -0.0076 | Y8: 30.10.2024 | Z8: 432.53 | AA8: 437.43 | AB8: 438.5 | AC8: 432.1 | AD8: 29,75M | AE8: 0.0013
A9: 31.10.2024 | B9: 18095.15 | C9: 18427.31 | D9: 18427.31 | E9: 18083.95 | F9: 1,31B | G9: -0.0276 | I9: 31.10.2024 | J9: 225.91 | K9: 229.34 | L9: 229.83 | M9: 225.37 | N9: 64,37M | O9: -0.0182 | Q9: 31.10.2024 | R9: 249.85 | S9: 257.99 | T9: 259.75 | U9: 249.25 | V9: 66,58M | W9: -0.0299 | Y9: 31.10.2024 | Z9: 406.35 | AA9: 415.36 | AB9: 416.16 | AC9: 406.3 | AD9: 53,97M | AE9: -0.0605
A10: 01.11.2024 | B10: 18239.92 | C10: 18189.67 | D10: 18363.94 | E10: 18181.53 | F10: 1,05B | G10: 0.008 | I10: 01.11.2024 | J10: 222.91 | K10: 220.96 | L10: 225.35 | M10: 220.27 | N10: 65,28M | O10: -0.0133 | Q10: 01.11.2024 | R10: 248.98 | S10: 252.04 | T10: 254 | U10: 246.63 | V10: 57,55M | W10: -0.0035 | Y10: 01.11.2024 | Z10: 410.37 | AA10: 409.01 | AB10: 415.5 | AC10: 407.5 | AD10: 24,23M | AE10: 0.0099
A11: 04.11.2024 | B11: 18179.98 | C11: 18220.43 | D11: 18308.3 | E11: 18112.83 | F11: 1,04B | G11: -0.0033 | I11: 04.11.2024 | J11: 222.01 | K11: 220.99 | L11: 222.79 | M11: 219.71 | N11: 44,94M | O11: -0.004 | Q11: 04.11.2024 | R11: 242.84 | S11: 244.56 | T11: 248.9 | U11: 238.88 | V11: 68,80M | W11: -0.0247 | Y11: 04.11.2024 | Z11: 408.46 | AA11: 409.8 | AB11: 410.42 | AC11: 405.57 | AD11: 19,67M | AE11: -0.0047
A12: 05.11.2024 | B12: 18439.17 | C12: 18250.71 | D12: 18449.68 | E12: 18250.71 | F12: 1,07B | G12: 0.0143 | I12: 05.11.2024 | J12: 223.45 | K12: 221.79 | L12: 223.95 | M12: 221.14 | N12: 28,11M | O12: 0.0065 | Q12: 05.11.2024 | R12: 251.44 | S12: 247.34 | T12: 255.28 | U12: 246.21 | V12: 69,28M | W12: 0.0354 | Y12: 05.11.2024 | Z12: 411.46 | AA12: 408.37 | AB12: 414.9 | AC12: 408.08 | AD12: 17,63M | AE12: 0.0073
A13: 06.11.2024 | B13: 18983.46 | C13: 18772.76 | D13: 19000.5 | E13: 18730.21 | F13: 1,64B | G13: 0.0295 | I13: 06.11.2024 | J13: 222.72 | K13: 222.61 | L13: 226.07 | M13: 221.19 | N13: 54,56M | O13: -0.0033 | Q13: 06.11.2024 | R13: 288.53 | S13: 284.67 | T13: 289.59 | U13: 275.62 | V13: 165,23M | W13: 0.1475 | Y13: 06.11.2024 | Z13: 420.18 | AA13: 412.42 | AB13: 420.45 | AC13: 410.52 | AD13: 26,68M | AE13: 0.0212
A14: 07.11.2024 | B14: 19269.46 | C14: 19084.43 | D14: 19301.7 | E14: 19084.43 | F14: 1,43B | G14: 0.0151 | I14: 07.11.2024 | J14: 227.48 | K14: 224.63 | L14: 227.88 | M14: 224.57 | N14: 42,14M | O14: 0.0214 | Q14: 07.11.2024 | R14: 296.91 | S14: 288.89 | T14: 299.75 | U14: 285.52 | V14: 117,31M | W14: 0.029 | Y14: 07.11.2024 | Z14: 425.43 | AA14: 421.28 | AB14: 426.85 | AC14: 419.88 | AD14: 19,90M | AE14: 0.0125
... A252: 22.10.2025 | B252: 22740.4 | C252: 22940.79 | D252: 22978.4 | E252: 22514.08 | F252: 2,06B | G252: -0.0093 | I252: 22.10.2025 | J252: 258.45 | K252: 262.65 | L252: 262.85 | M252: 255.43 | N252: 45,02M | O252: -0.0164 | Q252: 22.10.2025 | R252: 438.97 | S252: 443.45 | T252: 445.54 | U252: 429 | V252: 84,02M | W252: -0.0082 | Y252: 22.10.2025 | Z252: 520.54 | AA252: 521.15 | AB252: 525.23 | AC252: 517.71 | AD252: 18,96M | AE252: 0.0056

Sheet USA Ret
B1: ΑΠΟΔΟΣΕΙΣ(RETURNS)
B2: ΜΕΤΟΧΕΣ | C2: ΜΕΤΟΧΕΣ | D2: ΜΕΤΟΧΕΣ | E2: ΜΕΤΟΧΕΣ | F2: ΜΕΤΟΧΕΣ | G2: ΜΕΤΟΧΕΣ | H2: ΜΕΤΟΧΕΣ | I2: ΜΕΤΟΧΕΣ
A3: Trade Date | B3: DOW JONES | C3: V | D3: JNJ | E3: KO | F3: AAPL | G3: TSLA | H3: MSFT | I3: NASDAQ
A5: 24.10.2024 | B5: =LN(NYSE!B4/NYSE!B3) -> -0.0033123164 | C5: =LN(NYSE!J4/NYSE!J3) -> -0.0019048297 | D5: =LN(NYSE!R4/NYSE!R3) -> -0.013291854 | E5: =LN(NYSE!Z4/NYSE!Z3) -> -0.010494517 | F5: =LN(NASDAQ!J4/NASDAQ!J3) -> -0.00082370542 | G5: =LN(NASDAQ!R4/NASDAQ!R3) -> 0.19818692 | H5: =LN(NASDAQ!Z4/NASDAQ!Z3) -> 0.00030612365 | I5: =LN(NASDAQ!B4/NASDAQ!B3) -> 0.0075678694
A6: 25.10.2024 | B6: =LN(NYSE!B5/NYSE!B4) -> -0.0061537374 | C6: =LN(NYSE!J5/NYSE!J4) -> -0.0052748153 | D6: =LN(NYSE!R5/NYSE!R4) -> -0.01719346 | E6: =LN(NYSE!Z5/NYSE!Z4) -> -0.0056623605 | F6: =LN(NASDAQ!J5/NASDAQ!J4) -> 0.0036365251 | G6: =LN(NASDAQ!R5/NASDAQ!R4) -> 0.032891367 | H6: =LN(NASDAQ!Z5/NASDAQ!Z4) -> 0.0080199286 | I6: =LN(NASDAQ!B5/NASDAQ!B4) -> 0.0055840141 | L6: ΜΕΤΡΑ ΑΠΟΔΟΣΗΣ ΚΑΙ ΚΙΝΔΥΝΟΥ | N6: DOW JONES | O6: V | P6: JNJ | Q6: KO | R6: AAPL | S6: TSLA | T6: MSFT | U6: NASDAQ
A7: 28.10.2024 | B7: =LN(NYSE!B6/NYSE!B5) -> 0.0064654339 | C7: =LN(NYSE!J6/NYSE!J5) -> 0.0086938631 | D7: =LN(NYSE!R6/NYSE!R5) -> 0.0044654006 | E7: =LN(NYSE!Z6/NYSE!Z5) -> -0.0037427995 | F7: =LN(NASDAQ!J6/NASDAQ!J5) -> 0.0085626908 | G7: =LN(NASDAQ!R6/NASDAQ!R5) -> -0.025128273 | H7: =LN(NASDAQ!Z6/NASDAQ!Z5) -> -0.0036502369 | I7: =LN(NASDAQ!B6/NASDAQ!B5) -> 0.0026198722 | K7: 1 | L7: ΜΕΣΗ ΑΠΟΔΟΣΗ | M7: μ | N7: =AVERAGE(B5:B253) -> 0.00039634242 | O7: =AVERAGE(C5:C253) -> 0.00078899012 | P7: =AVERAGE(D5:D253) -> 0.00060737028 | Q7: =AVERAGE(E5:E253) -> 0.00016203004 | R7: =AVERAGE(F5:F253) -> 0.00045511664 | S7: =AVERAGE(G5:G253) -> 0.0028919354 | T7: =AVERAGE(H5:H253) -> 0.00081814934 | U7: =AVERAGE(I5:I253) -> 0.0008775855
A8: 29.10.2024 | B8: =LN(NYSE!B7/NYSE!B6) -> -0.003652069 | C8: =LN(NYSE!J7/NYSE!J6) -> -0.0081615801 | D8: =LN(NYSE!R7/NYSE!R6) -> -0.009387989 | E8: =LN(NYSE!Z7/NYSE!Z6) -> -0.016789323 | F8: =LN(NASDAQ!J7/NASDAQ!J6) -> 0.0011561437 | G8: =LN(NASDAQ!R7/NASDAQ!R6) -> -0.011455406 | H8: =LN(NASDAQ!Z7/NASDAQ!Z6) -> 0.012486476 | I8: =LN(NASDAQ!B7/NASDAQ!B6) -> 0.0078090651 | L8: ΔΙΑΚΥΜΑΝΣΗ | M8: σ^2 | N8: =VARP(B5:B253) -> 0.0001138843 | O8: =VARP(C5:C253) -> 0.00019870188 | P8: =VARP(D5:D253) -> 0.00014920758 | Q8: =VARP(E5:E253) -> 0.0001210824 | R8: =VARP(F5:F253) -> 0.00041554757 | S8: =VARP(G5:G253) -> 0.0019409976 | T8: =VARP(H5:H253) -> 0.00023821959 | U8: =VARP(I5:I253) -> 0.00023329294 | V8: ΣΥΝΟΛΙΚΟΣ ΚΙΝΔΥΝΟΣ
A9: 30.10.2024 | B9: =LN(NYSE!B8/NYSE!B7) -> -0.0021691373 | C9: =LN(NYSE!J8/NYSE!J7) -> 0.028951047 | D9: =LN(NYSE!R8/NYSE!R7) -> 0.003242909 | E9: =LN(NYSE!Z8/NYSE!Z7) -> 0.0054761317 | F9: =LN(NASDAQ!J8/NASDAQ!J7) -> -0.015395867 | G9: =LN(NASDAQ!R8/NASDAQ!R7) -> -0.0076198949 | H9: =LN(NASDAQ!Z8/NASDAQ!Z7) -> 0.0013418473 | I9: =LN(NASDAQ!B8/NASDAQ!B7) -> -0.0056172758 | L9: ΤΥΠΙΚΗ ΑΠΟΚΛΙΣΗ | M9: σ | N9: =SQRT(N8) -> 0.010671659 | O9: =SQRT(O8) -> 0.014096166 | P9: =SQRT(P8) -> 0.012215056 | Q9: =SQRT(Q8) -> 0.011003745 | R9: =SQRT(R8) -> 0.020384984 | S9: =SQRT(S8) -> 0.044056755 | T9: =SQRT(T8) -> 0.015434364 | U9: =SQRT(U8) -> 0.01527393
A10: 31.10.2024 | B10: =LN(NYSE!B9/NYSE!B8) -> -0.009012158 | C10: =LN(NYSE!J9/NYSE!J8) -> -0.0010689472 | D10: =LN(NYSE!R9/NYSE!R8) -> -0.0046806339 | E10: =LN(NYSE!Z9/NYSE!Z8) -> -0.0092967217 | F10: =LN(NASDAQ!J9/NASDAQ!J8) -> -0.018377307 | G10: =LN(NASDAQ!R9/NASDAQ!R8) -> -0.030353138 | H10: =LN(NASDAQ!Z9/NASDAQ!Z8) -> -0.062436831 | I10: =LN(NASDAQ!B9/NASDAQ!B8) -> -0.027943887
A11: 01.11.2024 | B11: =LN(NYSE!B10/NYSE!B9) -> 0.0068896714 | C11: =LN(NYSE!J10/NYSE!J9) -> 0.0030658492 | D11: =LN(NYSE!R10/NYSE!R9) -> 0.0016875531 | E11: =LN(NYSE!Z10/NYSE!Z9) -> -0.0046040597 | F11: =LN(NASDAQ!J10/NASDAQ!J9) -> -0.013368587 | G11: =LN(NASDAQ!R10/NASDAQ!R9) -> -0.0034881658 | H11: =LN(NASDAQ!Z10/NASDAQ!Z9) -> 0.0098443346 | I11: =LN(NASDAQ!B10/NASDAQ!B9) -> 0.0079686521 | L11: ΣΥΝΤΕΛΕΣΤΗΣ ΜΕΤΑΒΛΗΤΟΤΗΤΑΣ | M11: σ/μ | N11: =N9/N7 -> 26.925351 | O11: =O9/O7 -> 17.866086 | P11: =P9/P7 -> 20.111382 | Q11: =Q9/Q7 -> 67.911756 | R11: =R9/R7 -> 44.790681 | S11: =S9/S7 -> 15.23435 | T11: =T9/T7 -> 18.864971 | U11: =U9/U7 -> 17.404492
A12: 04.11.2024 | B12: =LN(NYSE!B11/NYSE!B10) -> -0.0061443213 | C12: =LN(NYSE!J11/NYSE!J10) -> 0.0038105747 | D12: =LN(NYSE!R11/NYSE!R10) -> -0.011873117 | E12: =LN(NYSE!Z11/NYSE!Z10) -> 0.001537043 | F12: =LN(NASDAQ!J11/NASDAQ!J10) -> -0.0040456767 | G12: =LN(NASDAQ!R11/NASDAQ!R10) -> -0.024969782 | H12: =LN(NASDAQ!Z11/NASDAQ!Z10) -> -0.0046652015 | I12: =LN(NASDAQ!B11/NASDAQ!B10) -> -0.00329161
A13: 05.11.2024 | B13: =LN(NYSE!B12/NYSE!B11) -> 0.010171426 | C13: =LN(NYSE!J12/NYSE!J11) -> 0.004921909 | D13: =LN(NYSE!R12/NYSE!R11) -> 0.00069490511 | E13: =LN(NYSE!Z12/NYSE!Z11) -> 0.0039852904 | F13: =LN(NASDAQ!J12/NASDAQ!J11) -> 0.0064652495 | G13: =LN(NASDAQ!R12/NASDAQ!R11) -> 0.034801602 | H13: =LN(NASDAQ!Z12/NASDAQ!Z11) -> 0.0073178198 | I13: =LN(NASDAQ!B12/NASDAQ!B11) -> 0.014156218 | K13: 2 | L13: α ΜΕΤΟΧΗΣ | O13: =INTERCEPT(C5:C253,$B$5:$B$253) -> 0.00075346158 | P13: =INTERCEPT(D5:D253,$B$5:$B$253) -> 0.0006372648 | Q13: =INTERCEPT(E5:E253,$B$5:$B$253) -> 0.0001286993 | R13: =INTERCEPT(F5:F253,$I$5:$I$253) -> -0.00040415684 | S13: =INTERCEPT(G5:G253,$I$5:$I$253) -> 0.0011781038 | T13: =INTERCEPT(H5:H253,$I$5:$I$253) -> 0.00013235951
A14: 06.11.2024 | B14: =LN(NYSE!B13/NYSE!B12) -> 0.035094195 | C14: =LN(NYSE!J13/NYSE!J12) -> 0.04698795 | D14: =LN(NYSE!R13/NYSE!R12) -> -0.0029725222 | E14: =LN(NYSE!Z13/NYSE!Z12) -> -0.025878875 | F14: =LN(NASDAQ!J13/NASDAQ!J12) -> -0.0032722982 | G14: =LN(NASDAQ!R13/NASDAQ!R12) -> 0.13759467 | H14: =LN(NASDAQ!Z13/NASDAQ!Z12) -> 0.020971381 | I14: =LN(NASDAQ!B13/NASDAQ!B12) -> 0.029090867 | L14: β ΜΕΤΟΧΗΣ | O14: =SLOPE(C5:C253,$B$5:$B$253) -> 0.08964102 | P14: =SLOPE(D5:D253,$B$5:$B$253) -> -0.075425974 | Q14: =SLOPE(E5:E253,$B$5:$B$253) -> 0.084095835 | R14: =SLOPE(F5:F253,$I$5:$I$253) -> 0.97913362 | S14: =SLOPE(G5:G253,$I$5:$I$253) -> 1.9528942 | T14: =SLOPE(H5:H253,$I$5:$I$253) -> 0.78145073 | V14: ΣΥΣΤΗΜΑΤΙΚΟΣ ΚΙΝΔΥΝΟΣ
A15: 07.11.2024 | B15: =LN(NYSE!B14/NYSE!B13) -> -1.3491995e-05 | C15: =LN(NYSE!J14/NYSE!J13) -> -0.0052185376 | D15: =LN(NYSE!R14/NYSE!R13) -> -0.0073106711 | E15: =LN(NYSE!Z14/NYSE!Z13) -> -0.00062814072 | F15: =LN(NASDAQ!J14/NASDAQ!J13) -> 0.021146945 | G15: =LN(NASDAQ!R14/NASDAQ!R13) -> 0.028629996 | H15: =LN(NASDAQ!Z14/NASDAQ!Z13) -> 0.012417231 | I15: =LN(NASDAQ!B14/NASDAQ!B13) -> 0.014953385
A16: 08.11.2024 | B16: =LN(NYSE!B15/NYSE!B14) -> 0.0059201026 | C16: =LN(NYSE!J15/NYSE!J14) -> 0.0067463225 | D16: =LN(NYSE!R15/NYSE!R14) -> -0.0080717927 | E16: =LN(NYSE!Z15/NYSE!Z14) -> 0.0040758796 | F16: =LN(NASDAQ!J15/NASDAQ!J14) -> -0.0022885319 | G16: =LN(NASDAQ!R15/NASDAQ!R14) -> 0.078697184 | H16: =LN(NASDAQ!Z15/NASDAQ!Z14) -> -0.0068163053 | I16: =LN(NASDAQ!B15/NASDAQ!B14) -> 0.00089842792 | L16: ΗΜΕΡΕΣ ΣΤΟ ΕΤΟΣ | N16: =COUNT(B5:B253) -> 249 | O16: =COUNT(C5:C253) -> 249 | P16: =COUNT(D5:D253) -> 249 | Q16: =COUNT(E5:E253) -> 249 | R16: =COUNT(F5:F253) -> 249 | S16: =COUNT(G5:G253) -> 249 | T16: =COUNT(H5:H253) -> 249 | U16: =COUNT(I5:I253) -> 249
A17: 11.11.2024 | B17: =LN(NYSE!B16/NYSE!B15) -> 0.0068902107 | C17: =LN(NYSE!J16/NYSE!J15) -> 0.0098580284 | D17: =LN(NYSE!R16/NYSE!R15) -> -0.0027696388 | E17: =LN(NYSE!Z16/NYSE!Z15) -> -0.008799554 | F17: =LN(NASDAQ!J16/NASDAQ!J15) -> -0.01210148 | G17: =LN(NASDAQ!R16/NASDAQ!R15) -> 0.085806908 | H17: =LN(NASDAQ!Z16/NASDAQ!Z15) -> -0.010778761 | I17: =LN(NASDAQ!B16/NASDAQ!B15) -> 0.00062095803 | L17: ΑΠΟΔΟΣΗ ΣΕ ΕΤΗΣΙΑ ΒΑΣΗ
A18: 12.11.2024 | B18: =LN(NYSE!B17/NYSE!B16) -> -0.0086651833 | C18: =LN(NYSE!J17/NYSE!J16) -> -0.003447335 | D18: =LN(NYSE!R17/NYSE!R16) -> -0.01560094 | E18: =LN(NYSE!Z17/NYSE!Z16) -> -0.0025284464 | F18: =LN(NASDAQ!J17/NASDAQ!J16) -> 0 | G18: =LN(NASDAQ!R17/NASDAQ!R16) -> -0.063426758 | H18: =LN(NASDAQ!Z17/NASDAQ!Z16) -> 0.011937743 | I18: =LN(NASDAQ!B17/NASDAQ!B16) -> -0.00089994449 | L18: (1+R)=(1+R/m)mn
A19: 13.11.2024 | B19: =LN(NYSE!B18/NYSE!B17) -> 0.0010745522 | C19: =LN(NYSE!J18/NYSE!J17) -> -0.0011948397 | D19: =LN(NYSE!R18/NYSE!R17) -> 0.0039231121 | E19: =LN(NYSE!Z18/NYSE!Z17) -> -0.0031695748 | F19: =LN(NASDAQ!J18/NASDAQ!J17) -> 0.0039612826 | G19: =LN(NASDAQ!R18/NASDAQ!R17) -> 0.0053132668 | H19: =LN(NASDAQ!Z18/NASDAQ!Z17) -> 0.005116548 | I19: =LN(NASDAQ!B18/NASDAQ!B17) -> -0.0026319003 | L19: R/m= Επιτόκιο περιόδου | O19: =N7 -> 0.00039634242 | P19: =O7 -> 0.00078899012 | Q19: =P7 -> 0.00060737028 | R19: =Q7 -> 0.00016203004 | S19: =R7 -> 0.00045511664 | T19: =S7 -> 0.0028919354 | U19: =T7 -> 0.00081814934
A20: 14.11.2024 | B20: =LN(NYSE!B19/NYSE!B18) -> -0.0047276851 | C20: =LN(NYSE!J19/NYSE!J18) -> -0.0039823276 | D20: =LN(NYSE!R19/NYSE!R18) -> -0.0089804281 | E20: =LN(NYSE!Z19/NYSE!Z18) -> -0.0071684895 | F20: =LN(NASDAQ!J19/NASDAQ!J18) -> 0.013676483 | G20: =LN(NASDAQ!R19/NASDAQ!R18) -> -0.05944814 | H20: =LN(NASDAQ!Z19/NASDAQ!Z18) -> 0.0039667223 | I20: =LN(NASDAQ!B19/NASDAQ!B18) -> -0.006420222 | L20: n= Αριθμός Ετών | O20: 1 | P20: 1 | Q20: 1 | R20: 1 | S20: 1 | T20: 1 | U20: 1
A21: 15.11.2024 | B21: =LN(NYSE!B20/NYSE!B19) -> -0.0070157296 | C21: =LN(NYSE!J20/NYSE!J19) -> 0.0044991903 | D21: =LN(NYSE!R20/NYSE!R19) -> 0.013927711 | E21: =LN(NYSE!Z20/NYSE!Z19) -> -0.013034218 | F21: =LN(NASDAQ!J20/NASDAQ!J19) -> -0.014209674 | G21: =LN(NASDAQ!R20/NASDAQ!R19) -> 0.030196945 | H21: =LN(NASDAQ!Z20/NASDAQ!Z19) -> -0.028247849 | I21: =LN(NASDAQ!B20/NASDAQ!B19) -> -0.022628922 | L21: m= περίοδοι ανα Ετος | O21: =N16 -> 249 | P21: =O16 -> 249 | Q21: =P16 -> 249 | R21: =Q16 -> 249 | S21: =R16 -> 249 | T21: =S16 -> 249 | U21: =T16 -> 249
A22: 18.11.2024 | B22: =LN(NYSE!B21/NYSE!B20) -> -0.0012757591 | C22: =LN(NYSE!J21/NYSE!J20) -> 0.0081055445 | D22: =LN(NYSE!R21/NYSE!R20) -> 0.0049875415 | E22: =LN(NYSE!Z21/NYSE!Z20) -> 0.0019417482 | F22: =LN(NASDAQ!J21/NASDAQ!J20) -> 0.013332942 | G22: =LN(NASDAQ!R21/NASDAQ!R20) -> 0.054664383 | H22: =LN(NASDAQ!Z21/NASDAQ!Z20) -> 0.0018296505 | I22: =LN(NASDAQ!B21/NASDAQ!B20) -> 0.0059612799 | K22: * | L22: R= [(1+R/m)mn]-1
A23: 19.11.2024 | B23: =LN(NYSE!B22/NYSE!B21) -> -0.0027847245 | C23: =LN(NYSE!J22/NYSE!J21) -> -0.0009935739 | D23: =LN(NYSE!R22/NYSE!R21) -> -0.011502223 | E23: =LN(NYSE!Z22/NYSE!Z21) -> 0.011731754 | F23: =LN(NASDAQ!J22/NASDAQ!J21) -> 0.0011396013 | G23: =LN(NASDAQ!R22/NASDAQ!R21) -> 0.021205924 | H23: =LN(NASDAQ!Z22/NASDAQ!Z21) -> 0.0048707432 | I23: =LN(NASDAQ!B22/NASDAQ!B21) -> 0.010358151 | L23: R= Ετήσια Αποδοση | O23: =(1+O19)^(O20*O16)-1 -> 0.1037017 | P23: =(1+P19)^(P20*P16)-1 -> 0.21699059 | Q23: =(1+Q19)^(Q20*Q16)-1 -> 0.16321682 | R23: =(1+R19)^(R20*R16)-1 -> 0.041167013 | S23: =(1+S19)^(S20*S16)-1 -> 0.11996593 | T23: =(1+T19)^(T20*T16)-1 -> 1.0524879 | U23: =(1+U19)^(U20*U16)-1 -> 0.22585173
A24: 20.11.2024 | B24: =LN(NYSE!B23/NYSE!B22) -> 0.0032195268 | C24: =LN(NYSE!J23/NYSE!J22) -> -0.014405003 | D24: =LN(NYSE!R23/NYSE!R22) -> 0.00071869592 | E24: =LN(NYSE!Z23/NYSE!Z22) -> 0.0063704627 | F24: =LN(NASDAQ!J23/NASDAQ!J22) -> 0.0031490579 | G24: =LN(NASDAQ!R23/NASDAQ!R22) -> -0.011540323 | H24: =LN(NASDAQ!Z23/NASDAQ!Z22) -> -0.0055203673 | I24: =LN(NASDAQ!B23/NASDAQ!B22) -> -0.0011240039
A25: 21.11.2024 | B25: =LN(NYSE!B24/NYSE!B23) -> 0.01058411 | C25: =LN(NYSE!J24/NYSE!J23) -> 0.0081323651 | D25: =LN(NYSE!R24/NYSE!R23) -> 0.015489114 | E25: =LN(NYSE!Z24/NYSE!Z23) -> 0.012150051 | F25: =LN(NASDAQ!J24/NASDAQ!J23) -> -0.0020982697 | G25: =LN(NASDAQ!R24/NASDAQ!R23) -> -0.0070122194 | H25: =LN(NASDAQ!Z24/NASDAQ!Z23) -> -0.0063257732 | I25: =LN(NASDAQ!B24/NASDAQ!B23) -> 0.00033106159
A26: 22.11.2024 | B26: =LN(NYSE!B25/NYSE!B24) -> 0.0096671996 | C26: =LN(NYSE!J25/NYSE!J24) -> 6.4534865e-05 | D26: =LN(NYSE!R25/NYSE!R24) -> -0.0021244415 | E26: =LN(NYSE!Z25/NYSE!Z24) -> 0.002506267 | F26: =LN(NASDAQ!J25/NASDAQ!J24) -> 0.0058901979 | G26: =LN(NASDAQ!R25/NASDAQ!R24) -> 0.037334587 | H26: =LN(NASDAQ!Z25/NASDAQ!Z24) -> 0.0099534484 | I26: =LN(NASDAQ!B25/NASDAQ!B24) -> 0.0016447203 | L26: ETΗΣΙΟΠOIHMENO ΣΕ ΠΕΡΙΟΔΙΚΟ | O26: =((1+O23)^(1/(O21*O20)))-1 -> 0.00039634242 | P26: =((1+P23)^(1/(P21*P20)))-1 -> 0.00078899012 | Q26: =((1+Q23)^(1/(Q21*Q20)))-1 -> 0.00060737028 | R26: =((1+R23)^(1/(R21*R20)))-1 -> 0.00016203004 | S26: =((1+S23)^(1/(S21*S20)))-1 -> 0.00045511664 | T26: =((1+T23)^(1/(T21*T20)))-1 -> 0.0028919354 | U26: =((1+U23)^(1/(U21*U20)))-1 -> 0.00081814934
A27: 25.11.2024 | B27: =LN(NYSE!B26/NYSE!B25) -> 0.009885395 | C27: =LN(NYSE!J26/NYSE!J25) -> 0.010495835 | D27: =LN(NYSE!R26/NYSE!R25) -> 0.0039234654 | E27: =LN(NYSE!Z26/NYSE!Z25) -> 0.0071707244 | F27: =LN(NASDAQ!J26/NASDAQ!J25) -> 0.012966426 | G27: =LN(NASDAQ!R26/NASDAQ!R25) -> -0.040430885 | H27: =LN(NASDAQ!Z26/NASDAQ!Z25) -> 0.0042833792 | I27: =LN(NASDAQ!B26/NASDAQ!B25) -> 0.0026900716
A28: 26.11.2024 | B28: =LN(NYSE!B27/NYSE!B26) -> 0.0027621515 | C28: =LN(NYSE!J27/NYSE!J26) -> -0.0043839369 | D28: =LN(NYSE!R27/NYSE!R26) -> -0.0081212177 | E28: =LN(NYSE!Z27/NYSE!Z26) -> 0.0026370914 | F28: =LN(NASDAQ!J27/NASDAQ!J26) -> 0.0093604428 | G28: =LN(NASDAQ!R27/NASDAQ!R26) -> -0.0010637985 | H28: =LN(NASDAQ!Z27/NASDAQ!Z26) -> 0.02173023 | I28: =LN(NASDAQ!B27/NASDAQ!B26) -> 0.006316457 | L28: ΙΣΧΥΕΙ Η ΣΧΕΣΗ
A29: 27.11.2024 | B29: =LN(NYSE!B28/NYSE!B27) -> -0.0030865473 | C29: =LN(NYSE!J28/NYSE!J27) -> 0.0091937058 | D29: =LN(NYSE!R28/NYSE!R27) -> 0.0056789001 | E29: =LN(NYSE!Z28/NYSE!Z27) -> -0.0018607541 | F29: =LN(NASDAQ!J28/NASDAQ!J27) -> -0.00055320327 | G29: =LN(NASDAQ!R28/NASDAQ!R27) -> -0.015914032 | H29: =LN(NASDAQ!Z28/NASDAQ!Z27) -> -0.011751293 | I29: =LN(NASDAQ!B28/NASDAQ!B27) -> -0.006020513
A30: 29.11.2024 | B30: =LN(NYSE!B29/NYSE!B28) -> 0.0042080682 | C30: =LN(NYSE!J29/NYSE!J28) -> 0.0012067708 | D30: =LN(NYSE!R29/NYSE!R28) -> -0.002512807 | E30: =LN(NYSE!Z29/NYSE!Z28) -> -0.0054470604 | F30: =LN(NASDAQ!J29/NASDAQ!J28) -> 0.01016398 | G30: =LN(NASDAQ!R29/NASDAQ!R28) -> 0.036195973 | H30: =LN(NASDAQ!Z29/NASDAQ!Z28) -> 0.0011105205 | I30: =LN(NASDAQ!B29/NASDAQ!B28) -> 0.0082391042
A31: 02.12.2024 | B31: =LN(NYSE!B30/NYSE!B29) -> -0.0028686874 | C31: =LN(NYSE!J30/NYSE!J29) -> 0.0049704881 | D31: =LN(NYSE!R30/NYSE!R29) -> -0.0013556698 | E31: =LN(NYSE!Z30/NYSE!Z29) -> -0.0067329778 | F31: =LN(NASDAQ!J30/NASDAQ!J29) -> 0.0094775514 | G31: =LN(NASDAQ!R30/NASDAQ!R29) -> 0.033979773 | H31: =LN(NASDAQ!Z30/NASDAQ!Z29) -> 0.017602627 | I31: =LN(NASDAQ!B30/NASDAQ!B29) -> 0.0096204679
A32: 03.12.2024 | B32: =LN(NYSE!B31/NYSE!B30) -> -0.0017090654 | C32: =LN(NYSE!J31/NYSE!J30) -> -0.011561924 | D32: =LN(NYSE!R31/NYSE!R30) -> -0.01588782 | E32: =LN(NYSE!Z31/NYSE!Z30) -> -0.0020445081 | F32: =LN(NASDAQ!J31/NASDAQ!J30) -> 0.012690947 | G32: =LN(NASDAQ!R31/NASDAQ!R30) -> -0.016005762 | H32: =LN(NASDAQ!Z31/NASDAQ!Z30) -> 0.00051033428 | I32: =LN(NASDAQ!B31/NASDAQ!B30) -> 0.0039583581 | L32: R το Ετησιο Επιτοκιο
A33: 04.12.2024 | B33: =LN(NYSE!B32/NYSE!B31) -> 0.0068772335 | C33: =LN(NYSE!J32/NYSE!J31) -> -0.0099854741 | D33: =LN(NYSE!R32/NYSE!R31) -> -0.012482413 | E33: =LN(NYSE!Z32/NYSE!Z31) -> -0.020839058 | F33: =LN(NASDAQ!J32/NASDAQ!J31) -> 0.0014825189 | G33: =LN(NASDAQ!R32/NASDAQ!R31) -> 0.018355347 | H33: =LN(NASDAQ!Z32/NASDAQ!Z31) -> 0.014321812 | I33: =LN(NASDAQ!B32/NASDAQ!B31) -> 0.012964778 | L33: r=R/m το Περιοδικο Επιτοκιο
A34: 05.12.2024 | B34: =LN(NYSE!B33/NYSE!B32) -> -0.0055319965 | C34: =LN(NYSE!J33/NYSE!J32) -> -0.0026495217 | D34: =LN(NYSE!R33/NYSE!R32) -> -0.0063335656 | E34: =LN(NYSE!Z33/NYSE!Z32) -> 0.01134832 | F34: =LN(NASDAQ!J33/NASDAQ!J32) -> 0.00012344409 | G34: =LN(NASDAQ!R33/NASDAQ!R32) -> 0.03178624 | H34: =LN(NASDAQ!Z33/NASDAQ!Z32) -> 0.011817782 | I34: =LN(NASDAQ!B33/NASDAQ!B32) -> -0.0017446064
A35: 06.12.2024 | B35: =LN(NYSE!B34/NYSE!B33) -> -0.0027556765 | C35: =LN(NYSE!J34/NYSE!J33) -> 0.0062249229 | D35: =LN(NYSE!R34/NYSE!R33) -> -0.0014054816 | E35: =LN(NYSE!Z34/NYSE!Z33) -> -0.0062176366 | F35: =LN(NASDAQ!J34/NASDAQ!J33) -> -0.00082324859 | G35: =LN(NASDAQ!R34/NASDAQ!R33) -> 0.05202106 | H35: =LN(NASDAQ!Z34/NASDAQ!Z33) -> 0.0021440106 | I35: =LN(NASDAQ!B34/NASDAQ!B33) -> 0.0080408942 | K35: *
A36: 09.12.2024 | B36: =LN(NYSE!B35/NYSE!B34) -> -0.0054038311 | C36: =LN(NYSE!J35/NYSE!J34) -> -0.0087517311 | D36: =LN(NYSE!R35/NYSE!R34) -> 0.001940384 | E36: =LN(NYSE!Z35/NYSE!Z34) -> 0.0011188365 | F36: =LN(NASDAQ!J35/NASDAQ!J34) -> 0.015972888 | G36: =LN(NASDAQ!R35/NASDAQ!R34) -> 0.0014633961 | H36: =LN(NASDAQ!Z35/NASDAQ!Z34) -> 0.0055081694 | I36: =LN(NASDAQ!B35/NASDAQ!B34) -> -0.0062167374
A37: 10.12.2024 | B37: =LN(NYSE!B36/NYSE!B35) -> -0.0034766063 | C37: =LN(NYSE!J36/NYSE!J35) -> 0.013147061 | D37: =LN(NYSE!R36/NYSE!R35) -> -0.0024763256 | E37: =LN(NYSE!Z36/NYSE!Z35) -> 0.0049398555 | F37: =LN(NASDAQ!J36/NASDAQ!J35) -> 0.0041252182 | G37: =LN(NASDAQ!R36/NASDAQ!R35) -> 0.028328357 | H37: =LN(NASDAQ!Z36/NASDAQ!Z35) -> -0.0060493803 | I37: =LN(NASDAQ!B36/NASDAQ!B35) -> -0.00250863
A38: 11.12.2024 | B38: =LN(NYSE!B37/NYSE!B36) -> -0.0022460203 | C38: =LN(NYSE!J37/NYSE!J36) -> 0.0045035769 | D38: =LN(NYSE!R37/NYSE!R36) -> -0.017508136 | E38: =LN(NYSE!Z37/NYSE!Z36) -> -0.0043010819 | F38: =LN(NASDAQ!J37/NASDAQ!J36) -> -0.0051794718 | G38: =LN(NASDAQ!R37/NASDAQ!R36) -> 0.057611357 | H38: =LN(NASDAQ!Z37/NASDAQ!Z36) -> 0.012686202 | I38: =LN(NASDAQ!B37/NASDAQ!B36) -> 0.017504544 | K38: **
A39: 12.12.2024 | B39: =LN(NYSE!B38/NYSE!B37) -> -0.005324402 | C39: =LN(NYSE!J38/NYSE!J37) -> 0.0014012295 | D39: =LN(NYSE!R38/NYSE!R37) -> -0.0027314958 | E39: =LN(NYSE!Z38/NYSE!Z37) -> 0.018975901 | F39: =LN(NASDAQ!J38/NASDAQ!J37) -> 0.0059460181 | G39: =LN(NASDAQ!R38/NASDAQ!R37) -> -0.015827208 | H39: =LN(NASDAQ!Z38/NASDAQ!Z37) -> 0.0012687109 | I39: =LN(NASDAQ!B38/NASDAQ!B37) -> -0.0066128186
A40: 13.12.2024 | B40: =LN(NYSE!B39/NYSE!B38) -> -0.0019616569 | C40: =LN(NYSE!J39/NYSE!J38) -> 0.0016216993 | D40: =LN(NYSE!R39/NYSE!R38) -> 0.0025950981 | E40: =LN(NYSE!Z39/NYSE!Z38) -> -0.011342277 | F40: =LN(NASDAQ!J39/NASDAQ!J38) -> 0.00068535954 | G40: =LN(NASDAQ!R39/NASDAQ!R38) -> 0.042448989 | H40: =LN(NASDAQ!Z39/NASDAQ!Z38) -> -0.0051068875 | I40: =LN(NASDAQ!B39/NASDAQ!B38) -> 0.0011991095
A41: 16.12.2024 | B41: =LN(NYSE!B40/NYSE!B39) -> -0.0025262294 | C41: =LN(NYSE!J40/NYSE!J39) -> 0.0036471505 | D41: =LN(NYSE!R40/NYSE!R39) -> -0.019073116 | E41: =LN(NYSE!Z40/NYSE!Z39) -> -0.0090714396 | F41: =LN(NASDAQ!J40/NASDAQ!J39) -> 0.011659487 | G41: =LN(NASDAQ!R40/NASDAQ!R39) -> 0.059600623 | H41: =LN(NASDAQ!Z40/NASDAQ!Z39) -> 0.0096122494 | I41: =LN(NASDAQ!B40/NASDAQ!B39) -> 0.012327649
A42: 17.12.2024 | B42: =LN(NYSE!B41/NYSE!B40) -> -0.0061394719 | C42: =LN(NYSE!J41/NYSE!J40) -> 0.0076002826 | D42: =LN(NYSE!R41/NYSE!R40) -> 0.017639815 | E42: =LN(NYSE!Z41/NYSE!Z40) -> 0.013497625 | F42: =LN(NASDAQ!J41/NASDAQ!J40) -> 0.0096726355 | G42: =LN(NASDAQ!R41/NASDAQ!R40) -> 0.035724145 | H42: =LN(NASDAQ!Z41/NASDAQ!Z40) -> 0.0063352124 | I42: =LN(NASDAQ!B41/NASDAQ!B40) -> -0.0032187343 | L42: Correlation Matrix | M42: V | N42: JNJ | O42: KO | P42: AAPL | Q42: TSLA | R42: MSFT
A43: 18.12.2024 | B43: =LN(NYSE!B42/NYSE!B41) -> -0.026186441 | C43: =LN(NYSE!J42/NYSE!J41) -> -0.027131966 | D43: =LN(NYSE!R42/NYSE!R41) -> -0.011402789 | E43: =LN(NYSE!Z42/NYSE!Z41) -> -0.0087129264 | F43: =LN(NASDAQ!J42/NASDAQ!J41) -> -0.021654586 | G43: =LN(NASDAQ!R42/NASDAQ!R41) -> -0.086424257 | H43: =LN(NASDAQ!Z42/NASDAQ!Z41) -> -0.038284655 | I43: =LN(NASDAQ!B42/NASDAQ!B41) -> -0.036274269 | L43: V | M43: 1
A44: 19.12.2024 | B44: =LN(NYSE!B43/NYSE!B42) -> 0.00036306039 | C44: =LN(NYSE!J43/NYSE!J42) -> 0.016329246 | D44: =LN(NYSE!R43/NYSE!R42) -> -0.0081157453 | E44: =LN(NYSE!Z43/NYSE!Z42) -> -0.0063846985 | F44: =LN(NASDAQ!J43/NASDAQ!J42) -> 0.0069902261 | G44: =LN(NASDAQ!R43/NASDAQ!R42) -> -0.0090380622 | H44: =LN(NASDAQ!Z43/NASDAQ!Z42) -> -0.00082340299 | I44: =LN(NASDAQ!B43/NASDAQ!B42) -> -0.0010277191 | L44: JNJ | M44: 0.27524528 | N44: 1
A45: 20.12.2024 | B45: =LN(NYSE!B44/NYSE!B43) -> 0.011693145 | C45: =LN(NYSE!J44/NYSE!J43) -> 0.0089474032 | D45: =LN(NYSE!R44/NYSE!R43) -> 0.0061795024 | E45: =LN(NYSE!Z44/NYSE!Z43) -> 0.0016000003 | F45: =LN(NASDAQ!J44/NASDAQ!J43) -> 0.018640978 | G45: =LN(NASDAQ!R44/NASDAQ!R43) -> -0.035256734 | H45: =LN(NASDAQ!Z44/NASDAQ!Z43) -> -0.00098439851 | I45: =LN(NASDAQ!B44/NASDAQ!B43) -> 0.010262157 | L45: KO | M45: 0.29924421 | N45: 0.42484531 | O45: 1
A46: 23.12.2024 | B46: =LN(NYSE!B45/NYSE!B44) -> 0.0015555028 | C46: =LN(NYSE!J45/NYSE!J44) -> -0.0015434775 | D46: =LN(NYSE!R45/NYSE!R44) -> 0.0055222063 | E46: =LN(NYSE!Z45/NYSE!Z44) -> -0.0027215257 | F46: =LN(NASDAQ!J45/NASDAQ!J44) -> 0.003060266 | G46: =LN(NASDAQ!R45/NASDAQ!R44) -> 0.022404244 | H46: =LN(NASDAQ!Z45/NASDAQ!Z44) -> -0.0030968655 | I46: =LN(NASDAQ!B45/NASDAQ!B44) -> 0.0097759964 | L46: AAPL | M46: 0.49550549 | N46: 0.078897281 | O46: 0.11234268 | P46: 1
A47: 24.12.2024 | B47: =LN(NYSE!B46/NYSE!B45) -> 0.009050224 | C47: =LN(NYSE!J46/NYSE!J45) -> 0.010754646 | D47: =LN(NYSE!R46/NYSE!R45) -> 0.0039846164 | E47: =LN(NYSE!Z46/NYSE!Z45) -> 0.0073471022 | F47: =LN(NASDAQ!J46/NASDAQ!J45) -> 0.01141267 | G47: =LN(NASDAQ!R46/NASDAQ!R45) -> 0.070991183 | H47: =LN(NASDAQ!Z46/NASDAQ!Z45) -> 0.0093302605 | I47: =LN(NASDAQ!B46/NASDAQ!B45) -> 0.013380938 | L47: TSLA | M47: 0.39641935 | N47: -0.052288099 | O47: -0.094678959 | P47: 0.47699733 | Q47: 1
A48: 25.12.2024 | B48: =LN(NYSE!B47/NYSE!B46) -> 0 | C48: =LN(NYSE!J47/NYSE!J46) -> 0.00081052439 | D48: =LN(NYSE!R47/NYSE!R46) -> -0.0018529326 | E48: =LN(NYSE!Z47/NYSE!Z46) -> -0.0043058834 | F48: =LN(NASDAQ!J47/NASDAQ!J46) -> 0.0031708004 | G48: =LN(NASDAQ!R47/NASDAQ!R46) -> -0.017787267 | H48: =LN(NASDAQ!Z47/NASDAQ!Z46) -> -0.0027808187 | I48: =LN(NASDAQ!B47/NASDAQ!B46) -> -0.00053780772 | L48: MSFT | M48: 0.36136394 | N48: -0.14860871 | O48: -0.098769159 | P48: 0.50947548 | Q48: 0.44977483 | R48: 1
A49: 26.12.2024 | B49: =LN(NYSE!B48/NYSE!B47) -> 0.00066425909 | C49: =LN(NYSE!J48/NYSE!J47) -> -0.0070360063 | D49: =LN(NYSE!R48/NYSE!R47) -> -0.0036472531 | E49: =LN(NYSE!Z48/NYSE!Z47) -> -0.0019196934 | F49: =LN(NASDAQ!J48/NASDAQ!J47) -> -0.013330681 | G49: =LN(NASDAQ!R48/NASDAQ!R47) -> -0.050745259 | H49: =LN(NASDAQ!Z48/NASDAQ!Z47) -> -0.017453013 | I49: =LN(NASDAQ!B48/NASDAQ!B47) -> -0.015013471
A50: 27.12.2024 | B50: =LN(NYSE!B49/NYSE!B48) -> -0.007729364 | C50: =LN(NYSE!J49/NYSE!J48) -> -0.010568422 | D50: =LN(NYSE!R49/NYSE!R48) -> -0.01185908 | E50: =LN(NYSE!Z49/NYSE!Z48) -> -0.0067480976 | F50: =LN(NASDAQ!J49/NASDAQ!J48) -> -0.013352175 | G50: =LN(NASDAQ!R49/NASDAQ!R48) -> -0.033569289 | H50: =LN(NASDAQ!Z49/NASDAQ!Z48) -> -0.013327919 | I50: =LN(NASDAQ!B49/NASDAQ!B48) -> -0.011999485
A51: 30.12.2024 | B51: =LN(NYSE!B50/NYSE!B49) -> -0.0097815401 | C51: =LN(NYSE!J50/NYSE!J49) -> 0.002312506 | D51: =LN(NYSE!R50/NYSE!R49) -> 0.0088901822 | E51: =LN(NYSE!Z50/NYSE!Z49) -> 0.003701026 | F51: =LN(NASDAQ!J50/NASDAQ!J49) -> -0.0070829153 | G51: =LN(NASDAQ!R50/NASDAQ!R49) -> -0.033050192 | H51: =LN(NASDAQ!Z50/NASDAQ!Z49) -> -0.0078693115 | I51: =LN(NASDAQ!B50/NASDAQ!B49) -> -0.0090727931
A52: 31.12.2024 | B52: =LN(NYSE!B51/NYSE!B50) -> -0.00069339079 | C52: =LN(NYSE!J51/NYSE!J50) -> -0.0052027273 | D52: =LN(NYSE!R51/NYSE!R50) -> -0.0041574339 | E52: =LN(NYSE!Z51/NYSE!Z50) -> -0.0067687607 | F52: =LN(NASDAQ!J51/NASDAQ!J50) -> -0.026586226 | G52: =LN(NASDAQ!R51/NASDAQ!R50) -> -0.062744041 | H52: =LN(NASDAQ!Z51/NASDAQ!Z50) -> -0.0069517469 | I52: =LN(NASDAQ!B51/NASDAQ!B50) -> -0.0015547436
A53: 02.01.2025 | B53: =LN(NYSE!B52/NYSE!B51) -> -0.0035779713 | C53: =LN(NYSE!J52/NYSE!J51) -> 0.0016208232 | D53: =LN(NYSE!R52/NYSE!R51) -> 0.0011796955 | E53: =LN(NYSE!Z52/NYSE!Z51) -> -0.0014564288 | F53: =LN(NASDAQ!J52/NASDAQ!J51) -> -0.0020114536 | G53: =LN(NASDAQ!R52/NASDAQ!R51) -> 0.078955036 | H53: =LN(NASDAQ!Z52/NASDAQ!Z51) -> 0.01133123 | I53: =LN(NASDAQ!B52/NASDAQ!B51) -> 0.017525814
A54: 03.01.2025 | B54: =LN(NYSE!B53/NYSE!B52) -> 0.007985062 | C54: =LN(NYSE!J53/NYSE!J52) -> -0.0059559058 | D54: =LN(NYSE!R53/NYSE!R52) -> -0.0036824777 | E54: =LN(NYSE!Z53/NYSE!Z52) -> -0.015339726 | F54: =LN(NASDAQ!J53/NASDAQ!J52) -> 0.006716382 | G54: =LN(NASDAQ!R53/NASDAQ!R52) -> 0.0014851066 | H54: =LN(NASDAQ!Z53/NASDAQ!Z52) -> 0.010573407 | I54: =LN(NASDAQ!B53/NASDAQ!B52) -> 0.012323305
A55: 06.01.2025 | B55: =LN(NYSE!B54/NYSE!B53) -> -0.00059855788 | C55: =LN(NYSE!J54/NYSE!J53) -> -0.0043860422 | D55: =LN(NYSE!R54/NYSE!R53) -> 0.017731328 | E55: =LN(NYSE!Z54/NYSE!Z53) -> 0.00049321826 | F55: =LN(NASDAQ!J54/NASDAQ!J53) -> -0.011453092 | G55: =LN(NASDAQ!R54/NASDAQ!R53) -> -0.041450664 | H55: =LN(NASDAQ!Z54/NASDAQ!Z53) -> -0.01289096 | I55: =LN(NASDAQ!B54/NASDAQ!B53) -> -0.019073288
A56: 07.01.2025 | B56: =LN(NYSE!B55/NYSE!B54) -> -0.0041813909 | C56: =LN(NYSE!J55/NYSE!J54) -> 0.0029794822 | D56: =LN(NYSE!R55/NYSE!R54) -> -0.027454064 | E56: =LN(NYSE!Z55/NYSE!Z54) -> 0.014198525 | F56: =LN(NASDAQ!J55/NASDAQ!J54) -> 0.0020209943 | G56: =LN(NASDAQ!R55/NASDAQ!R54) -> 0.0014696569 | H56: =LN(NASDAQ!Z55/NASDAQ!Z54) -> 0.0051716314 | I56: =LN(NASDAQ!B55/NASDAQ!B54) -> -0.00055429301
A57: 08.01.2025 | B57: =LN(NYSE!B56/NYSE!B55) -> 0.0025090557 | C57: =LN(NYSE!J56/NYSE!J55) -> -0.015766637 | D57: =LN(NYSE!R56/NYSE!R55) -> -0.0014771571 | E57: =LN(NYSE!Z56/NYSE!Z55) -> -0.010425245 | F57: =LN(NASDAQ!J56/NASDAQ!J55) -> -0.024399083 | G57: =LN(NASDAQ!R56/NASDAQ!R55) -> -0.0005065343 | H57: =LN(NASDAQ!Z56/NASDAQ!Z55) -> -0.013301757 | I57: =LN(NASDAQ!B56/NASDAQ!B55) -> -0.01642096
A58: 10.01.2025 | B58: =LN(NYSE!B57/NYSE!B56) -> -0.016477136 | C58: =LN(NYSE!J57/NYSE!J56) -> -0.0025706537 | D58: =LN(NYSE!R57/NYSE!R56) -> 0.01682237 | E58: =LN(NYSE!Z57/NYSE!Z56) -> 0.0094524824 | F58: =LN(NASDAQ!J57/NASDAQ!J56) -> -0.010397972 | G58: =LN(NASDAQ!R57/NASDAQ!R56) -> 0.021478177 | H58: =LN(NASDAQ!Z57/NASDAQ!Z56) -> -0.0042098275 | I58: =LN(NASDAQ!B57/NASDAQ!B56) -> -0.0038447378
A59: 13.01.2025 | B59: =LN(NYSE!B58/NYSE!B57) -> 0.0085159314 | C59: =LN(NYSE!J58/NYSE!J57) -> 0.0070453693 | D59: =LN(NYSE!R58/NYSE!R57) -> 0.0019362429 | E59: =LN(NYSE!Z58/NYSE!Z57) -> 0.0063061087 | F59: =LN(NASDAQ!J58/NASDAQ!J57) -> -0.0047896089 | G59: =LN(NASDAQ!R58/NASDAQ!R57) -> -0.017382608 | H59: =LN(NASDAQ!Z58/NASDAQ!Z57) -> -0.0036500773 | I59: =LN(NASDAQ!B58/NASDAQ!B57) -> -0.0022925342
A60: 14.01.2025 | B60: =LN(NYSE!B59/NYSE!B58) -> 0.0052151025 | C60: =LN(NYSE!J59/NYSE!J58) -> 0.022995401 | D60: =LN(NYSE!R59/NYSE!R58) -> 0.001518708 | E60: =LN(NYSE!Z59/NYSE!Z58) -> -0.0043615286 | F60: =LN(NASDAQ!J59/NASDAQ!J58) -> 0.019484857 | G60: =LN(NASDAQ!R59/NASDAQ!R58) -> 0.077314193 | H60: =LN(NASDAQ!Z59/NASDAQ!Z58) -> 0.025275105 | I60: =LN(NASDAQ!B59/NASDAQ!B58) -> 0.024217627
... A253: 21.10.2025 | B253: =LN(NYSE!B252/NYSE!B251) -> 0.0046599876 | C253: =LN(NYSE!J252/NYSE!J251) -> -0.005342433 | D253: =LN(NYSE!R252/NYSE!R251) -> 0.0055090831 | E253: =LN(NYSE!Z252/NYSE!Z251) -> -0.0057734442 | F253: =LN(NASDAQ!J252/NASDAQ!J251) -> -0.016576873 | G253: =LN(NASDAQ!R252/NASDAQ!R251) -> -0.008235354 | H253: =LN(NASDAQ!Z252/NASDAQ!Z251) -> 0.0055480782 | I253: =LN(NASDAQ!B252/NASDAQ!B251) -> -0.0093347583
J300: ΤΕΛΟΣ ΧΑΡΤΟΦΥΚΑΚΙΟΥ
J301: ΠΡΟΒΛΕΨΗ ΤΙΜΩΝ ΜΕ ΒΑΣΗ ΈΝΑ ΕΤΟΣ ΠΡΙΝ

Sheet GREECE Ret
B1: ΑΠΟΔΟΣΕΙΣ(RETURNS)
C2: ΜΕΤΟΧΕΣ | D2: ΜΕΤΟΧΕΣ | E2: ΜΕΤΟΧΕΣ | F2: ΜΕΤΟΧΕΣ | G2: ΜΕΤΟΧΕΣ | H2: ΜΕΤΟΧΕΣ
A3: Trade Date | B3: ΓΔ | C3: OPAr | D3: AGNr | E3: ACBr | F3: HRMr | G3: MTLNr | H3: EURBr
A5: 24.10.2024 | B5: =LN(ΧΑΑ!B4/ΧΑΑ!B3) -> -0.0032316185 | C5: =LN(ΧΑΑ!J4/ΧΑΑ!J3) -> -0.0019053674 | D5: =LN(ΧΑΑ!R4/ΧΑΑ!R3) -> 0.0057859371 | E5: =LN(ΧΑΑ!Z4/ΧΑΑ!Z3) -> -0.017538156 | F5: =LN(ΧΑΑ!AH4/ΧΑΑ!AH3) -> -0.0052677909 | G5: =LN(ΧΑΑ!AP4/ΧΑΑ!AP3) -> 0.010882816 | H5: =LN(ΧΑΑ!AX4/ΧΑΑ!AX3) -> 0.0050125418
A6: 25.10.2024 | B6: =LN(ΧΑΑ!B5/ΧΑΑ!B4) -> -0.00884407 | C6: =LN(ΧΑΑ!J5/ΧΑΑ!J4) -> -0.0038216607 | D6: =LN(ΧΑΑ!R5/ΧΑΑ!R4) -> -0.024332101 | E6: =LN(ΧΑΑ!Z5/ΧΑΑ!Z4) -> -0.0085288363 | F6: =LN(ΧΑΑ!AH5/ΧΑΑ!AH4) -> 0.0035149421 | G6: =LN(ΧΑΑ!AP5/ΧΑΑ!AP4) -> -0.029288244 | H6: =LN(ΧΑΑ!AX5/ΧΑΑ!AX4) -> -0.010582109 | L6: ΜΕΤΡΑ ΑΠΟΔΟΣΗΣ ΚΑΙ ΚΙΝΔΥΝΟΥ | N6: ΓΔ | O6: OPAr | P6: AGNr | Q6: ACBr | R6: HRMr | S6: MTLNr | T6: EURBr
A7: 29.10.2024 | B7: =LN(ΧΑΑ!B6/ΧΑΑ!B5) -> 0.0078311517 | C7: =LN(ΧΑΑ!J6/ΧΑΑ!J5) -> 0.006995259 | D7: =LN(ΧΑΑ!R6/ΧΑΑ!R5) -> -0.0019723872 | E7: =LN(ΧΑΑ!Z6/ΧΑΑ!Z5) -> 0.014878064 | F7: =LN(ΧΑΑ!AH6/ΧΑΑ!AH5) -> 0 | G7: =LN(ΧΑΑ!AP6/ΧΑΑ!AP5) -> 0.0030911926 | H7: =LN(ΧΑΑ!AX6/ΧΑΑ!AX5) -> 0.025211419 | K7: 1 | L7: ΜΕΣΗ ΑΠΟΔΟΣΗ | M7: μ | N7: =AVERAGE(B5:B251) -> 0.0014916205 | O7: =AVERAGE(C5:C251) -> 0.00063142488 | P7: =AVERAGE(D5:D251) -> 0.0010856283 | Q7: =AVERAGE(E5:E251) -> 0.003675864 | R7: =AVERAGE(F5:F251) -> -0.0011107072 | S7: =AVERAGE(G5:G251) -> 0.0011806707 | T7: =AVERAGE(H5:H251) -> 0.0024505827
A8: 30.10.2024 | B8: =LN(ΧΑΑ!B7/ΧΑΑ!B6) -> -0.013906031 | C8: =LN(ΧΑΑ!J7/ΧΑΑ!J6) -> -0.016613801 | D8: =LN(ΧΑΑ!R7/ΧΑΑ!R6) -> -0.01994084 | E8: =LN(ΧΑΑ!Z7/ΧΑΑ!Z6) -> -0.037253592 | F8: =LN(ΧΑΑ!AH7/ΧΑΑ!AH6) -> 0.013072082 | G8: =LN(ΧΑΑ!AP7/ΧΑΑ!AP6) -> 0.012270093 | H8: =LN(ΧΑΑ!AX7/ΧΑΑ!AX6) -> -0.014103133 | L8: ΔΙΑΚΥΜΑΝΣΗ | M8: σ^2 | N8: =VARP(B5:B251) -> 0.00013844652 | O8: =VARP(C5:C251) -> 0.0002389505 | P8: =VARP(D5:D251) -> 0.00029754383 | Q8: =VARP(E5:E248) -> 0.00058530722 | R8: =VARP(F5:F251) -> 0.00017390677 | S8: =VARP(G5:G251) -> 0.00035113043 | T8: =VARP(H5:H251) -> 0.00040863047 | V8: ΣΥΝΟΛΙΚΟΣ ΚΙΝΔΥΝΟΣ
A9: 31.10.2024 | B9: =LN(ΧΑΑ!B8/ΧΑΑ!B7) -> 0.00061493721 | C9: =LN(ΧΑΑ!J8/ΧΑΑ!J7) -> 0.0102565 | D9: =LN(ΧΑΑ!R8/ΧΑΑ!R7) -> 0.0040201059 | E9: =LN(ΧΑΑ!Z8/ΧΑΑ!Z7) -> 0.0072727593 | F9: =LN(ΧΑΑ!AH8/ΧΑΑ!AH7) -> 0.013757741 | G9: =LN(ΧΑΑ!AP8/ΧΑΑ!AP7) -> -0.022819368 | H9: =LN(ΧΑΑ!AX8/ΧΑΑ!AX7) -> -0.0058032344 | L9: ΤΥΠΙΚΗ ΑΠΟΚΛΙΣΗ | M9: σ | N9: =SQRT(N8) -> 0.01176633 | O9: =SQRT(O8) -> 0.015458024 | P9: =SQRT(P8) -> 0.017249459 | Q9: =SQRT(Q8) -> 0.024193123 | R9: =SQRT(R8) -> 0.013187371 | S9: =SQRT(S8) -> 0.018738475 | T9: =SQRT(T8) -> 0.02021461
A10: 01.11.2024 | B10: =LN(ΧΑΑ!B9/ΧΑΑ!B8) -> 0.0056325582 | C10: =LN(ΧΑΑ!J9/ΧΑΑ!J8) -> 0.00063755182 | D10: =LN(ΧΑΑ!R9/ΧΑΑ!R8) -> -0.0070458268 | E10: =LN(ΧΑΑ!Z9/ΧΑΑ!Z8) -> 0.015102768 | F10: =LN(ΧΑΑ!AH9/ΧΑΑ!AH8) -> -0.00085433581 | G10: =LN(ΧΑΑ!AP9/ΧΑΑ!AP8) -> -0.00062402498 | H10: =LN(ΧΑΑ!AX9/ΧΑΑ!AX8) -> 0.015227388
A11: 04.11.2024 | B11: =LN(ΧΑΑ!B10/ΧΑΑ!B9) -> 0.00011506073 | C11: =LN(ΧΑΑ!J10/ΧΑΑ!J9) -> -0.028444064 | D11: =LN(ΧΑΑ!R10/ΧΑΑ!R9) -> -0.014242357 | E11: =LN(ΧΑΑ!Z10/ΧΑΑ!Z9) -> 0 | F11: =LN(ΧΑΑ!AH10/ΧΑΑ!AH9) -> -0.0017108644 | G11: =LN(ΧΑΑ!AP10/ΧΑΑ!AP9) -> -0.0031259794 | H11: =LN(ΧΑΑ!AX10/ΧΑΑ!AX9) -> 0.010883756 | L11: ΣΥΝΤΕΛΕΣΤΗΣ ΜΕΤΑΒΛΗΤΟΤΗΤΑΣ | M11: σ/μ | N11: =N9/N7 -> 7.8882864 | O11: =O9/O7 -> 24.481176 | P11: =P9/P7 -> 15.888917 | Q11: =Q9/Q7 -> 6.5816154 | R11: =R9/R7 -> -11.872951 | S11: =S9/S7 -> 15.871043 | T11: =T9/T7 -> 8.2488995
A12: 05.11.2024 | B12: =LN(ΧΑΑ!B11/ΧΑΑ!B10) -> 0.0064580862 | C12: =LN(ΧΑΑ!J11/ΧΑΑ!J10) -> 0.0019652807 | D12: =LN(ΧΑΑ!R11/ΧΑΑ!R10) -> 0.0040899853 | E12: =LN(ΧΑΑ!Z11/ΧΑΑ!Z10) -> 0.0092363001 | F12: =LN(ΧΑΑ!AH11/ΧΑΑ!AH10) -> -0.016400886 | G12: =LN(ΧΑΑ!AP11/ΧΑΑ!AP10) -> 0.0049968873 | H12: =LN(ΧΑΑ!AX11/ΧΑΑ!AX10) -> 0.01534557
A13: 06.11.2024 | B13: =LN(ΧΑΑ!B12/ΧΑΑ!B11) -> 0.0063456554 | C13: =LN(ΧΑΑ!J12/ΧΑΑ!J11) -> -0.01185004 | D13: =LN(ΧΑΑ!R12/ΧΑΑ!R11) -> -0.0010209291 | E13: =LN(ΧΑΑ!Z12/ΧΑΑ!Z11) -> 0.011950933 | F13: =LN(ΧΑΑ!AH12/ΧΑΑ!AH11) -> -0.0017421607 | G13: =LN(ΧΑΑ!AP12/ΧΑΑ!AP11) -> 0.0031104224 | H13: =LN(ΧΑΑ!AX12/ΧΑΑ!AX11) -> 0.010854581 | K13: 2 | L13: α ΜΕΤΟΧΗΣ | O13: =INTERCEPT(C5:C251,$B$5:$B$251) -> -0.00052391234 | P13: =INTERCEPT(D5:D251,$B$5:$B$251) -> -0.00024363003 | Q13: =INTERCEPT(E5:E251,$B$5:$B$251) -> 0.0017567453 | R13: =INTERCEPT(F5:F251,$B$5:$B$251) -> -0.0011375575 | S13: =INTERCEPT(G5:G251,$B$5:$B$251) -> -0.00044591077 | T13: =INTERCEPT(H5:H251,$B$5:$B$251) -> 0.00031996985
A14: 07.11.2024 | B14: =LN(ΧΑΑ!B13/ΧΑΑ!B12) -> -4.9697026e-05 | C14: =LN(ΧΑΑ!J13/ΧΑΑ!J12) -> 0 | D14: =LN(ΧΑΑ!R13/ΧΑΑ!R12) -> 0.0010209291 | E14: =LN(ΧΑΑ!Z13/ΧΑΑ!Z12) -> -0.0035001786 | F14: =LN(ΧΑΑ!AH13/ΧΑΑ!AH12) -> -0.018478308 | G14: =LN(ΧΑΑ!AP13/ΧΑΑ!AP12) -> -0.0031104224 | H14: =LN(ΧΑΑ!AX13/ΧΑΑ!AX12) -> -0.0017590154 | L14: β ΜΕΤΟΧΗΣ | O14: =SLOPE(C5:C251,$B$5:$B$251) -> 0.7745517 | P14: =SLOPE(D5:D251,$B$5:$B$251) -> 0.89115049 | Q14: =SLOPE(E5:E251,$B$5:$B$251) -> 1.3559992 | R14: =SLOPE(F5:F251,$B$5:$B$251) -> 0.018000746 | S14: =SLOPE(G5:G251,$B$5:$B$251) -> 1.0904794 | T14: =SLOPE(H5:H251,$B$5:$B$251) -> 1.428388 | V14: ΣΥΣΤΗΜΑΤΙΚΟΣ ΚΙΝΔΥΝΟΣ
A15: 08.11.2024 | B15: =LN(ΧΑΑ!B14/ΧΑΑ!B13) -> 0.003281794 | C15: =LN(ΧΑΑ!J14/ΧΑΑ!J13) -> -0.0026525214 | D15: =LN(ΧΑΑ!R14/ΧΑΑ!R13) -> 0.0050890695 | E15: =LN(ΧΑΑ!Z14/ΧΑΑ!Z13) -> 0.051924231 | F15: =LN(ΧΑΑ!AH14/ΧΑΑ!AH13) -> -0.0017777782 | G15: =LN(ΧΑΑ!AP14/ΧΑΑ!AP13) -> 0.014842573 | H15: =LN(ΧΑΑ!AX14/ΧΑΑ!AX13) -> 0.028268681
A16: 11.11.2024 | B16: =LN(ΧΑΑ!B15/ΧΑΑ!B14) -> 0.010747834 | C16: =LN(ΧΑΑ!J15/ΧΑΑ!J14) -> 0.0046373054 | D16: =LN(ΧΑΑ!R15/ΧΑΑ!R14) -> 0.01711164 | E16: =LN(ΧΑΑ!Z15/ΧΑΑ!Z14) -> 0.046822597 | F16: =LN(ΧΑΑ!AH15/ΧΑΑ!AH14) -> -0.017048417 | G16: =LN(ΧΑΑ!AP15/ΧΑΑ!AP14) -> 0.019453501 | H16: =LN(ΧΑΑ!AX15/ΧΑΑ!AX14) -> -0.0049019706 | K16: ΗΜΕΡΕΣ ΣΤΟ ΕΤΟΣ | N16: =COUNT(B5:B251) -> 247 | O16: =COUNT(C5:C251) -> 247 | P16: =COUNT(D5:D251) -> 247 | Q16: =COUNT(E5:E251) -> 244 | R16: =COUNT(F5:F251) -> 247 | S16: =COUNT(G5:G251) -> 247 | T16: =COUNT(H5:H251) -> 247
A17: 12.11.2024 | B17: =LN(ΧΑΑ!B16/ΧΑΑ!B15) -> 0.0017556688 | C17: =LN(ΧΑΑ!J16/ΧΑΑ!J15) -> -0.001984784 | D17: =LN(ΧΑΑ!R16/ΧΑΑ!R15) -> -0.012048339 | E17: =LN(ΧΑΑ!Z16/ΧΑΑ!Z15) -> 0.028805999 | F17: =LN(ΧΑΑ!AH16/ΧΑΑ!AH15) -> 0.022372298 | G17: =LN(ΧΑΑ!AP16/ΧΑΑ!AP15) -> -0.0066445427 | H17: =LN(ΧΑΑ!AX16/ΧΑΑ!AX15) -> -0.00049152127 | K17: ΑΠΟΔΟΣΗ ΣΕ ΕΤΗΣΙΑ ΒΑΣΗ
A18: 13.11.2024 | B18: =LN(ΧΑΑ!B17/ΧΑΑ!B16) -> -0.0079988639 | C18: =LN(ΧΑΑ!J17/ΧΑΑ!J16) -> -0.0066445427 | D18: =LN(ΧΑΑ!R17/ΧΑΑ!R16) -> -0.010152371 | E18: =LN(ΧΑΑ!Z17/ΧΑΑ!Z16) -> -0.0093023927 | F18: =LN(ΧΑΑ!AH17/ΧΑΑ!AH16) -> -0.0079964886 | G18: =LN(ΧΑΑ!AP17/ΧΑΑ!AP16) -> -0.00060624434 | H18: =LN(ΧΑΑ!AX17/ΧΑΑ!AX16) -> -0.016857117 | K18: (1+R)=(1+R/m)mn
A19: 14.11.2024 | B19: =LN(ΧΑΑ!B18/ΧΑΑ!B17) -> -0.001416985 | C19: =LN(ΧΑΑ!J18/ΧΑΑ!J17) -> 0.0059820717 | D19: =LN(ΧΑΑ!R18/ΧΑΑ!R17) -> 0.0050890695 | E19: =LN(ΧΑΑ!Z18/ΧΑΑ!Z17) -> 0.0012453302 | F19: =LN(ΧΑΑ!AH18/ΧΑΑ!AH17) -> 0.0079964886 | G19: =LN(ΧΑΑ!AP18/ΧΑΑ!AP17) -> 0.0066485588 | H19: =LN(ΧΑΑ!AX18/ΧΑΑ!AX17) -> -0.014352506 | K19: R/m= Επιτόκιο περιόδου | O19: =N7 -> 0.0014916205 | P19: =O7 -> 0.00063142488 | Q19: =P7 -> 0.0010856283 | R19: =Q7 -> 0.003675864 | S19: =R7 -> -0.0011107072 | T19: =S7 -> 0.0011806707
A20: 15.11.2024 | B20: =LN(ΧΑΑ!B19/ΧΑΑ!B18) -> -0.0096620479 | C20: =LN(ΧΑΑ!J19/ΧΑΑ!J18) -> 0.0033079752 | D20: =LN(ΧΑΑ!R19/ΧΑΑ!R18) -> -0.016377029 | E20: =LN(ΧΑΑ!Z19/ΧΑΑ!Z18) -> -0.017577351 | F20: =LN(ΧΑΑ!AH19/ΧΑΑ!AH18) -> -0.011571113 | G20: =LN(ΧΑΑ!AP19/ΧΑΑ!AP18) -> -0.0060423145 | H20: =LN(ΧΑΑ!AX19/ΧΑΑ!AX18) -> -0.00076113159 | K20: n= Αριθμός Ετών | O20: 1 | P20: 1 | Q20: 1 | R20: 1 | S20: 1 | T20: 1
A21: 18.11.2024 | B21: =LN(ΧΑΑ!B20/ΧΑΑ!B19) -> -0.0081751048 | C21: =LN(ΧΑΑ!J20/ΧΑΑ!J19) -> -0.01062427 | D21: =LN(ΧΑΑ!R20/ΧΑΑ!R19) -> -0.016649708 | E21: =LN(ΧΑΑ!Z20/ΧΑΑ!Z19) -> -0.0095450932 | F21: =LN(ΧΑΑ!AH20/ΧΑΑ!AH19) -> 0.021258551 | G21: =LN(ΧΑΑ!AP20/ΧΑΑ!AP19) -> -0.020821328 | H21: =LN(ΧΑΑ!AX20/ΧΑΑ!AX19) -> 0.018109147 | K21: m= περίοδοι ανα Ετος | O21: =N16 -> 247 | P21: =O16 -> 247 | Q21: =P16 -> 247 | R21: =Q16 -> 244 | S21: =R16 -> 247 | T21: =S16 -> 247
A22: 19.11.2024 | B22: =LN(ΧΑΑ!B21/ΧΑΑ!B20) -> -0.018643895 | C22: =LN(ΧΑΑ!J21/ΧΑΑ!J20) -> -0.0087161128 | D22: =LN(ΧΑΑ!R21/ΧΑΑ!R20) -> -0.031985669 | E22: =LN(ΧΑΑ!Z21/ΧΑΑ!Z20) -> -0.017414178 | F22: =LN(ΧΑΑ!AH21/ΧΑΑ!AH20) -> -0.013233541 | G22: =LN(ΧΑΑ!AP21/ΧΑΑ!AP20) -> -0.050121496 | H22: =LN(ΧΑΑ!AX21/ΧΑΑ!AX20) -> -0.014562145 | K22: R= [(1+R/m)mn]-1
A23: 20.11.2024 | B23: =LN(ΧΑΑ!B22/ΧΑΑ!B21) -> 0.012997581 | C23: =LN(ΧΑΑ!J22/ΧΑΑ!J21) -> 0.012048339 | D23: =LN(ΧΑΑ!R22/ΧΑΑ!R21) -> 0.021437048 | E23: =LN(ΧΑΑ!Z22/ΧΑΑ!Z21) -> 0.011643081 | F23: =LN(ΧΑΑ!AH22/ΧΑΑ!AH21) -> -0.0098171248 | G23: =LN(ΧΑΑ!AP22/ΧΑΑ!AP21) -> 0.017414178 | H23: =LN(ΧΑΑ!AX22/ΧΑΑ!AX21) -> 0.0095646337 | K23: R= Ετήσια Αποδοση | O23: =(1+O19)^(O20*O16)-1 -> 0.44506711 | P23: =(1+P19)^(P20*P16)-1 -> 0.1687242 | Q23: =(1+Q19)^(Q20*Q16)-1 -> 0.30310468 | R23: =(1+R19)^(R20*R16)-1 -> 1.4750826 | S23: =(1+S19)^(S20*S16)-1 -> -0.24004583 | T23: =(1+T19)^(T20*T16)-1 -> 0.33837158
A24: 21.11.2024 | B24: =LN(ΧΑΑ!B23/ΧΑΑ!B22) -> 0.0093666557 | C24: =LN(ΧΑΑ!J23/ΧΑΑ!J22) -> 0.017804625 | D24: =LN(ΧΑΑ!R23/ΧΑΑ!R22) -> 0.0010598835 | E24: =LN(ΧΑΑ!Z23/ΧΑΑ!Z22) -> 0.0051315058 | F24: =LN(ΧΑΑ!AH23/ΧΑΑ!AH22) -> 0.02480198 | G24: =LN(ΧΑΑ!AP23/ΧΑΑ!AP22) -> 0.0038289772 | H24: =LN(ΧΑΑ!AX23/ΧΑΑ!AX22) -> 0.02180463
A25: 22.11.2024 | B25: =LN(ΧΑΑ!B24/ΧΑΑ!B23) -> 0.0028222267 | C25: =LN(ΧΑΑ!J24/ΧΑΑ!J23) -> 0.032157112 | D25: =LN(ΧΑΑ!R24/ΧΑΑ!R23) -> 0.014721612 | E25: =LN(ΧΑΑ!Z24/ΧΑΑ!Z23) -> -0.020685935 | F25: =LN(ΧΑΑ!AH24/ΧΑΑ!AH23) -> 0 | G25: =LN(ΧΑΑ!AP24/ΧΑΑ!AP23) -> 0.009508788 | H25: =LN(ΧΑΑ!AX24/ΧΑΑ!AX23) -> -0.0019627092
A26: 25.11.2024 | B26: =LN(ΧΑΑ!B25/ΧΑΑ!B24) -> 0.0032908591 | C26: =LN(ΧΑΑ!J25/ΧΑΑ!J24) -> -0.015306421 | D26: =LN(ΧΑΑ!R25/ΧΑΑ!R24) -> 0.018614808 | E26: =LN(ΧΑΑ!Z25/ΧΑΑ!Z24) -> -0.0052390428 | F26: =LN(ΧΑΑ!AH25/ΧΑΑ!AH24) -> 0.00087450814 | G26: =LN(ΧΑΑ!AP25/ΧΑΑ!AP24) -> -0.0056944159 | H26: =LN(ΧΑΑ!AX25/ΧΑΑ!AX24) -> 0.0044106908 | K26: ETΗΣΙΟΠOIHMENO ΣΕ ΠΕΡΙΟΔΙΚΟ | O26: =((1+O23)^(1/(O21*O20)))-1 -> 0.0014916205 | P26: =((1+P23)^(1/(P21*P20)))-1 -> 0.00063142488 | Q26: =((1+Q23)^(1/(Q21*Q20)))-1 -> 0.0010724355 | R26: =((1+R23)^(1/(R21*R20)))-1 -> 0.0037211431 | S26: =((1+S23)^(1/(S21*S20)))-1 -> -0.0011107072 | T26: =((1+T23)^(1/(T21*T20)))-1 -> 0.0011806707
A27: 26.11.2024 | B27: =LN(ΧΑΑ!B26/ΧΑΑ!B25) -> 0.0013147377 | C27: =LN(ΧΑΑ!J26/ΧΑΑ!J25) -> 0.014039797 | D27: =LN(ΧΑΑ!R26/ΧΑΑ!R25) -> -0.010298752 | E27: =LN(ΧΑΑ!Z26/ΧΑΑ!Z25) -> -0.005266635 | F27: =LN(ΧΑΑ!AH26/ΧΑΑ!AH25) -> 0.0087032751 | G27: =LN(ΧΑΑ!AP26/ΧΑΑ!AP25) -> -0.0038143721 | H27: =LN(ΧΑΑ!AX26/ΧΑΑ!AX25) -> 0.0063368479
A28: 27.11.2024 | B28: =LN(ΧΑΑ!B27/ΧΑΑ!B26) -> -0.0031440304 | C28: =LN(ΧΑΑ!J27/ΧΑΑ!J26) -> 0.00063351285 | D28: =LN(ΧΑΑ!R27/ΧΑΑ!R26) -> 0.010298752 | E28: =LN(ΧΑΑ!Z27/ΧΑΑ!Z26) -> -0.016639319 | F28: =LN(ΧΑΑ!AH27/ΧΑΑ!AH26) -> -0.0087032751 | G28: =LN(ΧΑΑ!AP27/ΧΑΑ!AP26) -> -0.0044685679 | H28: =LN(ΧΑΑ!AX27/ΧΑΑ!AX26) -> -0.010747539 | L28: ΙΣΧΥΕΙ Η ΣΧΕΣΗ
A29: 28.11.2024 | B29: =LN(ΧΑΑ!B28/ΧΑΑ!B27) -> 0.00014247754 | C29: =LN(ΧΑΑ!J28/ΧΑΑ!J27) -> -0.0082671377 | D29: =LN(ΧΑΑ!R28/ΧΑΑ!R27) -> -0.010298752 | E29: =LN(ΧΑΑ!Z28/ΧΑΑ!Z27) -> -0.0067340322 | F29: =LN(ΧΑΑ!AH28/ΧΑΑ!AH27) -> 0.0017467253 | G29: =LN(ΧΑΑ!AP28/ΧΑΑ!AP27) -> -0.0051315058 | H29: =LN(ΧΑΑ!AX28/ΧΑΑ!AX27) -> -0.012852377
A30: 29.11.2024 | B30: =LN(ΧΑΑ!B29/ΧΑΑ!B28) -> -0.0073928239 | C30: =LN(ΧΑΑ!J29/ΧΑΑ!J28) -> -0.0096247134 | D30: =LN(ΧΑΑ!R29/ΧΑΑ!R28) -> -0.018809332 | E30: =LN(ΧΑΑ!Z29/ΧΑΑ!Z28) -> -0.0088225886 | F30: =LN(ΧΑΑ!AH29/ΧΑΑ!AH28) -> 0.0017436796 | G30: =LN(ΧΑΑ!AP29/ΧΑΑ!AP28) -> -0.0012870015 | H30: =LN(ΧΑΑ!AX29/ΧΑΑ!AX28) -> -0.0049875415
A31: 02.12.2024 | B31: =LN(ΧΑΑ!B30/ΧΑΑ!B29) -> 0.021890136 | C31: =LN(ΧΑΑ!J30/ΧΑΑ!J29) -> 0 | D31: =LN(ΧΑΑ!R30/ΧΑΑ!R29) -> 0.022941569 | E31: =LN(ΧΑΑ!Z30/ΧΑΑ!Z29) -> 0.047913356 | F31: =LN(ΧΑΑ!AH30/ΧΑΑ!AH29) -> 0.0026098318 | G31: =LN(ΧΑΑ!AP30/ΧΑΑ!AP29) -> 0.03666656 | H31: =LN(ΧΑΑ!AX30/ΧΑΑ!AX29) -> 0.054488185
A32: 03.12.2024 | B32: =LN(ΧΑΑ!B31/ΧΑΑ!B30) -> 0.0034273132 | C32: =LN(ΧΑΑ!J31/ΧΑΑ!J30) -> -0.012978768 | D32: =LN(ΧΑΑ!R31/ΧΑΑ!R30) -> 0.018386626 | E32: =LN(ΧΑΑ!Z31/ΧΑΑ!Z30) -> 0.011628038 | F32: =LN(ΧΑΑ!AH31/ΧΑΑ!AH30) -> -0.0069747449 | G32: =LN(ΧΑΑ!AP31/ΧΑΑ!AP30) -> -0.021330796 | H32: =LN(ΧΑΑ!AX31/ΧΑΑ!AX30) -> 0.015970278 | L32: R το Ετησιο Επιτοκιο
A33: 04.12.2024 | B33: =LN(ΧΑΑ!B32/ΧΑΑ!B31) -> 0.0052826177 | C33: =LN(ΧΑΑ!J32/ΧΑΑ!J31) -> 0.011042658 | D33: =LN(ΧΑΑ!R32/ΧΑΑ!R31) -> 0.0020222454 | E33: =LN(ΧΑΑ!Z32/ΧΑΑ!Z31) -> 0.010223731 | F33: =LN(ΧΑΑ!AH32/ΧΑΑ!AH31) -> -0.0079051795 | G33: =LN(ΧΑΑ!AP32/ΧΑΑ!AP31) -> -0.014048762 | H33: =LN(ΧΑΑ!AX32/ΧΑΑ!AX31) -> 0.024397067 | L33: r=R/m το Περιοδικο Επιτοκιο
A34: 05.12.2024 | B34: =LN(ΧΑΑ!B33/ΧΑΑ!B32) -> 0.013150988 | C34: =LN(ΧΑΑ!J33/ΧΑΑ!J32) -> 0.020461072 | D34: =LN(ΧΑΑ!R33/ΧΑΑ!R32) -> 0.027890254 | E34: =LN(ΧΑΑ!Z33/ΧΑΑ!Z32) -> 0.0362087 | F34: =LN(ΧΑΑ!AH33/ΧΑΑ!AH32) -> -0.0097475295 | G34: =LN(ΧΑΑ!AP33/ΧΑΑ!AP32) -> 0.031648211 | H34: =LN(ΧΑΑ!AX33/ΧΑΑ!AX32) -> 0.0095044843
A35: 06.12.2024 | B35: =LN(ΧΑΑ!B34/ΧΑΑ!B33) -> 0.00048758212 | C35: =LN(ΧΑΑ!J34/ΧΑΑ!J33) -> 0.0056800405 | D35: =LN(ΧΑΑ!R34/ΧΑΑ!R33) -> -0.012852377 | E35: =LN(ΧΑΑ!Z34/ΧΑΑ!Z33) -> 0.0073305154 | F35: =LN(ΧΑΑ!AH34/ΧΑΑ!AH33) -> -0.017969935 | G35: =LN(ΧΑΑ!AP34/ΧΑΑ!AP33) -> 0.0055918133 | H35: =LN(ΧΑΑ!AX34/ΧΑΑ!AX33) -> 0.0071813594 | K35: *
A36: 09.12.2024 | B36: =LN(ΧΑΑ!B35/ΧΑΑ!B34) -> 0.0057779095 | C36: =LN(ΧΑΑ!J35/ΧΑΑ!J34) -> 0.0031416928 | D36: =LN(ΧΑΑ!R35/ΧΑΑ!R34) -> 0.012852377 | E36: =LN(ΧΑΑ!Z35/ΧΑΑ!Z34) -> 0.0030385924 | F36: =LN(ΧΑΑ!AH35/ΧΑΑ!AH34) -> 0 | G36: =LN(ΧΑΑ!AP35/ΧΑΑ!AP34) -> 0.017808269 | H36: =LN(ΧΑΑ!AX35/ΧΑΑ!AX34) -> 0.0062416609
A37: 10.12.2024 | B37: =LN(ΧΑΑ!B36/ΧΑΑ!B35) -> -0.0042069035 | C37: =LN(ΧΑΑ!J36/ΧΑΑ!J35) -> -0.0012554929 | D37: =LN(ΧΑΑ!R36/ΧΑΑ!R35) -> -0.016840418 | E37: =LN(ΧΑΑ!Z36/ΧΑΑ!Z35) -> -0.016519189 | F37: =LN(ΧΑΑ!AH36/ΧΑΑ!AH35) -> -0.0045433972 | G37: =LN(ΧΑΑ!AP36/ΧΑΑ!AP35) -> -0.0042696009 | H37: =LN(ΧΑΑ!AX36/ΧΑΑ!AX35) -> -0.002224695
A38: 11.12.2024 | B38: =LN(ΧΑΑ!B37/ΧΑΑ!B36) -> -0.00082978735 | C38: =LN(ΧΑΑ!J37/ΧΑΑ!J36) -> -0.00062833807 | D38: =LN(ΧΑΑ!R37/ΧΑΑ!R36) -> -0.00099950033 | E38: =LN(ΧΑΑ!Z37/ΧΑΑ!Z36) -> -0.0037082861 | F38: =LN(ΧΑΑ!AH37/ΧΑΑ!AH36) -> 0.0081633106 | G38: =LN(ΧΑΑ!AP37/ΧΑΑ!AP36) -> 0.010942358 | H38: =LN(ΧΑΑ!AX37/ΧΑΑ!AX36) -> -0.0017833264 | K38: **
A39: 12.12.2024 | B39: =LN(ΧΑΑ!B38/ΧΑΑ!B37) -> 0.0044016596 | C39: =LN(ΧΑΑ!J38/ΧΑΑ!J37) -> 0.0068900993 | D39: =LN(ΧΑΑ!R38/ΧΑΑ!R37) -> 0.0099503309 | E39: =LN(ΧΑΑ!Z38/ΧΑΑ!Z37) -> 0.004324999 | F39: =LN(ΧΑΑ!AH38/ΧΑΑ!AH37) -> 0.0027063616 | G39: =LN(ΧΑΑ!AP38/ΧΑΑ!AP37) -> 0.021531932 | H39: =LN(ΧΑΑ!AX38/ΧΑΑ!AX37) -> -0.013929679
A40: 13.12.2024 | B40: =LN(ΧΑΑ!B39/ΧΑΑ!B38) -> 0.0036068016 | C40: =LN(ΧΑΑ!J39/ΧΑΑ!J38) -> -0.0012492194 | D40: =LN(ΧΑΑ!R39/ΧΑΑ!R38) -> 0.019608471 | E40: =LN(ΧΑΑ!Z39/ΧΑΑ!Z38) -> -0.0012338064 | F40: =LN(ΧΑΑ!AH39/ΧΑΑ!AH38) -> -0.0099593399 | G40: =LN(ΧΑΑ!AP39/ΧΑΑ!AP38) -> 0.0094229201 | H40: =LN(ΧΑΑ!AX39/ΧΑΑ!AX38) -> 0.00090456813
A41: 16.12.2024 | B41: =LN(ΧΑΑ!B40/ΧΑΑ!B39) -> -0.0032994781 | C41: =LN(ΧΑΑ!J40/ΧΑΑ!J39) -> -0.013845407 | D41: =LN(ΧΑΑ!R40/ΧΑΑ!R39) -> 0.0048426245 | E41: =LN(ΧΑΑ!Z40/ΧΑΑ!Z39) -> -0.0080570625 | F41: =LN(ΧΑΑ!AH40/ΧΑΑ!AH39) -> 0.0099593399 | G41: =LN(ΧΑΑ!AP40/ΧΑΑ!AP39) -> 0.0070093745 | H41: =LN(ΧΑΑ!AX40/ΧΑΑ!AX39) -> -0.0040770158 | K41: Correlation Matrix
A42: 17.12.2024 | B42: =LN(ΧΑΑ!B41/ΧΑΑ!B40) -> -0.0080075018 | C42: =LN(ΧΑΑ!J41/ΧΑΑ!J40) -> -0.024375806 | D42: =LN(ΧΑΑ!R41/ΧΑΑ!R40) -> -0.0048426245 | E42: =LN(ΧΑΑ!Z41/ΧΑΑ!Z40) -> -0.013784679 | F42: =LN(ΧΑΑ!AH41/ΧΑΑ!AH40) -> 0.00896867 | G42: =LN(ΧΑΑ!AP41/ΧΑΑ!AP40) -> -0.0034985458 | H42: =LN(ΧΑΑ!AX41/ΧΑΑ!AX40) -> -0.0036380213 | L42: OPAr | M42: AGNr | N42: ACBr | O42: HRMr | P42: MTLNr | Q42: EURBr
A43: 18.12.2024 | B43: =LN(ΧΑΑ!B42/ΧΑΑ!B41) -> 0.0019735469 | C43: =LN(ΧΑΑ!J42/ΧΑΑ!J41) -> 0.021837734 | D43: =LN(ΧΑΑ!R42/ΧΑΑ!R41) -> 0 | E43: =LN(ΧΑΑ!Z42/ΧΑΑ!Z41) -> 0.005662173 | F43: =LN(ΧΑΑ!AH42/ΧΑΑ!AH41) -> -0.00089325598 | G43: =LN(ΧΑΑ!AP42/ΧΑΑ!AP41) -> -0.0046838493 | H43: =LN(ΧΑΑ!AX42/ΧΑΑ!AX41) -> 0.0072628553 | K43: OPAr | L43: 1
A44: 19.12.2024 | B44: =LN(ΧΑΑ!B43/ΧΑΑ!B42) -> 0.00041896324 | C44: =LN(ΧΑΑ!J43/ΧΑΑ!J42) -> -0.00063552592 | D44: =LN(ΧΑΑ!R43/ΧΑΑ!R42) -> -0.0058422756 | E44: =LN(ΧΑΑ!Z43/ΧΑΑ!Z42) -> -0.0044011388 | F44: =LN(ΧΑΑ!AH43/ΧΑΑ!AH42) -> 0.020345682 | G44: =LN(ΧΑΑ!AP43/ΧΑΑ!AP42) -> -0.0082498995 | H44: =LN(ΧΑΑ!AX43/ΧΑΑ!AX42) -> 0.011243653 | K44: AGNr | L44: 0.32597385 | M44: 1
A45: 20.12.2024 | B45: =LN(ΧΑΑ!B44/ΧΑΑ!B43) -> -0.0025990292 | C45: =LN(ΧΑΑ!J44/ΧΑΑ!J43) -> -0.0025461503 | D45: =LN(ΧΑΑ!R44/ΧΑΑ!R43) -> -0.016740913 | E45: =LN(ΧΑΑ!Z44/ΧΑΑ!Z43) -> -0.0050537063 | F45: =LN(ΧΑΑ!AH44/ΧΑΑ!AH43) -> 0.0078500185 | G45: =LN(ΧΑΑ!AP44/ΧΑΑ!AP43) -> -0.011904903 | H45: =LN(ΧΑΑ!AX44/ΧΑΑ!AX43) -> 0.0062416609 | K45: ACBr | L45: 0.43023971 | M45: 0.32964306 | N45: 1
A46: 23.12.2024 | B46: =LN(ΧΑΑ!B45/ΧΑΑ!B44) -> -0.0025091694 | C46: =LN(ΧΑΑ!J45/ΧΑΑ!J44) -> -0.012183543 | D46: =LN(ΧΑΑ!R45/ΧΑΑ!R44) -> 0.00099255591 | E46: =LN(ΧΑΑ!Z45/ΧΑΑ!Z44) -> -0.0019017438 | F46: =LN(ΧΑΑ!AH45/ΧΑΑ!AH44) -> 0.016372619 | G46: =LN(ΧΑΑ!AP45/ΧΑΑ!AP44) -> -0.0066086152 | H46: =LN(ΧΑΑ!AX45/ΧΑΑ!AX44) -> -0.01162284 | K46: HRMr | L46: 0.0041962356 | M46: -0.072355644 | N46: 0.088570716 | O46: 1
A47: 27.12.2024 | B47: =LN(ΧΑΑ!B46/ΧΑΑ!B45) -> 0.0058632628 | C47: =LN(ΧΑΑ!J46/ΧΑΑ!J45) -> 0.010269667 | D47: =LN(ΧΑΑ!R46/ΧΑΑ!R45) -> 0.0019821612 | E47: =LN(ΧΑΑ!Z46/ΧΑΑ!Z45) -> 0.0025348556 | F47: =LN(ΧΑΑ!AH46/ΧΑΑ!AH45) -> -0.012037979 | G47: =LN(ΧΑΑ!AP46/ΧΑΑ!AP45) -> 0 | H47: =LN(ΧΑΑ!AX46/ΧΑΑ!AX45) -> 0.0049338517 | K47: MTLNr | L47: 0.33817938 | M47: 0.53017126 | N47: 0.44684383 | O47: 0.050257976 | P47: 1
A48: 30.12.2024 | B48: =LN(ΧΑΑ!B47/ΧΑΑ!B46) -> -0.00073446389 | C48: =LN(ΧΑΑ!J47/ΧΑΑ!J46) -> -0.0038387763 | D48: =LN(ΧΑΑ!R47/ΧΑΑ!R46) -> -0.0089508305 | E48: =LN(ΧΑΑ!Z47/ΧΑΑ!Z46) -> 0.026235109 | F48: =LN(ΧΑΑ!AH47/ΧΑΑ!AH46) -> -0.0095611332 | G48: =LN(ΧΑΑ!AP47/ΧΑΑ!AP46) -> -0.0012062728 | H48: =LN(ΧΑΑ!AX47/ΧΑΑ!AX46) -> 0.0022346378 | K48: EURBr | L48: 0.43825443 | M48: 0.42676286 | N48: 0.60247818 | O48: 0.036810279 | P48: 0.47280408 | Q48: 1
A49: 31.12.2024 | B49: =LN(ΧΑΑ!B48/ΧΑΑ!B47) -> 0.0091320466 | C49: =LN(ΧΑΑ!J48/ΧΑΑ!J47) -> 0.0063897981 | D49: =LN(ΧΑΑ!R48/ΧΑΑ!R47) -> 0.010929071 | E49: =LN(ΧΑΑ!Z48/ΧΑΑ!Z47) -> -0.0030873751 | F49: =LN(ΧΑΑ!AH48/ΧΑΑ!AH47) -> 0.008695707 | G49: =LN(ΧΑΑ!AP48/ΧΑΑ!AP47) -> 0.011401264 | H49: =LN(ΧΑΑ!AX48/ΧΑΑ!AX47) -> -0.0044742804
A50: 02.01.2025 | B50: =LN(ΧΑΑ!B49/ΧΑΑ!B48) -> 0.007666145 | C50: =LN(ΧΑΑ!J49/ΧΑΑ!J48) -> 0.0050826031 | D50: =LN(ΧΑΑ!R49/ΧΑΑ!R48) -> 0.0068931834 | E50: =LN(ΧΑΑ!Z49/ΧΑΑ!Z48) -> 0 | F50: =LN(ΧΑΑ!AH49/ΧΑΑ!AH48) -> -0.032558969 | G50: =LN(ΧΑΑ!AP49/ΧΑΑ!AP48) -> 0.02823717 | H50: =LN(ΧΑΑ!AX49/ΧΑΑ!AX48) -> 0.012034912
A51: 03.01.2025 | B51: =LN(ΧΑΑ!B50/ΧΑΑ!B49) -> 0.003942306 | C51: =LN(ΧΑΑ!J50/ΧΑΑ!J49) -> -0.0025380724 | D51: =LN(ΧΑΑ!R50/ΧΑΑ!R49) -> 0.017510175 | E51: =LN(ΧΑΑ!Z50/ΧΑΑ!Z49) -> 0.020202707 | F51: =LN(ΧΑΑ!AH50/ΧΑΑ!AH49) -> 0.0089047783 | G51: =LN(ΧΑΑ!AP50/ΧΑΑ!AP49) -> 0.0017386269 | H51: =LN(ΧΑΑ!AX50/ΧΑΑ!AX49) -> 0.011891794
A52: 07.01.2025 | B52: =LN(ΧΑΑ!B51/ΧΑΑ!B50) -> 0.013215757 | C52: =LN(ΧΑΑ!J51/ΧΑΑ!J50) -> 0.015758284 | D52: =LN(ΧΑΑ!R51/ΧΑΑ!R50) -> 0.021936979 | E52: =LN(ΧΑΑ!Z51/ΧΑΑ!Z50) -> 0.031028742 | F52: =LN(ΧΑΑ!AH51/ΧΑΑ!AH50) -> 0.019315789 | G52: =LN(ΧΑΑ!AP51/ΧΑΑ!AP50) -> 0.0097955263 | H52: =LN(ΧΑΑ!AX51/ΧΑΑ!AX50) -> 0.021655242
A53: 08.01.2025 | B53: =LN(ΧΑΑ!B52/ΧΑΑ!B51) -> -8.6290154e-05 | C53: =LN(ΧΑΑ!J52/ΧΑΑ!J51) -> -0.011953587 | D53: =LN(ΧΑΑ!R52/ΧΑΑ!R51) -> -0.013295542 | E53: =LN(ΧΑΑ!Z52/ΧΑΑ!Z51) -> 0.014581769 | F53: =LN(ΧΑΑ!AH52/ΧΑΑ!AH51) -> -0.0026121042 | G53: =LN(ΧΑΑ!AP52/ΧΑΑ!AP51) -> -0.02085823 | H53: =LN(ΧΑΑ!AX52/ΧΑΑ!AX51) -> 0.0051282164
A54: 09.01.2025 | B54: =LN(ΧΑΑ!B53/ΧΑΑ!B52) -> 0.0029495516 | C54: =LN(ΧΑΑ!J53/ΧΑΑ!J52) -> -0.0063492277 | D54: =LN(ΧΑΑ!R53/ΧΑΑ!R52) -> -0.0076775809 | E54: =LN(ΧΑΑ!Z53/ΧΑΑ!Z52) -> -0.0023188416 | F54: =LN(ΧΑΑ!AH53/ΧΑΑ!AH52) -> -0.018478308 | G54: =LN(ΧΑΑ!AP53/ΧΑΑ!AP52) -> 0.00058530877 | H54: =LN(ΧΑΑ!AX53/ΧΑΑ!AX52) -> 0.0046778737
A55: 10.01.2025 | B55: =LN(ΧΑΑ!B54/ΧΑΑ!B53) -> -0.0047766671 | C55: =LN(ΧΑΑ!J54/ΧΑΑ!J53) -> -0.0089571936 | D55: =LN(ΧΑΑ!R54/ΧΑΑ!R53) -> -0.0009638555 | E55: =LN(ΧΑΑ!Z54/ΧΑΑ!Z53) -> -0.002906134 | F55: =LN(ΧΑΑ!AH54/ΧΑΑ!AH53) -> 0.0079611212 | G55: =LN(ΧΑΑ!AP54/ΧΑΑ!AP53) -> -0.0088158079 | H55: =LN(ΧΑΑ!AX54/ΧΑΑ!AX53) -> -0.0059574644
A56: 13.01.2025 | B56: =LN(ΧΑΑ!B55/ΧΑΑ!B54) -> -0.0090249281 | C56: =LN(ΧΑΑ!J55/ΧΑΑ!J54) -> 0.0025673955 | D56: =LN(ΧΑΑ!R55/ΧΑΑ!R54) -> -0.012615403 | E56: =LN(ΧΑΑ!Z55/ΧΑΑ!Z54) -> -0.011120981 | F56: =LN(ΧΑΑ!AH55/ΧΑΑ!AH54) -> -0.0035304538 | G56: =LN(ΧΑΑ!AP55/ΧΑΑ!AP54) -> -0.022083858 | H56: =LN(ΧΑΑ!AX55/ΧΑΑ!AX54) -> -0.024628594
A57: 14.01.2025 | B57: =LN(ΧΑΑ!B56/ΧΑΑ!B55) -> 0.0019374329 | C57: =LN(ΧΑΑ!J56/ΧΑΑ!J55) -> 0.021560759 | D57: =LN(ΧΑΑ!R56/ΧΑΑ!R55) -> -0.00097703965 | E57: =LN(ΧΑΑ!Z56/ΧΑΑ!Z55) -> 0.0011764707 | F57: =LN(ΧΑΑ!AH56/ΧΑΑ!AH55) -> -0.00088456441 | G57: =LN(ΧΑΑ!AP56/ΧΑΑ!AP55) -> -0.0097029263 | H57: =LN(ΧΑΑ!AX56/ΧΑΑ!AX55) -> 0.020351428
A58: 15.01.2025 | B58: =LN(ΧΑΑ!B57/ΧΑΑ!B56) -> 0.0067216711 | C58: =LN(ΧΑΑ!J57/ΧΑΑ!J56) -> 0.0037570489 | D58: =LN(ΧΑΑ!R57/ΧΑΑ!R56) -> 0.00097703965 | E58: =LN(ΧΑΑ!Z57/ΧΑΑ!Z56) -> 0.016905095 | F58: =LN(ΧΑΑ!AH57/ΧΑΑ!AH56) -> -0.020563979 | G58: =LN(ΧΑΑ!AP57/ΧΑΑ!AP56) -> 0.0078907845 | H58: =LN(ΧΑΑ!AX57/ΧΑΑ!AX56) -> 0.0029959363
A59: 16.01.2025 | B59: =LN(ΧΑΑ!B58/ΧΑΑ!B57) -> 0.0024252423 | C59: =LN(ΧΑΑ!J58/ΧΑΑ!J57) -> -0.0050125418 | D59: =LN(ΧΑΑ!R58/ΧΑΑ!R57) -> -0.014756785 | E59: =LN(ΧΑΑ!Z58/ΧΑΑ!Z57) -> 0 | F59: =LN(ΧΑΑ!AH58/ΧΑΑ!AH57) -> -0.004526943 | G59: =LN(ΧΑΑ!AP58/ΧΑΑ!AP57) -> -0.0012099215 | H59: =LN(ΧΑΑ!AX58/ΧΑΑ!AX57) -> 0.017789542
A60: 17.01.2025 | B60: =LN(ΧΑΑ!B59/ΧΑΑ!B58) -> 0.011769887 | C60: =LN(ΧΑΑ!J59/ΧΑΑ!J58) -> 0.0093779993 | D60: =LN(ΧΑΑ!R59/ΧΑΑ!R58) -> 0.0029688295 | E60: =LN(ΧΑΑ!Z59/ΧΑΑ!Z58) -> 0.027367729 | F60: =LN(ΧΑΑ!AH59/ΧΑΑ!AH58) -> -0.022947313 | G60: =LN(ΧΑΑ!AP59/ΧΑΑ!AP58) -> -0.0012113872 | H60: =LN(ΧΑΑ!AX59/ΧΑΑ!AX58) -> 0.04434224
... A248: 17.10.2025 | B248: =LN(ΧΑΑ!B247/ΧΑΑ!B246) -> -0.013115991 | C248: =LN(ΧΑΑ!J247/ΧΑΑ!J246) -> 0.016269644 | D248: =LN(ΧΑΑ!R247/ΧΑΑ!R246) -> -0.010518504 | E248: =LN(ΧΑΑ!Z247/ΧΑΑ!Z246) -> 0.017451451 | F248: =LN(ΧΑΑ!AH247/ΧΑΑ!AH246) -> -0.0011448198 | G248: =LN(ΧΑΑ!AP247/ΧΑΑ!AP246) -> -0.0018779348 | H248: =LN(ΧΑΑ!AX247/ΧΑΑ!AX246) -> -0.028693462
A249: 20.10.2025 | B249: =LN(ΧΑΑ!B248/ΧΑΑ!B247) -> 0.0043727713 | C249: =LN(ΧΑΑ!J248/ΧΑΑ!J247) -> 0.0049958472 | D249: =LN(ΧΑΑ!R248/ΧΑΑ!R247) -> 0.00752449 | F249: =LN(ΧΑΑ!AH248/ΧΑΑ!AH247) -> 0.0011448198 | G249: =LN(ΧΑΑ!AP248/ΧΑΑ!AP247) -> -0.015629018 | H249: =LN(ΧΑΑ!AX248/ΧΑΑ!AX247) -> -0.0032395846
A250: 21.10.2025 | B250: =LN(ΧΑΑ!B249/ΧΑΑ!B248) -> 0.011465754 | C250: =LN(ΧΑΑ!J249/ΧΑΑ!J248) -> 0.0044198967 | D250: =LN(ΧΑΑ!R249/ΧΑΑ!R248) -> 0.0089552837 | F250: =LN(ΧΑΑ!AH249/ΧΑΑ!AH248) -> 0.0011435107 | G250: =LN(ΧΑΑ!AP249/ΧΑΑ!AP248) -> 0.022186419 | H250: =LN(ΧΑΑ!AX249/ΧΑΑ!AX248) -> 0.010563479
A251: 22.10.2025 | B251: =LN(ΧΑΑ!B250/ΧΑΑ!B249) -> 0.0072633929 | C251: =LN(ΧΑΑ!J250/ΧΑΑ!J249) -> 0.015317586 | D251: =LN(ΧΑΑ!R250/ΧΑΑ!R249) -> 0.0044477464 | F251: =LN(ΧΑΑ!AH250/ΧΑΑ!AH249) -> -0.0080321717 | G251: =LN(ΧΑΑ!AP250/ΧΑΑ!AP249) -> 0.027626066 | H251: =LN(ΧΑΑ!AX250/ΧΑΑ!AX249) -> 0.010741866

Sheet GREECE Markowitz
R1: OPAr | S1: AGNr | T1: ACBr | U1: HRMr | V1: MTLNr | W1: EURBr | Y1: ΧΑΡΤΟΦΥΛΑΚΙΟ
P2: AVERAGE (AEG) | R2: =AVERAGE(C5:C251) -> 0.00063142488 | S2: =AVERAGE(D5:D251) -> 0.0010856283 | T2: =AVERAGE(E5:E251) -> 0.0036312179 | U2: =AVERAGE(F5:F251) -> -0.0011107072 | V2: =AVERAGE(G5:G251) -> 0.0011806707 | W2: =AVERAGE(H5:H251) -> 0.0024505827 | Y2: =AVERAGE(R2:W2) -> 0.0013114695 | Z2: ΜΕΣΗ ΑΠΌΔΟΣΗ ΧΑΡΤΟΦΥΛΑΚΙΟΥ
A3: Trade Date | C3: OPAr | D3: AGNr | E3: ACBr | F3: HRMr | G3: MTLNr | H3: EURBr | J3: ΧΑΡΤΟΦΥΛΑΚΙΟ | L3: =B4 -> 0 | M3: ME | N3: =B256 -> 0 | P3: VARIANCE | R3: =VARP(C5:C251) -> 0.0002389505 | S3: =VARP(D5:D251) -> 0.00029754383 | T3: =VARP(E5:E251) -> 0.00057836034 | U3: =VARP(F5:F251) -> 0.00017390677 | V3: =VARP(G5:G251) -> 0.00035113043 | W3: =VARP(H5:H251) -> 0.00040863047 | Z3: ΔΙΑΚ. ΧΑΡΤΟΦΥΛΑΚΙΟΥ
P4: STAND DEV | R4: =SQRT(R3) -> 0.015458024 | S4: =SQRT(S3) -> 0.017249459 | T4: =SQRT(T3) -> 0.024049124 | U4: =SQRT(U3) -> 0.013187371 | V4: =SQRT(V3) -> 0.018738475 | W4: =SQRT(W3) -> 0.02021461 | Z4: ΤΥΠ.ΑΠΟΚΛ. ΧΑΡΤΟΦΥΛΑΚΙΟΥ
A5: 24.10.2024 | C5: ='GREECE Ret'!C5 -> -0.0019053674 | D5: ='GREECE Ret'!D5 -> 0.0057859371 | E5: ='GREECE Ret'!E5 -> -0.017538156 | F5: ='GREECE Ret'!F5 -> -0.0052677909 | G5: ='GREECE Ret'!G5 -> 0.010882816 | H5: ='GREECE Ret'!H5 -> 0.0050125418 | J5: =AVERAGE(C5:H5) -> -0.00050500317 | L5: ΠΙΝΑΚΑΣ ΣΥΝΔΙΑΚΥΜΑΝΣΕΩΝ | P5: COUNT | R5: =COUNT(C5:C251) -> 247 | S5: =COUNT(D5:D251) -> 247 | T5: =COUNT(E5:E251) -> 247 | U5: =COUNT(F5:F251) -> 247 | V5: =COUNT(G5:G251) -> 247 | W5: =COUNT(H5:H251) -> 247
A6: 25.10.2024 | C6: ='GREECE Ret'!C6 -> -0.0038216607 | D6: ='GREECE Ret'!D6 -> -0.024332101 | E6: ='GREECE Ret'!E6 -> -0.0085288363 | F6: ='GREECE Ret'!F6 -> 0.0035149421 | G6: ='GREECE Ret'!G6 -> -0.029288244 | H6: ='GREECE Ret'!H6 -> -0.010582109 | J6: =AVERAGE(C6:H6) -> -0.012173001 | L6: COVARIANCE MATRIX
A7: 29.10.2024 | C7: ='GREECE Ret'!C7 -> 0.006995259 | D7: ='GREECE Ret'!D7 -> -0.0019723872 | E7: ='GREECE Ret'!E7 -> 0.014878064 | F7: ='GREECE Ret'!F7 -> 0 | G7: ='GREECE Ret'!G7 -> 0.0030911926 | H7: ='GREECE Ret'!H7 -> 0.025211419 | J7: =AVERAGE(C7:H7) -> 0.0080339246 | L7: Δεδομενα/Αναλυση δεδομενων/Συνδιακυμανση
A8: 30.10.2024 | C8: ='GREECE Ret'!C8 -> -0.016613801 | D8: ='GREECE Ret'!D8 -> -0.01994084 | E8: ='GREECE Ret'!E8 -> -0.037253592 | F8: ='GREECE Ret'!F8 -> 0.013072082 | G8: ='GREECE Ret'!G8 -> 0.012270093 | H8: ='GREECE Ret'!H8 -> -0.014103133 | J8: =AVERAGE(C8:H8) -> -0.010428198 | L8: ΣΥΜΠΛΗΡΩΣΗ ΠΙΝΑΚΑ ΜΕ TRANSPOSE
A9: 31.10.2024 | C9: ='GREECE Ret'!C9 -> 0.0102565 | D9: ='GREECE Ret'!D9 -> 0.0040201059 | E9: ='GREECE Ret'!E9 -> 0.0072727593 | F9: ='GREECE Ret'!F9 -> 0.013757741 | G9: ='GREECE Ret'!G9 -> -0.022819368 | H9: ='GREECE Ret'!H9 -> -0.0058032344 | J9: =AVERAGE(C9:H9) -> 0.0011140839
A10: 01.11.2024 | C10: ='GREECE Ret'!C10 -> 0.00063755182 | D10: ='GREECE Ret'!D10 -> -0.0070458268 | E10: ='GREECE Ret'!E10 -> 0.015102768 | F10: ='GREECE Ret'!F10 -> -0.00085433581 | G10: ='GREECE Ret'!G10 -> -0.00062402498 | H10: ='GREECE Ret'!H10 -> 0.015227388 | J10: =AVERAGE(C10:H10) -> 0.0037405867 | M10: OPAr | N10: AGNr | O10: ACBr | P10: HRMr | Q10: MTLNr | R10: EURBr
A11: 04.11.2024 | C11: ='GREECE Ret'!C11 -> -0.028444064 | D11: ='GREECE Ret'!D11 -> -0.014242357 | E11: ='GREECE Ret'!E11 -> 0 | F11: ='GREECE Ret'!F11 -> -0.0017108644 | G11: ='GREECE Ret'!G11 -> -0.0031259794 | H11: ='GREECE Ret'!H11 -> 0.010883756 | J11: =AVERAGE(C11:H11) -> -0.0061065847 | L11: OPAr | M11: =VARP('GREECE Markowitz'!$C$5:$C$251) -> 0.0002389505
A12: 05.11.2024 | C12: ='GREECE Ret'!C12 -> 0.0019652807 | D12: ='GREECE Ret'!D12 -> 0.0040899853 | E12: ='GREECE Ret'!E12 -> 0.0092363001 | F12: ='GREECE Ret'!F12 -> -0.016400886 | G12: ='GREECE Ret'!G12 -> 0.0049968873 | H12: ='GREECE Ret'!H12 -> 0.01534557 | J12: =AVERAGE(C12:H12) -> 0.0032055229 | L12: AGNr | M12: 8.6918497e-05 | N12: =VARP('GREECE Markowitz'!$D$5:$D$251) -> 0.00029754383
A13: 06.11.2024 | C13: ='GREECE Ret'!C13 -> -0.01185004 | D13: ='GREECE Ret'!D13 -> -0.0010209291 | E13: ='GREECE Ret'!E13 -> 0.011950933 | F13: ='GREECE Ret'!F13 -> -0.0017421607 | G13: ='GREECE Ret'!G13 -> 0.0031104224 | H13: ='GREECE Ret'!H13 -> 0.010854581 | J13: =AVERAGE(C13:H13) -> 0.0018838011 | L13: ACBr | M13: 0.00015923942 | N13: 0.0001363572 | O13: =VARP('GREECE Markowitz'!$E$5:$E$251) -> 0.00057836034
A14: 07.11.2024 | C14: ='GREECE Ret'!C14 -> 0 | D14: ='GREECE Ret'!D14 -> 0.0010209291 | E14: ='GREECE Ret'!E14 -> -0.0035001786 | F14: ='GREECE Ret'!F14 -> -0.018478308 | G14: ='GREECE Ret'!G14 -> -0.0031104224 | H14: ='GREECE Ret'!H14 -> -0.0017590154 | J14: =AVERAGE(C14:H14) -> -0.0043044993 | L14: HRMr | M14: 8.5540557e-07 | N14: -1.6459102e-05 | O14: 2.8102689e-05 | P14: =VARP('GREECE Markowitz'!$F$5:$F$251) -> 0.00017390677
A15: 08.11.2024 | C15: ='GREECE Ret'!C15 -> -0.0026525214 | D15: ='GREECE Ret'!D15 -> 0.0050890695 | E15: ='GREECE Ret'!E15 -> 0.051924231 | F15: ='GREECE Ret'!F15 -> -0.0017777782 | G15: ='GREECE Ret'!G15 -> 0.014842573 | H15: ='GREECE Ret'!H15 -> 0.028268681 | J15: =AVERAGE(C15:H15) -> 0.015949043 | L15: MTLNr | M15: 9.7956966e-05 | N15: 0.00017136648 | O15: 0.00019921996 | P15: 1.241931e-05 | Q15: =VARP('GREECE Markowitz'!$G$5:$G$251) -> 0.00035113043
A16: 11.11.2024 | C16: ='GREECE Ret'!C16 -> 0.0046373054 | D16: ='GREECE Ret'!D16 -> 0.01711164 | E16: ='GREECE Ret'!E16 -> 0.046822597 | F16: ='GREECE Ret'!F16 -> -0.017048417 | G16: ='GREECE Ret'!G16 -> 0.019453501 | H16: ='GREECE Ret'!H16 -> -0.0049019706 | J16: =AVERAGE(C16:H16) -> 0.011012443 | L16: EURBr | M16: 0.00013694483 | N16: 0.00014880841 | O16: 0.00029244748 | P16: 9.812795e-06 | Q16: 0.00017909391 | R16: =VARP('GREECE Markowitz'!$H$5:$H$251) -> 0.00040863047
A17: 12.11.2024 | C17: ='GREECE Ret'!C17 -> -0.001984784 | D17: ='GREECE Ret'!D17 -> -0.012048339 | E17: ='GREECE Ret'!E17 -> 0.028805999 | F17: ='GREECE Ret'!F17 -> 0.022372298 | G17: ='GREECE Ret'!G17 -> -0.0066445427 | H17: ='GREECE Ret'!H17 -> -0.00049152127 | J17: =AVERAGE(C17:H17) -> 0.0050015184
A18: 13.11.2024 | C18: ='GREECE Ret'!C18 -> -0.0066445427 | D18: ='GREECE Ret'!D18 -> -0.010152371 | E18: ='GREECE Ret'!E18 -> -0.0093023927 | F18: ='GREECE Ret'!F18 -> -0.0079964886 | G18: ='GREECE Ret'!G18 -> -0.00060624434 | H18: ='GREECE Ret'!H18 -> -0.016857117 | J18: =AVERAGE(C18:H18) -> -0.0085931928
A19: 14.11.2024 | C19: ='GREECE Ret'!C19 -> 0.0059820717 | D19: ='GREECE Ret'!D19 -> 0.0050890695 | E19: ='GREECE Ret'!E19 -> 0.0012453302 | F19: ='GREECE Ret'!F19 -> 0.0079964886 | G19: ='GREECE Ret'!G19 -> 0.0066485588 | H19: ='GREECE Ret'!H19 -> -0.014352506 | J19: =AVERAGE(C19:H19) -> 0.0021015021 | M19: OPAr | N19: AGNr | O19: ACBr | P19: HRMr | Q19: MTLNr | R19: EURBr | T19: Wr
A20: 15.11.2024 | C20: ='GREECE Ret'!C20 -> 0.0033079752 | D20: ='GREECE Ret'!D20 -> -0.016377029 | E20: ='GREECE Ret'!E20 -> -0.017577351 | F20: ='GREECE Ret'!F20 -> -0.011571113 | G20: ='GREECE Ret'!G20 -> -0.0060423145 | H20: ='GREECE Ret'!H20 -> -0.00076113159 | J20: =AVERAGE(C20:H20) -> -0.0081701607 | L20: OPAr | M20: =M11 -> 0.0002389505 | N20: =M21 -> 8.6918497e-05 | O20: =M22 -> 0.00015923942 | P20: =M23 -> 8.5540557e-07 | Q20: =M24 -> 9.7956966e-05 | R20: =M25 -> 0.00013694483 | T20: =1/6 -> 0.16666667 | U20: OPAr
A21: 18.11.2024 | C21: ='GREECE Ret'!C21 -> -0.01062427 | D21: ='GREECE Ret'!D21 -> -0.016649708 | E21: ='GREECE Ret'!E21 -> -0.0095450932 | F21: ='GREECE Ret'!F21 -> 0.021258551 | G21: ='GREECE Ret'!G21 -> -0.020821328 | H21: ='GREECE Ret'!H21 -> 0.018109147 | J21: =AVERAGE(C21:H21) -> -0.0030454503 | L21: AGNr | M21: =M12 -> 8.6918497e-05 | N21: =N12 -> 0.00029754383 | O21: =N22 -> 0.0001363572 | P21: =N23 -> -1.6459102e-05 | Q21: =N24 -> 0.00017136648 | R21: =N25 -> 0.00014880841 | T21: =1/6 -> 0.16666667 | U21: AGNr | V21: MMULT(TRANSPOSE(COVRij-ER);(COVRij-ER))/n)
A22: 19.11.2024 | C22: ='GREECE Ret'!C22 -> -0.0087161128 | D22: ='GREECE Ret'!D22 -> -0.031985669 | E22: ='GREECE Ret'!E22 -> -0.017414178 | F22: ='GREECE Ret'!F22 -> -0.013233541 | G22: ='GREECE Ret'!G22 -> -0.050121496 | H22: ='GREECE Ret'!H22 -> -0.014562145 | J22: =AVERAGE(C22:H22) -> -0.02267219 | L22: ACBr | M22: =M13 -> 0.00015923942 | N22: =N13 -> 0.0001363572 | O22: =O13 -> 0.00057836034 | P22: =O23 -> 2.8102689e-05 | Q22: =O24 -> 0.00019921996 | R22: =O25 -> 0.00029244748 | T22: =1/6 -> 0.16666667 | U22: ACBr | V22: COVRij | W22: ΠΙΝΑΚΑΣ ΣΥΝΔΙΑΚΥΜΑΝΣΗΣ ΑΠΟΔΟΣΕΩΝ
A23: 20.11.2024 | C23: ='GREECE Ret'!C23 -> 0.012048339 | D23: ='GREECE Ret'!D23 -> 0.021437048 | E23: ='GREECE Ret'!E23 -> 0.011643081 | F23: ='GREECE Ret'!F23 -> -0.0098171248 | G23: ='GREECE Ret'!G23 -> 0.017414178 | H23: ='GREECE Ret'!H23 -> 0.0095646337 | J23: =AVERAGE(C23:H23) -> 0.010381692 | L23: HRMr | M23: =M14 -> 8.5540557e-07 | N23: =N14 -> -1.6459102e-05 | O23: =O14 -> 2.8102689e-05 | P23: =P14 -> 0.00017390677 | Q23: =P24 -> 1.241931e-05 | R23: =P25 -> 9.812795e-06 | T23: =1/6 -> 0.16666667 | U23: HRMr | V23: ER | W23: ΑΝΑΜΕΝΟΜΕΝΗ ΑΠΟΔΟΣΗ
A24: 21.11.2024 | C24: ='GREECE Ret'!C24 -> 0.017804625 | D24: ='GREECE Ret'!D24 -> 0.0010598835 | E24: ='GREECE Ret'!E24 -> 0.0051315058 | F24: ='GREECE Ret'!F24 -> 0.02480198 | G24: ='GREECE Ret'!G24 -> 0.0038289772 | H24: ='GREECE Ret'!H24 -> 0.02180463 | J24: =AVERAGE(C24:H24) -> 0.012405267 | L24: MTLNr | M24: =M15 -> 9.7956966e-05 | N24: =N15 -> 0.00017136648 | O24: =O15 -> 0.00019921996 | P24: =P15 -> 1.241931e-05 | Q24: =Q15 -> 0.00035113043 | R24: =Q25 -> 0.00017909391 | T24: =1/6 -> 0.16666667 | U24: MTLNr
A25: 22.11.2024 | C25: ='GREECE Ret'!C25 -> 0.032157112 | D25: ='GREECE Ret'!D25 -> 0.014721612 | E25: ='GREECE Ret'!E25 -> -0.020685935 | F25: ='GREECE Ret'!F25 -> 0 | G25: ='GREECE Ret'!G25 -> 0.009508788 | H25: ='GREECE Ret'!H25 -> -0.0019627092 | J25: =AVERAGE(C25:H25) -> 0.0056231446 | L25: EURBr | M25: =M16 -> 0.00013694483 | N25: =N16 -> 0.00014880841 | O25: =O16 -> 0.00029244748 | P25: =P16 -> 9.812795e-06 | Q25: =Q16 -> 0.00017909391 | R25: =R16 -> 0.00040863047 | T25: =1/6 -> 0.16666667 | U25: EURBr | V25: n= ΑΡΙΘΜΟΣ ΠΑΡΑΤΗΡΗΣΕΩΝ
A26: 25.11.2024 | C26: ='GREECE Ret'!C26 -> -0.015306421 | D26: ='GREECE Ret'!D26 -> 0.018614808 | E26: ='GREECE Ret'!E26 -> -0.0052390428 | F26: ='GREECE Ret'!F26 -> 0.00087450814 | G26: ='GREECE Ret'!G26 -> -0.0056944159 | H26: ='GREECE Ret'!H26 -> 0.0044106908 | J26: =AVERAGE(C26:H26) -> -0.00038997876 | T26: =SUM(T20:T25) -> 1
A27: 26.11.2024 | C27: ='GREECE Ret'!C27 -> 0.014039797 | D27: ='GREECE Ret'!D27 -> -0.010298752 | E27: ='GREECE Ret'!E27 -> -0.005266635 | F27: ='GREECE Ret'!F27 -> 0.0087032751 | G27: ='GREECE Ret'!G27 -> -0.0038143721 | H27: ='GREECE Ret'!H27 -> 0.0063368479 | J27: =AVERAGE(C27:H27) -> 0.0016166934 | L27: ΠΙΝΑΚΑΣ ΣΥΝΔΙΑΚΥΜΑΝΣΕΩΝ | U27: SUM(TRANSPOSE(W)*ER)
A28: 27.11.2024 | C28: ='GREECE Ret'!C28 -> 0.00063351285 | D28: ='GREECE Ret'!D28 -> 0.010298752 | E28: ='GREECE Ret'!E28 -> -0.016639319 | F28: ='GREECE Ret'!F28 -> -0.0087032751 | G28: ='GREECE Ret'!G28 -> -0.0044685679 | H28: ='GREECE Ret'!H28 -> -0.010747539 | J28: =AVERAGE(C28:H28) -> -0.0049377393 | L28: MMULT(TRANSPOSE(Rij-ER);(Rij-ER))/n | S28: {=SUM(TRANSPOSE(Wr)*AER)} -> 0.0013114695 | U28: Αναμενομενη Αποδοση Χαρτοφυλακιου
A29: 28.11.2024 | C29: ='GREECE Ret'!C29 -> -0.0082671377 | D29: ='GREECE Ret'!D29 -> -0.010298752 | E29: ='GREECE Ret'!E29 -> -0.0067340322 | F29: ='GREECE Ret'!F29 -> 0.0017467253 | G29: ='GREECE Ret'!G29 -> -0.0051315058 | H29: ='GREECE Ret'!H29 -> -0.012852377 | J29: =AVERAGE(C29:H29) -> -0.0069228465 | L29: Rij | M29: ΠΙΝΑΚΑΣ ΑΠΟΔΟΣΕΩΝ | S29: {=MMULT(MMULT(TRANSPOSE(Wr),COVij),Wr)} -> 0.00014818586 | U29: Συνδιακυμανση Χαρτοφυλακιου
A30: 29.11.2024 | C30: ='GREECE Ret'!C30 -> -0.0096247134 | D30: ='GREECE Ret'!D30 -> -0.018809332 | E30: ='GREECE Ret'!E30 -> -0.0088225886 | F30: ='GREECE Ret'!F30 -> 0.0017436796 | G30: ='GREECE Ret'!G30 -> -0.0012870015 | H30: ='GREECE Ret'!H30 -> -0.0049875415 | J30: =AVERAGE(C30:H30) -> -0.0069645829 | L30: ER | M30: ΑΝΑΜΕΝΟΜΕΝΗ ΑΠΟΔΟΣΗ | S30: =SQRT(S29) -> 0.012173161 | U30: Τυπικη Αποκλιση Χαρτοφυλακιου
A31: 02.12.2024 | C31: ='GREECE Ret'!C31 -> 0 | D31: ='GREECE Ret'!D31 -> 0.022941569 | E31: ='GREECE Ret'!E31 -> 0.047913356 | F31: ='GREECE Ret'!F31 -> 0.0026098318 | G31: ='GREECE Ret'!G31 -> 0.03666656 | H31: ='GREECE Ret'!H31 -> 0.054488185 | J31: =AVERAGE(C31:H31) -> 0.027436584 | L31: n= ΑΡΙΘΜΟΣ ΠΑΡΑΤΗΡΗΣΕΩΝ
A32: 03.12.2024 | C32: ='GREECE Ret'!C32 -> -0.012978768 | D32: ='GREECE Ret'!D32 -> 0.018386626 | E32: ='GREECE Ret'!E32 -> 0.011628038 | F32: ='GREECE Ret'!F32 -> -0.0069747449 | G32: ='GREECE Ret'!G32 -> -0.021330796 | H32: ='GREECE Ret'!H32 -> 0.015970278 | J32: =AVERAGE(C32:H32) -> 0.00078343899 | T32: MMULT(MMULT(TRANSPOSE(Wr);COVij);Wr)
A33: 04.12.2024 | C33: ='GREECE Ret'!C33 -> 0.011042658 | D33: ='GREECE Ret'!D33 -> 0.0020222454 | E33: ='GREECE Ret'!E33 -> 0.010223731 | F33: ='GREECE Ret'!F33 -> -0.0079051795 | G33: ='GREECE Ret'!G33 -> -0.014048762 | H33: ='GREECE Ret'!H33 -> 0.024397067 | J33: =AVERAGE(C33:H33) -> 0.0042886268 | T33: CTRL+SHIFT+ENTER
A34: 05.12.2024 | C34: ='GREECE Ret'!C34 -> 0.020461072 | D34: ='GREECE Ret'!D34 -> 0.027890254 | E34: ='GREECE Ret'!E34 -> 0.0362087 | F34: ='GREECE Ret'!F34 -> -0.0097475295 | G34: ='GREECE Ret'!G34 -> 0.031648211 | H34: ='GREECE Ret'!H34 -> 0.0095044843 | J34: =AVERAGE(C34:H34) -> 0.019327532
A35: 06.12.2024 | C35: ='GREECE Ret'!C35 -> 0.0056800405 | D35: ='GREECE Ret'!D35 -> -0.012852377 | E35: ='GREECE Ret'!E35 -> 0.0073305154 | F35: ='GREECE Ret'!F35 -> -0.017969935 | G35: ='GREECE Ret'!G35 -> 0.0055918133 | H35: ='GREECE Ret'!H35 -> 0.0071813594 | J35: =AVERAGE(C35:H35) -> -0.00083976392
A36: 09.12.2024 | C36: ='GREECE Ret'!C36 -> 0.0031416928 | D36: ='GREECE Ret'!D36 -> 0.012852377 | E36: ='GREECE Ret'!E36 -> 0.0030385924 | F36: ='GREECE Ret'!F36 -> 0 | G36: ='GREECE Ret'!G36 -> 0.017808269 | H36: ='GREECE Ret'!H36 -> 0.0062416609 | J36: =AVERAGE(C36:H36) -> 0.007180432
A37: 10.12.2024 | C37: ='GREECE Ret'!C37 -> -0.0012554929 | D37: ='GREECE Ret'!D37 -> -0.016840418 | E37: ='GREECE Ret'!E37 -> -0.016519189 | F37: ='GREECE Ret'!F37 -> -0.0045433972 | G37: ='GREECE Ret'!G37 -> -0.0042696009 | H37: ='GREECE Ret'!H37 -> -0.002224695 | J37: =AVERAGE(C37:H37) -> -0.0076087988
A38: 11.12.2024 | C38: ='GREECE Ret'!C38 -> -0.00062833807 | D38: ='GREECE Ret'!D38 -> -0.00099950033 | E38: ='GREECE Ret'!E38 -> -0.0037082861 | F38: ='GREECE Ret'!F38 -> 0.0081633106 | G38: ='GREECE Ret'!G38 -> 0.010942358 | H38: ='GREECE Ret'!H38 -> -0.0017833264 | J38: =AVERAGE(C38:H38) -> 0.001997703 | L38: Σεναρια Χαρτοφυλακιου | P38: ΕΛΑΧΙΣΤΟΠΟΙΗΣΗ ΚΙΝΔΥΝΟΥ | T38: ΜΕΓΙΣΤΟΠΟΙΗΣΗ ΚΕΡΔΟΥΣ
A39: 12.12.2024 | C39: ='GREECE Ret'!C39 -> 0.0068900993 | D39: ='GREECE Ret'!D39 -> 0.0099503309 | E39: ='GREECE Ret'!E39 -> 0.004324999 | F39: ='GREECE Ret'!F39 -> 0.0027063616 | G39: ='GREECE Ret'!G39 -> 0.021531932 | H39: ='GREECE Ret'!H39 -> -0.013929679 | J39: =AVERAGE(C39:H39) -> 0.005245674 | O39: Risk Minimized | T39: Return Maximized
A40: 13.12.2024 | C40: ='GREECE Ret'!C40 -> -0.0012492194 | D40: ='GREECE Ret'!D40 -> 0.019608471 | E40: ='GREECE Ret'!E40 -> -0.0012338064 | F40: ='GREECE Ret'!F40 -> -0.0099593399 | G40: ='GREECE Ret'!G40 -> 0.0094229201 | H40: ='GREECE Ret'!H40 -> 0.00090456813 | J40: =AVERAGE(C40:H40) -> 0.002915599 | M40: ΙΣΟΜΕΡΕΣ | O40: Min | P40: Long | Q40: 0% to 25% | R40: 8% to 25% | T40: Long | U40: 0% to 25% | V40: 8% to 25%
A41: 16.12.2024 | C41: ='GREECE Ret'!C41 -> -0.013845407 | D41: ='GREECE Ret'!D41 -> 0.0048426245 | E41: ='GREECE Ret'!E41 -> -0.0080570625 | F41: ='GREECE Ret'!F41 -> 0.0099593399 | G41: ='GREECE Ret'!G41 -> 0.0070093745 | H41: ='GREECE Ret'!H41 -> -0.0040770158 | J41: =AVERAGE(C41:H41) -> -0.00069469105 | M41: ΧΑΡΤΟΦΥΛΑΚΙΟ | O41: Var | P41: Only | Q41: Weights | R41: Weights | T41: Only | U41: Weights | V41: Weights
A42: 17.12.2024 | C42: ='GREECE Ret'!C42 -> -0.024375806 | D42: ='GREECE Ret'!D42 -> -0.0048426245 | E42: ='GREECE Ret'!E42 -> -0.013784679 | F42: ='GREECE Ret'!F42 -> 0.00896867 | G42: ='GREECE Ret'!G42 -> -0.0034985458 | H42: ='GREECE Ret'!H42 -> -0.0036380213 | J42: =AVERAGE(C42:H42) -> -0.0068618345 | L42: ΜΕΤΟΧΕΣ | N42: ΜΕΤΟΧΕΣ | O42: Portfolio | P42: Portfolio | Q42: Portfolio | R42: Portfolio | S42: ΜΕΤΟΧΕΣ | T42: Portfolio | U42: Portfolio | V42: Portfolio
A43: 18.12.2024 | C43: ='GREECE Ret'!C43 -> 0.021837734 | D43: ='GREECE Ret'!D43 -> 0 | E43: ='GREECE Ret'!E43 -> 0.005662173 | F43: ='GREECE Ret'!F43 -> -0.00089325598 | G43: ='GREECE Ret'!G43 -> -0.0046838493 | H43: ='GREECE Ret'!H43 -> 0.0072628553 | J43: =AVERAGE(C43:H43) -> 0.0048642761 | L43: OPAr | M43: =1/6 -> 0.16666667 | N43: OPAr | O43: 0.25337294 | P43: 0.24540735 | Q43: 0.25 | R43: 0.25 | S43: OPAr | T43: 0 | U43: 0 | V43: 0.08
A44: 19.12.2024 | C44: ='GREECE Ret'!C44 -> -0.00063552592 | D44: ='GREECE Ret'!D44 -> -0.0058422756 | E44: ='GREECE Ret'!E44 -> -0.0044011388 | F44: ='GREECE Ret'!F44 -> 0.020345682 | G44: ='GREECE Ret'!G44 -> -0.0082498995 | H44: ='GREECE Ret'!H44 -> 0.011243653 | J44: =AVERAGE(C44:H44) -> 0.0020767492 | L44: AGNr | M44: =1/6 -> 0.16666667 | N44: AGNr | O44: 0.20017504 | P44: 0.20130428 | Q44: 0.25 | R44: 0.25 | S44: AGNr | T44: 0 | U44: 0.25 | V44: 0.09
A45: 20.12.2024 | C45: ='GREECE Ret'!C45 -> -0.0025461503 | D45: ='GREECE Ret'!D45 -> -0.016740913 | E45: ='GREECE Ret'!E45 -> -0.0050537063 | F45: ='GREECE Ret'!F45 -> 0.0078500185 | G45: ='GREECE Ret'!G45 -> -0.011904903 | H45: ='GREECE Ret'!H45 -> 0.0062416609 | J45: =AVERAGE(C45:H45) -> -0.0036923321 | L45: ACBr | M45: =1/6 -> 0.16666667 | N45: ACBr | O45: -0.032477206 | P45: 0 | Q45: 0.0038250242 | R45: 0.08 | S45: ACBr | T45: 1 | U45: 0.25 | V45: 0.25
A46: 23.12.2024 | C46: ='GREECE Ret'!C46 -> -0.012183543 | D46: ='GREECE Ret'!D46 -> 0.00099255591 | E46: ='GREECE Ret'!E46 -> -0.0019017438 | F46: ='GREECE Ret'!F46 -> 0.016372619 | G46: ='GREECE Ret'!G46 -> -0.0066086152 | H46: ='GREECE Ret'!H46 -> -0.01162284 | J46: =AVERAGE(C46:H46) -> -0.0024919278 | L46: HRMr | M46: =1/6 -> 0.16666667 | N46: HRMr | O46: 0.493796 | P46: 0.49196907 | Q46: 0.25 | R46: 0.25 | S46: HRMr | T46: 0 | U46: 0 | V46: 0.08
A47: 27.12.2024 | C47: ='GREECE Ret'!C47 -> 0.010269667 | D47: ='GREECE Ret'!D47 -> 0.0019821612 | E47: ='GREECE Ret'!E47 -> 0.0025348556 | F47: ='GREECE Ret'!F47 -> -0.012037979 | G47: ='GREECE Ret'!G47 -> 0 | H47: ='GREECE Ret'!H47 -> 0.0049338517 | J47: =AVERAGE(C47:H47) -> 0.0012804261 | L47: MTLNr | M47: =1/6 -> 0.16666667 | N47: MTLNr | O47: 0.051271453 | P47: 0.044542871 | Q47: 0.15020574 | R47: 0.09 | S47: MTLNr | T47: 0 | U47: 0.25 | V47: 0.25
A48: 30.12.2024 | C48: ='GREECE Ret'!C48 -> -0.0038387763 | D48: ='GREECE Ret'!D48 -> -0.0089508305 | E48: ='GREECE Ret'!E48 -> 0.026235109 | F48: ='GREECE Ret'!F48 -> -0.0095611332 | G48: ='GREECE Ret'!G48 -> -0.0012062728 | H48: ='GREECE Ret'!H48 -> 0.0022346378 | J48: =AVERAGE(C48:H48) -> 0.00081878894 | L48: EURBr | M48: =1/6 -> 0.16666667 | N48: EURBr | O48: 0.033861762 | P48: 0.016776437 | Q48: 0.095969231 | R48: 0.08 | S48: EURBr | T48: 0 | U48: 0.25 | V48: 0.25
A49: 31.12.2024 | C49: ='GREECE Ret'!C49 -> 0.0063897981 | D49: ='GREECE Ret'!D49 -> 0.010929071 | E49: ='GREECE Ret'!E49 -> -0.0030873751 | F49: ='GREECE Ret'!F49 -> 0.008695707 | G49: ='GREECE Ret'!G49 -> 0.011401264 | H49: ='GREECE Ret'!H49 -> -0.0044742804 | J49: =AVERAGE(C49:H49) -> 0.0049756973 | L49: Αθροισμα | M49: =SUM(M43:M48) -> 1 | N49: Αθροισμα | O49: =SUM(O43:O48) -> 1 | P49: =SUM(P43:P48) -> 1 | Q49: =SUM(Q43:Q48) -> 1 | R49: =SUM(R43:R48) -> 1 | S49: ΑΘΡΟΙΣΜΑ | T49: =SUM(T43:T48) -> 1 | U49: =SUM(U43:U48) -> 1 | V49: =SUM(V43:V48) -> 1
A50: 02.01.2025 | C50: ='GREECE Ret'!C50 -> 0.0050826031 | D50: ='GREECE Ret'!D50 -> 0.0068931834 | E50: ='GREECE Ret'!E50 -> 0 | F50: ='GREECE Ret'!F50 -> -0.032558969 | G50: ='GREECE Ret'!G50 -> 0.02823717 | H50: ='GREECE Ret'!H50 -> 0.012034912 | J50: =AVERAGE(C50:H50) -> 0.0032814833
A51: 03.01.2025 | C51: ='GREECE Ret'!C51 -> -0.0025380724 | D51: ='GREECE Ret'!D51 -> 0.017510175 | E51: ='GREECE Ret'!E51 -> 0.020202707 | F51: ='GREECE Ret'!F51 -> 0.0089047783 | G51: ='GREECE Ret'!G51 -> 0.0017386269 | H51: ='GREECE Ret'!H51 -> 0.011891794 | J51: =AVERAGE(C51:H51) -> 0.0096183349 | L51: Αναμ. Αποδ. | M51: {=SUM(TRANSPOSE(M43:M48)*AER)} -> 0.0013114695 | N51: Αναμ. Αποδ. | O51: {=SUM(TRANSPOSE(O43:O48)*AER)} -> -0.00014557715 | P51: {=SUM(TRANSPOSE(P43:P48)*AER)} -> -7.9233143e-05 | Q51: {=SUM(TRANSPOSE(Q43:Q48)*AER)} -> 0.00057800006 | R51: {=SUM(TRANSPOSE(R43:R48)*AER)} -> 0.00074439092 | S51: Αναμ. Αποδ. | T51: {=SUM(TRANSPOSE(T43:T48)*AER)} -> 0.0036312179 | U51: {=SUM(TRANSPOSE(U43:U48)*AER)} -> 0.0020870249 | V51: {=SUM(TRANSPOSE(V43:V48)*AER)} -> 0.0018749818
A52: 07.01.2025 | C52: ='GREECE Ret'!C52 -> 0.015758284 | D52: ='GREECE Ret'!D52 -> 0.021936979 | E52: ='GREECE Ret'!E52 -> 0.031028742 | F52: ='GREECE Ret'!F52 -> 0.019315789 | G52: ='GREECE Ret'!G52 -> 0.0097955263 | H52: ='GREECE Ret'!H52 -> 0.021655242 | J52: =AVERAGE(C52:H52) -> 0.019915094 | L52: Διακ. | M52: {=MMULT(MMULT(TRANSPOSE(M43:M48),COVij),M43:M48)} -> 0.00014818586 | N52: Διακ. | O52: {=MMULT(MMULT(TRANSPOSE(O43:O48),COVij),O43:O48)} -> 8.2852838e-05 | P52: {=MMULT(MMULT(TRANSPOSE(P43:P48),COVij),P43:P48)} -> 8.3206886e-05 | Q52: {=MMULT(MMULT(TRANSPOSE(Q43:Q48),COVij),Q43:Q48)} -> 0.00010657687 | R52: {=MMULT(MMULT(TRANSPOSE(R43:R48),COVij),R43:R48)} -> 0.0001091154 | S52: Διακ. | T52: {=MMULT(MMULT(TRANSPOSE(T43:T48),COVij),T43:T48)} -> 0.00057836034 | U52: {=MMULT(MMULT(TRANSPOSE(U43:U48),COVij),U43:U48)} -> 0.00024314075 | V52: {=MMULT(MMULT(TRANSPOSE(V43:V48),COVij),V43:V48)} -> 0.00021187869
A53: 08.01.2025 | C53: ='GREECE Ret'!C53 -> -0.011953587 | D53: ='GREECE Ret'!D53 -> -0.013295542 | E53: ='GREECE Ret'!E53 -> 0.014581769 | F53: ='GREECE Ret'!F53 -> -0.0026121042 | G53: ='GREECE Ret'!G53 -> -0.02085823 | H53: ='GREECE Ret'!H53 -> 0.0051282164 | J53: =AVERAGE(C53:H53) -> -0.004834913
A54: 09.01.2025 | C54: ='GREECE Ret'!C54 -> -0.0063492277 | D54: ='GREECE Ret'!D54 -> -0.0076775809 | E54: ='GREECE Ret'!E54 -> -0.0023188416 | F54: ='GREECE Ret'!F54 -> -0.018478308 | G54: ='GREECE Ret'!G54 -> 0.00058530877 | H54: ='GREECE Ret'!H54 -> 0.0046778737 | J54: =AVERAGE(C54:H54) -> -0.004926796 | L54: Τυπικη Αποκλ. | M54: =SQRT(M52) -> 0.012173161 | N54: Τυπικη Αποκλ. | O54: =SQRT(O52) -> 0.0091023534 | P54: =SQRT(P52) -> 0.0091217809 | Q54: =SQRT(Q52) -> 0.010323607 | R54: =SQRT(R52) -> 0.010445832 | S54: Τυπικη Αποκλ. | T54: =SQRT(T52) -> 0.024049124 | U54: =SQRT(U52) -> 0.015592971 | V54: =SQRT(V52) -> 0.014556053
A55: 10.01.2025 | C55: ='GREECE Ret'!C55 -> -0.0089571936 | D55: ='GREECE Ret'!D55 -> -0.0009638555 | E55: ='GREECE Ret'!E55 -> -0.002906134 | F55: ='GREECE Ret'!F55 -> 0.0079611212 | G55: ='GREECE Ret'!G55 -> -0.0088158079 | H55: ='GREECE Ret'!H55 -> -0.0059574644 | J55: =AVERAGE(C55:H55) -> -0.0032732224
A56: 13.01.2025 | C56: ='GREECE Ret'!C56 -> 0.0025673955 | D56: ='GREECE Ret'!D56 -> -0.012615403 | E56: ='GREECE Ret'!E56 -> -0.011120981 | F56: ='GREECE Ret'!F56 -> -0.0035304538 | G56: ='GREECE Ret'!G56 -> -0.022083858 | H56: ='GREECE Ret'!H56 -> -0.024628594 | J56: =AVERAGE(C56:H56) -> -0.011901982 | L56: Data/Solver | N56: CV | O56: =O54/O51 -> -62.525975 | P56: =P54/P51 -> -115.12582 | Q56: =Q54/Q51 -> 17.860911 | R56: =R54/R51 -> 14.032723 | T56: =T54/T51 -> 6.6228808 | U56: =U54/U51 -> 7.4713872 | V56: =V54/V51 -> 7.7633038
A57: 14.01.2025 | C57: ='GREECE Ret'!C57 -> 0.021560759 | D57: ='GREECE Ret'!D57 -> -0.00097703965 | E57: ='GREECE Ret'!E57 -> 0.0011764707 | F57: ='GREECE Ret'!F57 -> -0.00088456441 | G57: ='GREECE Ret'!G57 -> -0.0097029263 | H57: ='GREECE Ret'!H57 -> 0.020351428 | J57: =AVERAGE(C57:H57) -> 0.0052540212 | L57: MIN-MAX
A58: 15.01.2025 | C58: ='GREECE Ret'!C58 -> 0.0037570489 | D58: ='GREECE Ret'!D58 -> 0.00097703965 | E58: ='GREECE Ret'!E58 -> 0.016905095 | F58: ='GREECE Ret'!F58 -> -0.020563979 | G58: ='GREECE Ret'!G58 -> 0.0078907845 | H58: ='GREECE Ret'!H58 -> 0.0029959363 | J58: =AVERAGE(C58:H58) -> 0.0019936542
A59: 16.01.2025 | C59: ='GREECE Ret'!C59 -> -0.0050125418 | D59: ='GREECE Ret'!D59 -> -0.014756785 | E59: ='GREECE Ret'!E59 -> 0 | F59: ='GREECE Ret'!F59 -> -0.004526943 | G59: ='GREECE Ret'!G59 -> -0.0012099215 | H59: ='GREECE Ret'!H59 -> 0.017789542 | J59: =AVERAGE(C59:H59) -> -0.0012861083
A60: 17.01.2025 | C60: ='GREECE Ret'!C60 -> 0.0093779993 | D60: ='GREECE Ret'!D60 -> 0.0029688295 | E60: ='GREECE Ret'!E60 -> 0.027367729 | F60: ='GREECE Ret'!F60 -> -0.022947313 | G60: ='GREECE Ret'!G60 -> -0.0012113872 | H60: ='GREECE Ret'!H60 -> 0.04434224 | J60: =AVERAGE(C60:H60) -> 0.0099830162
A61: 20.01.2025 | C61: ='GREECE Ret'!C61 -> 0.0049658699 | D61: ='GREECE Ret'!D61 -> -0.0039604012 | E61: ='GREECE Ret'!E61 -> -0.0073384467 | F61: ='GREECE Ret'!F61 -> -0.022536165 | G61: ='GREECE Ret'!G61 -> 0.027497249 | H61: ='GREECE Ret'!H61 -> -0.016194686 | J61: =AVERAGE(C61:H61) -> -0.0029277632
A62: 21.01.2025 | C62: ='GREECE Ret'!C62 -> -0.010582109 | D62: ='GREECE Ret'!D62 -> 0.055945156 | E62: ='GREECE Ret'!E62 -> 0.0016982738 | F62: ='GREECE Ret'!F62 -> 0.028091735 | G62: ='GREECE Ret'!G62 -> 0.011140543 | H62: ='GREECE Ret'!H62 -> 0.01055633 | J62: =AVERAGE(C62:H62) -> 0.016141655
A63: 22.01.2025 | C63: ='GREECE Ret'!C63 -> 0.010582109 | D63: ='GREECE Ret'!D63 -> 0.03048735 | E63: ='GREECE Ret'!E63 -> -0.028688141 | F63: ='GREECE Ret'!F63 -> -0.01207632 | G63: ='GREECE Ret'!G63 -> -0.013501819 | H63: ='GREECE Ret'!H63 -> -0.034514519 | J63: =AVERAGE(C63:H63) -> -0.0079518899
A64: 23.01.2025 | C64: ='GREECE Ret'!C64 -> 0.001855862 | D64: ='GREECE Ret'!D64 -> -0.026742027 | E64: ='GREECE Ret'!E64 -> -0.0011648225 | F64: ='GREECE Ret'!F64 -> -0.028437935 | G64: ='GREECE Ret'!G64 -> -0.0035524016 | H64: ='GREECE Ret'!H64 -> -0.00083647014 | J64: =AVERAGE(C64:H64) -> -0.0098129658
A65: 24.01.2025 | C65: ='GREECE Ret'!C65 -> 0.016549566 | D65: ='GREECE Ret'!D65 -> 0.013921339 | E65: ='GREECE Ret'!E65 -> 0.016185324 | F65: ='GREECE Ret'!F65 -> -0.0038535693 | G65: ='GREECE Ret'!G65 -> 0.022868191 | H65: ='GREECE Ret'!H65 -> 0.014538158 | J65: =AVERAGE(C65:H65) -> 0.013368168
A66: 27.01.2025 | C66: ='GREECE Ret'!C66 -> 0 | D66: ='GREECE Ret'!D66 -> -0.012053924 | E66: ='GREECE Ret'!E66 -> 0.024356911 | F66: ='GREECE Ret'!F66 -> 0.0019286409 | G66: ='GREECE Ret'!G66 -> -0.014598799 | H66: ='GREECE Ret'!H66 -> -0.0062047769 | J66: =AVERAGE(C66:H66) -> -0.0010953248
A67: 28.01.2025 | C67: ='GREECE Ret'!C67 -> 0.01328522 | D67: ='GREECE Ret'!D67 -> 0.012975159 | E67: ='GREECE Ret'!E67 -> -0.0011198209 | F67: ='GREECE Ret'!F67 -> 0.0095878012 | G67: ='GREECE Ret'!G67 -> 0.01169604 | H67: ='GREECE Ret'!H67 -> 0.0082645098 | J67: =AVERAGE(C67:H67) -> 0.009114818
A68: 29.01.2025 | C68: ='GREECE Ret'!C68 -> 0.0077681896 | D68: ='GREECE Ret'!D68 -> -0.007393749 | E68: ='GREECE Ret'!E68 -> 0.01390843 | F68: ='GREECE Ret'!F68 -> 0.011385322 | G68: ='GREECE Ret'!G68 -> 0.0057971177 | H68: ='GREECE Ret'!H68 -> 0 | J68: =AVERAGE(C68:H68) -> 0.0052442184
A69: 30.01.2025 | C69: ='GREECE Ret'!C69 -> -0.016201975 | D69: ='GREECE Ret'!D69 -> 0.0083141357 | E69: ='GREECE Ret'!E69 -> 0 | F69: ='GREECE Ret'!F69 -> -0.0047281412 | G69: ='GREECE Ret'!G69 -> 0.0023094698 | H69: ='GREECE Ret'!H69 -> 0.0032867737 | J69: =AVERAGE(C69:H69) -> -0.0011699561
... A251: 22.10.2025 | C251: ='GREECE Ret'!C251 -> 0.015317586 | D251: ='GREECE Ret'!D251 -> 0.0044477464 | E251: ='GREECE Ret'!E251 -> 0 | F251: ='GREECE Ret'!F251 -> -0.0080321717 | G251: ='GREECE Ret'!G251 -> 0.027626066 | H251: ='GREECE Ret'!H251 -> 0.010741866 | J251: =AVERAGE(C251:H251) -> 0.0083501821

Sheet USA Markowitz
R1: V | S1: JNJ | T1: KO | U1: AAPL | V1: TSLA | W1: MSFT | Y1: ΧΑΡΤΟΦΥΛΑΚΙΟ
P2: AVERAGE (AEG) | R2: =AVERAGE(C5:C251) -> 0.00078422671 | S2: =AVERAGE(D5:D251) -> 0.0006286225 | T2: =AVERAGE(E5:E251) -> 2.5516987e-05 | U2: =AVERAGE(F5:F251) -> 0.00051774051 | V2: =AVERAGE(G5:G251) -> 0.0029926354 | W2: =AVERAGE(H5:H251) -> 0.00079550224 | Y2: =AVERAGE(R2:W2) -> 0.00095737406 | Z2: ΜΕΣΗ ΑΠΌΔΟΣΗ ΧΑΡΤΟΦΥΛΑΚΙΟΥ
A3: Trade Date | C3: V | D3: JNJ | E3: KO | F3: AAPL | G3: TSLA | H3: MSFT | J3: ΧΑΡΤΟΦΥΛΑΚΙΟ | L3: =B4 -> 0 | M3: ME | N3: =B256 -> 0 | P3: VARIANCE | R3: =VARP(C5:C251) -> 0.00019994236 | S3: =VARP(D5:D251) -> 0.00014990084 | T3: =VARP(E5:E251) -> 0.00011553534 | U3: =VARP(F5:F251) -> 0.00041772405 | V3: =VARP(G5:G251) -> 0.0019554379 | W3: =VARP(H5:H251) -> 0.00024005438 | Z3: ΔΙΑΚ. ΧΑΡΤΟΦΥΛΑΚΙΟΥ
P4: STAND DEV | R4: =SQRT(R3) -> 0.014140098 | S4: =SQRT(S3) -> 0.0122434 | T4: =SQRT(T3) -> 0.010748737 | U4: =SQRT(U3) -> 0.020438299 | V4: =SQRT(V3) -> 0.044220333 | W4: =SQRT(W3) -> 0.015493688 | Z4: ΤΥΠ.ΑΠΟΚΛ. ΧΑΡΤΟΦΥΛΑΚΙΟΥ
A5: 24.10.2024 | C5: ='USA Ret'!C5 -> -0.0019048297 | D5: ='USA Ret'!D5 -> -0.013291854 | E5: ='USA Ret'!E5 -> -0.010494517 | F5: ='USA Ret'!F5 -> -0.00082370542 | G5: ='USA Ret'!G5 -> 0.19818692 | H5: ='USA Ret'!H5 -> 0.00030612365 | J5: =AVERAGE(C5:H5) -> 0.028663023 | L5: ΠΙΝΑΚΑΣ ΣΥΝΔΙΑΚΥΜΑΝΣΕΩΝ | P5: COUNT | R5: =COUNT(C5:C251) -> 247 | S5: =COUNT(D5:D251) -> 247 | T5: =COUNT(E5:E251) -> 247 | U5: =COUNT(F5:F251) -> 247 | V5: =COUNT(G5:G251) -> 247 | W5: =COUNT(H5:H251) -> 247
A6: 25.10.2024 | C6: ='USA Ret'!C6 -> -0.0052748153 | D6: ='USA Ret'!D6 -> -0.01719346 | E6: ='USA Ret'!E6 -> -0.0056623605 | F6: ='USA Ret'!F6 -> 0.0036365251 | G6: ='USA Ret'!G6 -> 0.032891367 | H6: ='USA Ret'!H6 -> 0.0080199286 | J6: =AVERAGE(C6:H6) -> 0.0027361975 | L6: COVARIANCE MATRIX
A7: 28.10.2024 | C7: ='USA Ret'!C7 -> 0.0086938631 | D7: ='USA Ret'!D7 -> 0.0044654006 | E7: ='USA Ret'!E7 -> -0.0037427995 | F7: ='USA Ret'!F7 -> 0.0085626908 | G7: ='USA Ret'!G7 -> -0.025128273 | H7: ='USA Ret'!H7 -> -0.0036502369 | J7: =AVERAGE(C7:H7) -> -0.0017998925 | L7: Δεδομενα/Αναλυση δεδομενων/Συνδιακυμανση
A8: 29.10.2024 | C8: ='USA Ret'!C8 -> -0.0081615801 | D8: ='USA Ret'!D8 -> -0.009387989 | E8: ='USA Ret'!E8 -> -0.016789323 | F8: ='USA Ret'!F8 -> 0.0011561437 | G8: ='USA Ret'!G8 -> -0.011455406 | H8: ='USA Ret'!H8 -> 0.012486476 | J8: =AVERAGE(C8:H8) -> -0.0053586129 | L8: ΣΥΜΠΛΗΡΩΣΗ ΠΙΝΑΚΑ ΜΕ TRANSPOSE
A9: 30.10.2024 | C9: ='USA Ret'!C9 -> 0.028951047 | D9: ='USA Ret'!D9 -> 0.003242909 | E9: ='USA Ret'!E9 -> 0.0054761317 | F9: ='USA Ret'!F9 -> -0.015395867 | G9: ='USA Ret'!G9 -> -0.0076198949 | H9: ='USA Ret'!H9 -> 0.0013418473 | J9: =AVERAGE(C9:H9) -> 0.0026660288
A10: 31.10.2024 | C10: ='USA Ret'!C10 -> -0.0010689472 | D10: ='USA Ret'!D10 -> -0.0046806339 | E10: ='USA Ret'!E10 -> -0.0092967217 | F10: ='USA Ret'!F10 -> -0.018377307 | G10: ='USA Ret'!G10 -> -0.030353138 | H10: ='USA Ret'!H10 -> -0.062436831 | J10: =AVERAGE(C10:H10) -> -0.021035597 | M10: V | N10: JNJ | O10: KO | P10: AAPL | Q10: TSLA | R10: MSFT
A11: 01.11.2024 | C11: ='USA Ret'!C11 -> 0.0030658492 | D11: ='USA Ret'!D11 -> 0.0016875531 | E11: ='USA Ret'!E11 -> -0.0046040597 | F11: ='USA Ret'!F11 -> -0.013368587 | G11: ='USA Ret'!G11 -> -0.0034881658 | H11: ='USA Ret'!H11 -> 0.0098443346 | J11: =AVERAGE(C11:H11) -> -0.001143846 | L11: V | M11: =VARP('USA Markowitz'!$C$5:$C$253) -> 0.00019870188
A12: 04.11.2024 | C12: ='USA Ret'!C12 -> 0.0038105747 | D12: ='USA Ret'!D12 -> -0.011873117 | E12: ='USA Ret'!E12 -> 0.001537043 | F12: ='USA Ret'!F12 -> -0.0040456767 | G12: ='USA Ret'!G12 -> -0.024969782 | H12: ='USA Ret'!H12 -> -0.0046652015 | J12: =AVERAGE(C12:H12) -> -0.0067010266 | L12: JNJ | M12: 4.7393231e-05 | N12: =VARP('USA Markowitz'!$D$5:$D$253) -> 0.00014920758
A13: 05.11.2024 | C13: ='USA Ret'!C13 -> 0.004921909 | D13: ='USA Ret'!D13 -> 0.00069490511 | E13: ='USA Ret'!E13 -> 0.0039852904 | F13: ='USA Ret'!F13 -> 0.0064652495 | G13: ='USA Ret'!G13 -> 0.034801602 | H13: ='USA Ret'!H13 -> 0.0073178198 | J13: =AVERAGE(C13:H13) -> 0.009697796 | L13: KO | M13: 4.6415951e-05 | N13: 5.7104033e-05 | O13: =VARP('USA Markowitz'!$E$5:$E$253) -> 0.0001210824
A14: 06.11.2024 | C14: ='USA Ret'!C14 -> 0.04698795 | D14: ='USA Ret'!D14 -> -0.0029725222 | E14: ='USA Ret'!E14 -> -0.025878875 | F14: ='USA Ret'!F14 -> -0.0032722982 | G14: ='USA Ret'!G14 -> 0.13759467 | H14: ='USA Ret'!H14 -> 0.020971381 | J14: =AVERAGE(C14:H14) -> 0.028905052 | L14: AAPL | M14: 0.00014238356 | N14: 1.9645716e-05 | O14: 2.5199718e-05 | P14: =VARP('USA Markowitz'!$F$5:$F$253) -> 0.00041554757
A15: 07.11.2024 | C15: ='USA Ret'!C15 -> -0.0052185376 | D15: ='USA Ret'!D15 -> -0.0073106711 | E15: ='USA Ret'!E15 -> -0.00062814072 | F15: ='USA Ret'!F15 -> 0.021146945 | G15: ='USA Ret'!G15 -> 0.028629996 | H15: ='USA Ret'!H15 -> 0.012417231 | J15: =AVERAGE(C15:H15) -> 0.0081728038 | L15: TSLA | M15: 0.00024618883 | N15: -2.8139139e-05 | O15: -4.5899344e-05 | P15: 0.0004283895 | Q15: =VARP('USA Markowitz'!$G$5:$G$253) -> 0.0019409976
A16: 08.11.2024 | C16: ='USA Ret'!C16 -> 0.0067463225 | D16: ='USA Ret'!D16 -> -0.0080717927 | E16: ='USA Ret'!E16 -> 0.0040758796 | F16: ='USA Ret'!F16 -> -0.0022885319 | G16: ='USA Ret'!G16 -> 0.078697184 | H16: ='USA Ret'!H16 -> -0.0068163053 | J16: =AVERAGE(C16:H16) -> 0.012057126 | L16: MSFT | M16: 7.8620272e-05 | N16: -2.8017441e-05 | O16: -1.6774539e-05 | P16: 0.00016029589 | Q16: 0.00030584148 | R16: =VARP('USA Markowitz'!$H$5:$H$253) -> 0.00023821959
A17: 11.11.2024 | C17: ='USA Ret'!C17 -> 0.0098580284 | D17: ='USA Ret'!D17 -> -0.0027696388 | E17: ='USA Ret'!E17 -> -0.008799554 | F17: ='USA Ret'!F17 -> -0.01210148 | G17: ='USA Ret'!G17 -> 0.085806908 | H17: ='USA Ret'!H17 -> -0.010778761 | J17: =AVERAGE(C17:H17) -> 0.010202584
A18: 12.11.2024 | C18: ='USA Ret'!C18 -> -0.003447335 | D18: ='USA Ret'!D18 -> -0.01560094 | E18: ='USA Ret'!E18 -> -0.0025284464 | F18: ='USA Ret'!F18 -> 0 | G18: ='USA Ret'!G18 -> -0.063426758 | H18: ='USA Ret'!H18 -> 0.011937743 | J18: =AVERAGE(C18:H18) -> -0.012177623
A19: 13.11.2024 | C19: ='USA Ret'!C19 -> -0.0011948397 | D19: ='USA Ret'!D19 -> 0.0039231121 | E19: ='USA Ret'!E19 -> -0.0031695748 | F19: ='USA Ret'!F19 -> 0.0039612826 | G19: ='USA Ret'!G19 -> 0.0053132668 | H19: ='USA Ret'!H19 -> 0.005116548 | J19: =AVERAGE(C19:H19) -> 0.0023249658 | M19: V | N19: JNJ | O19: KO | P19: AAPL | Q19: TSLA | R19: MSFT | T19: Wr
A20: 14.11.2024 | C20: ='USA Ret'!C20 -> -0.0039823276 | D20: ='USA Ret'!D20 -> -0.0089804281 | E20: ='USA Ret'!E20 -> -0.0071684895 | F20: ='USA Ret'!F20 -> 0.013676483 | G20: ='USA Ret'!G20 -> -0.05944814 | H20: ='USA Ret'!H20 -> 0.0039667223 | J20: =AVERAGE(C20:H20) -> -0.010322697 | L20: V | M20: =M11 -> 0.00019870188 | N20: =M21 -> 4.7393231e-05 | O20: =M22 -> 4.6415951e-05 | P20: =M23 -> 0.00014238356 | Q20: =M24 -> 0.00024618883 | R20: =M25 -> 7.8620272e-05 | T20: =1/6 -> 0.16666667 | U20: V
A21: 15.11.2024 | C21: ='USA Ret'!C21 -> 0.0044991903 | D21: ='USA Ret'!D21 -> 0.013927711 | E21: ='USA Ret'!E21 -> -0.013034218 | F21: ='USA Ret'!F21 -> -0.014209674 | G21: ='USA Ret'!G21 -> 0.030196945 | H21: ='USA Ret'!H21 -> -0.028247849 | J21: =AVERAGE(C21:H21) -> -0.001144649 | L21: JNJ | M21: =M12 -> 4.7393231e-05 | N21: =N12 -> 0.00014920758 | O21: =N22 -> 5.7104033e-05 | P21: =N23 -> 1.9645716e-05 | Q21: =N24 -> -2.8139139e-05 | R21: =N25 -> -2.8017441e-05 | T21: =1/6 -> 0.16666667 | U21: JNJ | V21: MMULT(TRANSPOSE(COVRij-ER);(COVRij-ER))/n)
A22: 18.11.2024 | C22: ='USA Ret'!C22 -> 0.0081055445 | D22: ='USA Ret'!D22 -> 0.0049875415 | E22: ='USA Ret'!E22 -> 0.0019417482 | F22: ='USA Ret'!F22 -> 0.013332942 | G22: ='USA Ret'!G22 -> 0.054664383 | H22: ='USA Ret'!H22 -> 0.0018296505 | J22: =AVERAGE(C22:H22) -> 0.014143635 | L22: KO | M22: =M13 -> 4.6415951e-05 | N22: =N13 -> 5.7104033e-05 | O22: =O13 -> 0.0001210824 | P22: =O23 -> 2.5199718e-05 | Q22: =O24 -> -4.5899344e-05 | R22: =O25 -> -1.6774539e-05 | T22: =1/6 -> 0.16666667 | U22: KO | V22: COVRij | W22: ΠΙΝΑΚΑΣ ΣΥΝΔΙΑΚΥΜΑΝΣΗΣ ΑΠΟΔΟΣΕΩΝ
A23: 19.11.2024 | C23: ='USA Ret'!C23 -> -0.0009935739 | D23: ='USA Ret'!D23 -> -0.011502223 | E23: ='USA Ret'!E23 -> 0.011731754 | F23: ='USA Ret'!F23 -> 0.0011396013 | G23: ='USA Ret'!G23 -> 0.021205924 | H23: ='USA Ret'!H23 -> 0.0048707432 | J23: =AVERAGE(C23:H23) -> 0.0044087042 | L23: AAPL | M23: =M14 -> 0.00014238356 | N23: =N14 -> 1.9645716e-05 | O23: =O14 -> 2.5199718e-05 | P23: =P14 -> 0.00041554757 | Q23: =P24 -> 0.0004283895 | R23: =P25 -> 0.00016029589 | T23: =1/6 -> 0.16666667 | U23: AAPL | V23: ER | W23: ΑΝΑΜΕΝΟΜΕΝΗ ΑΠΟΔΟΣΗ
A24: 20.11.2024 | C24: ='USA Ret'!C24 -> -0.014405003 | D24: ='USA Ret'!D24 -> 0.00071869592 | E24: ='USA Ret'!E24 -> 0.0063704627 | F24: ='USA Ret'!F24 -> 0.0031490579 | G24: ='USA Ret'!G24 -> -0.011540323 | H24: ='USA Ret'!H24 -> -0.0055203673 | J24: =AVERAGE(C24:H24) -> -0.0035379128 | L24: TSLA | M24: =M15 -> 0.00024618883 | N24: =N15 -> -2.8139139e-05 | O24: =O15 -> -4.5899344e-05 | P24: =P15 -> 0.0004283895 | Q24: =Q15 -> 0.0019409976 | R24: =Q25 -> 0.00030584148 | T24: =1/6 -> 0.16666667 | U24: TSLA
A25: 21.11.2024 | C25: ='USA Ret'!C25 -> 0.0081323651 | D25: ='USA Ret'!D25 -> 0.015489114 | E25: ='USA Ret'!E25 -> 0.012150051 | F25: ='USA Ret'!F25 -> -0.0020982697 | G25: ='USA Ret'!G25 -> -0.0070122194 | H25: ='USA Ret'!H25 -> -0.0063257732 | J25: =AVERAGE(C25:H25) -> 0.0033892113 | L25: MSFT | M25: =M16 -> 7.8620272e-05 | N25: =N16 -> -2.8017441e-05 | O25: =O16 -> -1.6774539e-05 | P25: =P16 -> 0.00016029589 | Q25: =Q16 -> 0.00030584148 | R25: =R16 -> 0.00023821959 | T25: =1/6 -> 0.16666667 | U25: MSFT | V25: n= ΑΡΙΘΜΟΣ ΠΑΡΑΤΗΡΗΣΕΩΝ
A26: 22.11.2024 | C26: ='USA Ret'!C26 -> 6.4534865e-05 | D26: ='USA Ret'!D26 -> -0.0021244415 | E26: ='USA Ret'!E26 -> 0.002506267 | F26: ='USA Ret'!F26 -> 0.0058901979 | G26: ='USA Ret'!G26 -> 0.037334587 | H26: ='USA Ret'!H26 -> 0.0099534484 | J26: =AVERAGE(C26:H26) -> 0.0089374323 | T26: =SUM(T20:T25) -> 1
A27: 25.11.2024 | C27: ='USA Ret'!C27 -> 0.010495835 | D27: ='USA Ret'!D27 -> 0.0039234654 | E27: ='USA Ret'!E27 -> 0.0071707244 | F27: ='USA Ret'!F27 -> 0.012966426 | G27: ='USA Ret'!G27 -> -0.040430885 | H27: ='USA Ret'!H27 -> 0.0042833792 | J27: =AVERAGE(C27:H27) -> -0.00026517567 | U27: SUM(TRANSPOSE(W)*ER)
A28: 26.11.2024 | C28: ='USA Ret'!C28 -> -0.0043839369 | D28: ='USA Ret'!D28 -> -0.0081212177 | E28: ='USA Ret'!E28 -> 0.0026370914 | F28: ='USA Ret'!F28 -> 0.0093604428 | G28: ='USA Ret'!G28 -> -0.0010637985 | H28: ='USA Ret'!H28 -> 0.02173023 | J28: =AVERAGE(C28:H28) -> 0.0033598018 | S28: {=SUM(TRANSPOSE(Wr)*AER)} -> 0.0013114695 | U28: Αναμενομενη Αποδοση Χαρτοφυλακιου
A29: 27.11.2024 | C29: ='USA Ret'!C29 -> 0.0091937058 | D29: ='USA Ret'!D29 -> 0.0056789001 | E29: ='USA Ret'!E29 -> -0.0018607541 | F29: ='USA Ret'!F29 -> -0.00055320327 | G29: ='USA Ret'!G29 -> -0.015914032 | H29: ='USA Ret'!H29 -> -0.011751293 | J29: =AVERAGE(C29:H29) -> -0.0025344461 | S29: {=MMULT(MMULT(TRANSPOSE(Wr),COVij),Wr)} -> 0.00016502922 | U29: Συνδιακυμανση Χαρτοφυλακιου
A30: 29.11.2024 | C30: ='USA Ret'!C30 -> 0.0012067708 | D30: ='USA Ret'!D30 -> -0.002512807 | E30: ='USA Ret'!E30 -> -0.0054470604 | F30: ='USA Ret'!F30 -> 0.01016398 | G30: ='USA Ret'!G30 -> 0.036195973 | H30: ='USA Ret'!H30 -> 0.0011105205 | J30: =AVERAGE(C30:H30) -> 0.0067862295 | S30: =SQRT(S29) -> 0.01284637 | U30: Τυπικη Αποκλιση Χαρτοφυλακιου
A31: 02.12.2024 | C31: ='USA Ret'!C31 -> 0.0049704881 | D31: ='USA Ret'!D31 -> -0.0013556698 | E31: ='USA Ret'!E31 -> -0.0067329778 | F31: ='USA Ret'!F31 -> 0.0094775514 | G31: ='USA Ret'!G31 -> 0.033979773 | H31: ='USA Ret'!H31 -> 0.017602627 | J31: =AVERAGE(C31:H31) -> 0.0096569653
A32: 03.12.2024 | C32: ='USA Ret'!C32 -> -0.011561924 | D32: ='USA Ret'!D32 -> -0.01588782 | E32: ='USA Ret'!E32 -> -0.0020445081 | F32: ='USA Ret'!F32 -> 0.012690947 | G32: ='USA Ret'!G32 -> -0.016005762 | H32: ='USA Ret'!H32 -> 0.00051033428 | J32: =AVERAGE(C32:H32) -> -0.005383122 | T32: MMULT(MMULT(TRANSPOSE(USW);USCOVij);USW)
A33: 04.12.2024 | C33: ='USA Ret'!C33 -> -0.0099854741 | D33: ='USA Ret'!D33 -> -0.012482413 | E33: ='USA Ret'!E33 -> -0.020839058 | F33: ='USA Ret'!F33 -> 0.0014825189 | G33: ='USA Ret'!G33 -> 0.018355347 | H33: ='USA Ret'!H33 -> 0.014321812 | J33: =AVERAGE(C33:H33) -> -0.0015245445 | T33: CTRL+SHIFT+ENTER
A34: 05.12.2024 | C34: ='USA Ret'!C34 -> -0.0026495217 | D34: ='USA Ret'!D34 -> -0.0063335656 | E34: ='USA Ret'!E34 -> 0.01134832 | F34: ='USA Ret'!F34 -> 0.00012344409 | G34: ='USA Ret'!G34 -> 0.03178624 | H34: ='USA Ret'!H34 -> 0.011817782 | J34: =AVERAGE(C34:H34) -> 0.0076821164
A35: 06.12.2024 | C35: ='USA Ret'!C35 -> 0.0062249229 | D35: ='USA Ret'!D35 -> -0.0014054816 | E35: ='USA Ret'!E35 -> -0.0062176366 | F35: ='USA Ret'!F35 -> -0.00082324859 | G35: ='USA Ret'!G35 -> 0.05202106 | H35: ='USA Ret'!H35 -> 0.0021440106 | J35: =AVERAGE(C35:H35) -> 0.0086572711
A36: 09.12.2024 | C36: ='USA Ret'!C36 -> -0.0087517311 | D36: ='USA Ret'!D36 -> 0.001940384 | E36: ='USA Ret'!E36 -> 0.0011188365 | F36: ='USA Ret'!F36 -> 0.015972888 | G36: ='USA Ret'!G36 -> 0.0014633961 | H36: ='USA Ret'!H36 -> 0.0055081694 | J36: =AVERAGE(C36:H36) -> 0.0028753238
A37: 10.12.2024 | C37: ='USA Ret'!C37 -> 0.013147061 | D37: ='USA Ret'!D37 -> -0.0024763256 | E37: ='USA Ret'!E37 -> 0.0049398555 | F37: ='USA Ret'!F37 -> 0.0041252182 | G37: ='USA Ret'!G37 -> 0.028328357 | H37: ='USA Ret'!H37 -> -0.0060493803 | J37: =AVERAGE(C37:H37) -> 0.0070024642
A38: 11.12.2024 | C38: ='USA Ret'!C38 -> 0.0045035769 | D38: ='USA Ret'!D38 -> -0.017508136 | E38: ='USA Ret'!E38 -> -0.0043010819 | F38: ='USA Ret'!F38 -> -0.0051794718 | G38: ='USA Ret'!G38 -> 0.057611357 | H38: ='USA Ret'!H38 -> 0.012686202 | J38: =AVERAGE(C38:H38) -> 0.0079687409 | L38: Σεναρια Χαρτοφυλακιου | P38: ΕΛΑΧΙΣΤΟΠΟΙΗΣΗ ΚΙΝΔΥΝΟΥ | T38: ΜΕΓΙΣΤΟΠΟΙΗΣΗ ΚΕΡΔΟΥΣ
A39: 12.12.2024 | C39: ='USA Ret'!C39 -> 0.0014012295 | D39: ='USA Ret'!D39 -> -0.0027314958 | E39: ='USA Ret'!E39 -> 0.018975901 | F39: ='USA Ret'!F39 -> 0.0059460181 | G39: ='USA Ret'!G39 -> -0.015827208 | H39: ='USA Ret'!H39 -> 0.0012687109 | J39: =AVERAGE(C39:H39) -> 0.0015055261 | O39: Risk Minimized | T39: Return Maximized
A40: 13.12.2024 | C40: ='USA Ret'!C40 -> 0.0016216993 | D40: ='USA Ret'!D40 -> 0.0025950981 | E40: ='USA Ret'!E40 -> -0.011342277 | F40: ='USA Ret'!F40 -> 0.00068535954 | G40: ='USA Ret'!G40 -> 0.042448989 | H40: ='USA Ret'!H40 -> -0.0051068875 | J40: =AVERAGE(C40:H40) -> 0.0051503303 | M40: ΙΣΟΜΕΡΕΣ | O40: Min | P40: Long | Q40: 0% to 25% | R40: 8% to 25% | T40: Long | U40: 0% to 25% | V40: 8% to 25%
A41: 16.12.2024 | C41: ='USA Ret'!C41 -> 0.0036471505 | D41: ='USA Ret'!D41 -> -0.019073116 | E41: ='USA Ret'!E41 -> -0.0090714396 | F41: ='USA Ret'!F41 -> 0.011659487 | G41: ='USA Ret'!G41 -> 0.059600623 | H41: ='USA Ret'!H41 -> 0.0096122494 | J41: =AVERAGE(C41:H41) -> 0.0093958256 | M41: ΧΑΡΤΟΦΥΛΑΚΙΟ | O41: Var | P41: Only | Q41: Weights | R41: Weights | T41: Only | U41: Weights | V41: Weights
A42: 17.12.2024 | C42: ='USA Ret'!C42 -> 0.0076002826 | D42: ='USA Ret'!D42 -> 0.017639815 | E42: ='USA Ret'!E42 -> 0.013497625 | F42: ='USA Ret'!F42 -> 0.0096726355 | G42: ='USA Ret'!G42 -> 0.035724145 | H42: ='USA Ret'!H42 -> 0.0063352124 | J42: =AVERAGE(C42:H42) -> 0.015078286 | L42: ΜΕΤΟΧΕΣ | N42: ΜΕΤΟΧΕΣ | O42: Portfolio | P42: Portfolio | Q42: Portfolio | R42: Portfolio | S42: ΜΕΤΟΧΕΣ | T42: Portfolio | U42: Portfolio | V42: Portfolio
A43: 18.12.2024 | C43: ='USA Ret'!C43 -> -0.027131966 | D43: ='USA Ret'!D43 -> -0.011402789 | E43: ='USA Ret'!E43 -> -0.0087129264 | F43: ='USA Ret'!F43 -> -0.021654586 | G43: ='USA Ret'!G43 -> -0.086424257 | H43: ='USA Ret'!H43 -> -0.038284655 | J43: =AVERAGE(C43:H43) -> -0.03226853 | L43: V | M43: =1/6 -> 0.16666667 | N43: V | O43: 0.033419299 | P43: 0.015084057 | Q43: 0.23208822 | R43: 0.092314759 | S43: V | T43: 0 | U43: 0.25 | V43: 0.09
A44: 19.12.2024 | C44: ='USA Ret'!C44 -> 0.016329246 | D44: ='USA Ret'!D44 -> -0.0081157453 | E44: ='USA Ret'!E44 -> -0.0063846985 | F44: ='USA Ret'!F44 -> 0.0069902261 | G44: ='USA Ret'!G44 -> -0.0090380622 | H44: ='USA Ret'!H44 -> -0.00082340299 | J44: =AVERAGE(C44:H44) -> -0.00017373952 | L44: JNJ | M44: =1/6 -> 0.16666667 | N44: JNJ | O44: 0.3000896 | P44: 0.30091579 | Q44: 0.25 | R44: 0.25 | S44: JNJ | T44: 0 | U44: 0 | V44: 0.08
A45: 20.12.2024 | C45: ='USA Ret'!C45 -> 0.0089474032 | D45: ='USA Ret'!D45 -> 0.0061795024 | E45: ='USA Ret'!E45 -> 0.0016000003 | F45: ='USA Ret'!F45 -> 0.018640978 | G45: ='USA Ret'!G45 -> -0.035256734 | H45: ='USA Ret'!H45 -> -0.00098439851 | J45: =AVERAGE(C45:H45) -> -0.00014554154 | L45: KO | M45: =1/6 -> 0.16666667 | N45: KO | O45: 0.37669484 | P45: 0.3800102 | Q45: 0.25 | R45: 0.25 | S45: KO | T45: 0 | U45: 0 | V45: 0.08
A46: 23.12.2024 | C46: ='USA Ret'!C46 -> -0.0015434775 | D46: ='USA Ret'!D46 -> 0.0055222063 | E46: ='USA Ret'!E46 -> -0.0027215257 | F46: ='USA Ret'!F46 -> 0.003060266 | G46: ='USA Ret'!G46 -> 0.022404244 | H46: ='USA Ret'!H46 -> -0.0030968655 | J46: =AVERAGE(C46:H46) -> 0.0039374745 | L46: AAPL | M46: =1/6 -> 0.16666667 | N46: AAPL | O46: -0.025524796 | P46: 0 | Q46: 0.017911776 | R46: 0.08 | S46: AAPL | T46: 0 | U46: 0.25 | V46: 0.25
A47: 24.12.2024 | C47: ='USA Ret'!C47 -> 0.010754646 | D47: ='USA Ret'!D47 -> 0.0039846164 | E47: ='USA Ret'!E47 -> 0.0073471022 | F47: ='USA Ret'!F47 -> 0.01141267 | G47: ='USA Ret'!G47 -> 0.070991183 | H47: ='USA Ret'!H47 -> 0.0093302605 | J47: =AVERAGE(C47:H47) -> 0.01897008 | L47: TSLA | M47: =1/6 -> 0.16666667 | N47: TSLA | O47: -0.005783505 | P47: 0 | Q47: 0 | R47: 0.08 | S47: TSLA | T47: 1 | U47: 0.25 | V47: 0.25
A48: 25.12.2024 | C48: ='USA Ret'!C48 -> 0.00081052439 | D48: ='USA Ret'!D48 -> -0.0018529326 | E48: ='USA Ret'!E48 -> -0.0043058834 | F48: ='USA Ret'!F48 -> 0.0031708004 | G48: ='USA Ret'!G48 -> -0.017787267 | H48: ='USA Ret'!H48 -> -0.0027808187 | J48: =AVERAGE(C48:H48) -> -0.0037909296 | L48: MSFT | M48: =1/6 -> 0.16666667 | N48: MSFT | O48: 0.32110456 | P48: 0.30398996 | Q48: 0.25 | R48: 0.24768524 | S48: MSFT | T48: 0 | U48: 0.25 | V48: 0.25
A49: 26.12.2024 | C49: ='USA Ret'!C49 -> -0.0070360063 | D49: ='USA Ret'!D49 -> -0.0036472531 | E49: ='USA Ret'!E49 -> -0.0019196934 | F49: ='USA Ret'!F49 -> -0.013330681 | G49: ='USA Ret'!G49 -> -0.050745259 | H49: ='USA Ret'!H49 -> -0.017453013 | J49: =AVERAGE(C49:H49) -> -0.015688651 | L49: Αθροισμα | M49: =SUM(M43:M48) -> 1 | N49: Αθροισμα | O49: =SUM(O43:O48) -> 1 | P49: =SUM(P43:P48) -> 1 | Q49: =SUM(Q43:Q48) -> 1 | R49: =SUM(R43:R48) -> 1 | S49: Άθροισμα | T49: =SUM(T43:T48) -> 1 | U49: =SUM(U43:U48) -> 1 | V49: =SUM(V43:V48) -> 1
A50: 27.12.2024 | C50: ='USA Ret'!C50 -> -0.010568422 | D50: ='USA Ret'!D50 -> -0.01185908 | E50: ='USA Ret'!E50 -> -0.0067480976 | F50: ='USA Ret'!F50 -> -0.013352175 | G50: ='USA Ret'!G50 -> -0.033569289 | H50: ='USA Ret'!H50 -> -0.013327919 | J50: =AVERAGE(C50:H50) -> -0.014904164
A51: 30.12.2024 | C51: ='USA Ret'!C51 -> 0.002312506 | D51: ='USA Ret'!D51 -> 0.0088901822 | E51: ='USA Ret'!E51 -> 0.003701026 | F51: ='USA Ret'!F51 -> -0.0070829153 | G51: ='USA Ret'!G51 -> -0.033050192 | H51: ='USA Ret'!H51 -> -0.0078693115 | J51: =AVERAGE(C51:H51) -> -0.0055164508 | L51: Αναμ. Αποδ. | M51: {=SUM(TRANSPOSE(M43:M48)*AER)} -> 0.0013114695 | N51: Αναμ. Αποδ. | O51: {=SUM(TRANSPOSE(O43:O48)*AER)} -> 0.002523164 | P51: {=SUM(TRANSPOSE(P43:P48)*AER)} -> 0.0024610595 | Q51: {=SUM(TRANSPOSE(Q43:Q48)*AER)} -> 0.0019185088 | R51: {=SUM(TRANSPOSE(R43:R48)*AER)} -> 0.0018500716 | S51: Αναμ. Αποδ. | T51: {=SUM(TRANSPOSE(T43:T48)*AER)} -> 0.0011806707 | U51: {=SUM(TRANSPOSE(U43:U48)*AER)} -> 0.00078799276 | V51: {=SUM(TRANSPOSE(V43:V48)*AER)} -> 0.0010643125
A52: 31.12.2024 | C52: ='USA Ret'!C52 -> -0.0052027273 | D52: ='USA Ret'!D52 -> -0.0041574339 | E52: ='USA Ret'!E52 -> -0.0067687607 | F52: ='USA Ret'!F52 -> -0.026586226 | G52: ='USA Ret'!G52 -> -0.062744041 | H52: ='USA Ret'!H52 -> -0.0069517469 | J52: =AVERAGE(C52:H52) -> -0.018735156 | L52: Διακ. | M52: {=MMULT(MMULT(TRANSPOSE(M43:M48),COVij),M43:M48)} -> 0.00016502922 | N52: Διακ. | O52: {=MMULT(MMULT(TRANSPOSE(O43:O48),COVij),O43:O48)} -> 5.8534439e-05 | P52: {=MMULT(MMULT(TRANSPOSE(P43:P48),COVij),P43:P48)} -> 5.8796895e-05 | Q52: {=MMULT(MMULT(TRANSPOSE(Q43:Q48),COVij),Q43:Q48)} -> 6.7187696e-05 | R52: {=MMULT(MMULT(TRANSPOSE(R43:R48),COVij),R43:R48)} -> 8.6326657e-05 | S52: Διακ. | T52: {=MMULT(MMULT(TRANSPOSE(T43:T48),COVij),T43:T48)} -> 0.0019409976 | U52: {=MMULT(MMULT(TRANSPOSE(U43:U48),COVij),U43:U48)} -> 0.00034480661 | V52: {=MMULT(MMULT(TRANSPOSE(V43:V48),COVij),V43:V48)} -> 0.00029747405
A53: 02.01.2025 | C53: ='USA Ret'!C53 -> 0.0016208232 | D53: ='USA Ret'!D53 -> 0.0011796955 | E53: ='USA Ret'!E53 -> -0.0014564288 | F53: ='USA Ret'!F53 -> -0.0020114536 | G53: ='USA Ret'!G53 -> 0.078955036 | H53: ='USA Ret'!H53 -> 0.01133123 | J53: =AVERAGE(C53:H53) -> 0.014936484
A54: 03.01.2025 | C54: ='USA Ret'!C54 -> -0.0059559058 | D54: ='USA Ret'!D54 -> -0.0036824777 | E54: ='USA Ret'!E54 -> -0.015339726 | F54: ='USA Ret'!F54 -> 0.006716382 | G54: ='USA Ret'!G54 -> 0.0014851066 | H54: ='USA Ret'!H54 -> 0.010573407 | J54: =AVERAGE(C54:H54) -> -0.0010338691 | L54: Τυπικη Αποκλ. | M54: =SQRT(M52) -> 0.01284637 | N54: Τυπικη Αποκλ. | O54: =SQRT(O52) -> 0.0076507803 | P54: =SQRT(P52) -> 0.0076679134 | Q54: =SQRT(Q52) -> 0.0081968101 | R54: =SQRT(R52) -> 0.009291214 | S54: Τυπικη Αποκλ. | T54: =SQRT(T52) -> 0.044056755 | U54: =SQRT(U52) -> 0.018568969 | V54: =SQRT(V52) -> 0.017247436
A55: 06.01.2025 | C55: ='USA Ret'!C55 -> -0.0043860422 | D55: ='USA Ret'!D55 -> 0.017731328 | E55: ='USA Ret'!E55 -> 0.00049321826 | F55: ='USA Ret'!F55 -> -0.011453092 | G55: ='USA Ret'!G55 -> -0.041450664 | H55: ='USA Ret'!H55 -> -0.01289096 | J55: =AVERAGE(C55:H55) -> -0.0086593686
A56: 07.01.2025 | C56: ='USA Ret'!C56 -> 0.0029794822 | D56: ='USA Ret'!D56 -> -0.027454064 | E56: ='USA Ret'!E56 -> 0.014198525 | F56: ='USA Ret'!F56 -> 0.0020209943 | G56: ='USA Ret'!G56 -> 0.0014696569 | H56: ='USA Ret'!H56 -> 0.0051716314 | J56: =AVERAGE(C56:H56) -> -0.00026896237 | L56: Data/Solver | N56: CV | O56: =O54/O51 -> 3.0322168 | P56: =P54/P51 -> 3.115696 | Q56: =Q54/Q51 -> 4.2724903 | R56: =R54/R51 -> 5.0220833 | T56: =T54/T51 -> 37.315024 | U56: =U54/U51 -> 23.564898 | V56: =V54/V51 -> 16.205237
A57: 08.01.2025 | C57: ='USA Ret'!C57 -> -0.015766637 | D57: ='USA Ret'!D57 -> -0.0014771571 | E57: ='USA Ret'!E57 -> -0.010425245 | F57: ='USA Ret'!F57 -> -0.024399083 | G57: ='USA Ret'!G57 -> -0.0005065343 | H57: ='USA Ret'!H57 -> -0.013301757 | J57: =AVERAGE(C57:H57) -> -0.010979402 | L57: MIN-MAX
A58: 10.01.2025 | C58: ='USA Ret'!C58 -> -0.0025706537 | D58: ='USA Ret'!D58 -> 0.01682237 | E58: ='USA Ret'!E58 -> 0.0094524824 | F58: ='USA Ret'!F58 -> -0.010397972 | G58: ='USA Ret'!G58 -> 0.021478177 | H58: ='USA Ret'!H58 -> -0.0042098275 | J58: =AVERAGE(C58:H58) -> 0.0050957627
A59: 13.01.2025 | C59: ='USA Ret'!C59 -> 0.0070453693 | D59: ='USA Ret'!D59 -> 0.0019362429 | E59: ='USA Ret'!E59 -> 0.0063061087 | F59: ='USA Ret'!F59 -> -0.0047896089 | G59: ='USA Ret'!G59 -> -0.017382608 | H59: ='USA Ret'!H59 -> -0.0036500773 | J59: =AVERAGE(C59:H59) -> -0.0017557622
A60: 14.01.2025 | C60: ='USA Ret'!C60 -> 0.022995401 | D60: ='USA Ret'!D60 -> 0.001518708 | E60: ='USA Ret'!E60 -> -0.0043615286 | F60: ='USA Ret'!F60 -> 0.019484857 | G60: ='USA Ret'!G60 -> 0.077314193 | H60: ='USA Ret'!H60 -> 0.025275105 | J60: =AVERAGE(C60:H60) -> 0.023704456
A61: 15.01.2025 | C61: ='USA Ret'!C61 -> 0.0030622094 | D61: ='USA Ret'!D61 -> 0.019130186 | E61: ='USA Ret'!E61 -> 0.0077407256 | F61: ='USA Ret'!F61 -> -0.041238976 | G61: ='USA Ret'!G61 -> -0.034205986 | H61: ='USA Ret'!H61 -> -0.0040663362 | J61: =AVERAGE(C61:H61) -> -0.0082630293
A62: 16.01.2025 | C62: ='USA Ret'!C62 -> 0.0074426836 | D62: ='USA Ret'!D62 -> -0.0050203633 | E62: ='USA Ret'!E62 -> 0.0073623892 | F62: ='USA Ret'!F62 -> 0.0075070185 | G62: ='USA Ret'!G62 -> 0.03018127 | H62: ='USA Ret'!H62 -> 0.010426402 | J62: =AVERAGE(C62:H62) -> 0.0096499
A63: 17.01.2025 | C63: ='USA Ret'!C63 -> 0.012468098 | D63: ='USA Ret'!D63 -> 0.0075886264 | E63: ='USA Ret'!E63 -> -0.0046351877 | F63: ='USA Ret'!F63 -> -0.032436231 | G63: ='USA Ret'!G63 -> -0.005713831 | H63: ='USA Ret'!H63 -> -0.0012361085 | J63: =AVERAGE(C63:H63) -> -0.0039941057
A64: 21.01.2025 | C64: ='USA Ret'!C64 -> -0.00021631978 | D64: ='USA Ret'!D64 -> -0.019631194 | E64: ='USA Ret'!E64 -> -0.010306049 | F64: ='USA Ret'!F64 -> 0.0053307179 | G64: ='USA Ret'!G64 -> -0.021354991 | H64: ='USA Ret'!H64 -> 0.040476544 | J64: =AVERAGE(C64:H64) -> -0.00095021533
A65: 22.01.2025 | C65: ='USA Ret'!C65 -> 0.014269079 | D65: ='USA Ret'!D65 -> 0.0093865236 | E65: ='USA Ret'!E65 -> -0.0040548267 | F65: ='USA Ret'!F65 -> -0.00075979355 | G65: ='USA Ret'!G65 -> -0.006598291 | H65: ='USA Ret'!H65 -> 0.0011423325 | J65: =AVERAGE(C65:H65) -> 0.0022308374
A66: 23.01.2025 | C66: ='USA Ret'!C66 -> 0.0060448841 | D66: ='USA Ret'!D66 -> 0.0012267432 | E66: ='USA Ret'!E66 -> 0.0063183685 | F66: ='USA Ret'!F66 -> -0.0039423042 | G66: ='USA Ret'!G66 -> -0.014164543 | H66: ='USA Ret'!H66 -> -0.0059499261 | J66: =AVERAGE(C66:H66) -> -0.0017444629
A67: 24.01.2025 | C67: ='USA Ret'!C67 -> 0.013057922 | D67: ='USA Ret'!D67 -> 0.040511362 | E67: ='USA Ret'!E67 -> 0.031006538 | F67: ='USA Ret'!F67 -> 0.031285691 | G67: ='USA Ret'!G67 -> -0.023466669 | H67: ='USA Ret'!H67 -> -0.021625664 | J67: =AVERAGE(C67:H67) -> 0.011794864
A68: 27.01.2025 | C68: ='USA Ret'!C68 -> -0.00017936684 | D68: ='USA Ret'!D68 -> -0.016553285 | E68: ='USA Ret'!E68 -> -0.023925723 | F68: ='USA Ret'!F68 -> 0.035892086 | G68: ='USA Ret'!G68 -> 0.0023640673 | H68: ='USA Ret'!H68 -> 0.028671897 | J68: =AVERAGE(C68:H68) -> 0.0043782793
A69: 28.01.2025 | C69: ='USA Ret'!C69 -> 0.0041768663 | D69: ='USA Ret'!D69 -> 0.0051072973 | E69: ='USA Ret'!E69 -> 0.0075086222 | F69: ='USA Ret'!F69 -> 0.0046061804 | G69: ='USA Ret'!G69 -> -0.02284173 | H69: ='USA Ret'!H69 -> -0.010949712 | J69: =AVERAGE(C69:H69) -> -0.0020654127
... A253: 21.10.2025 | C253: ='USA Ret'!C253 -> -0.005342433 | D253: ='USA Ret'!D253 -> 0.0055090831 | E253: ='USA Ret'!E253 -> -0.0057734442 | F253: ='USA Ret'!F253 -> -0.016576873 | G253: ='USA Ret'!G253 -> -0.008235354 | H253: ='USA Ret'!H253 -> 0.0055480782 | J253: =AVERAGE(C253:H253) -> -0.0041451572

Sheet GREECE Sharpe
A1: ΑΠΌ | B1: ΕΩΣ
A2: 43531 | B2: 43897 | D2: OPAr | E2: AGNr | F2: ACBr | G2: HRMr | H2: MTLNr | I2: EURBr
D3: R1 | E3: R2 | F3: R3 | G3: R4 | H3: R5 | I3: R6
B4: μ | D4: ='GREECE Ret'!O7 -> 0.00063142488 | E4: ='GREECE Ret'!P7 -> 0.0010856283 | F4: ='GREECE Ret'!Q7 -> 0.003675864 | G4: ='GREECE Ret'!R7 -> -0.0011107072 | H4: ='GREECE Ret'!S7 -> 0.0011806707 | I4: ='GREECE Ret'!T7 -> 0.0024505827
B5: σ^2 | D5: ='GREECE Ret'!O8 -> 0.0002389505 | E5: ='GREECE Ret'!P8 -> 0.00029754383 | F5: ='GREECE Ret'!Q8 -> 0.00058530722 | G5: ='GREECE Ret'!R8 -> 0.00017390677 | H5: ='GREECE Ret'!S8 -> 0.00035113043 | I5: ='GREECE Ret'!T8 -> 0.00040863047
B6: σ | D6: ='GREECE Ret'!O9 -> 0.015458024 | E6: ='GREECE Ret'!P9 -> 0.017249459 | F6: ='GREECE Ret'!Q9 -> 0.024193123 | G6: ='GREECE Ret'!R9 -> 0.013187371 | H6: ='GREECE Ret'!S9 -> 0.018738475 | I6: ='GREECE Ret'!T9 -> 0.02021461
B8: σ/μ | D8: ='GREECE Ret'!O11 -> 24.481176 | E8: ='GREECE Ret'!P11 -> 15.888917 | F8: ='GREECE Ret'!Q11 -> 6.5816154 | G8: ='GREECE Ret'!R11 -> -11.872951 | H8: ='GREECE Ret'!S11 -> 15.871043 | I8: ='GREECE Ret'!T11 -> 8.2488995
A9: Μέγεθος δείγματος | B9: n | D9: ='GREECE Ret'!O16 -> 247 | E9: ='GREECE Ret'!P16 -> 247 | F9: ='GREECE Ret'!Q16 -> 244 | G9: ='GREECE Ret'!R16 -> 247 | H9: ='GREECE Ret'!S16 -> 247 | I9: ='GREECE Ret'!T16 -> 247
A11: INTERCEPT | B11: αλφα | D11: ='GREECE Ret'!O13 -> -0.00052391234 | E11: ='GREECE Ret'!P13 -> -0.00024363003 | F11: ='GREECE Ret'!Q13 -> 0.0017567453 | G11: ='GREECE Ret'!R13 -> -0.0011375575 | H11: ='GREECE Ret'!S13 -> -0.00044591077 | I11: ='GREECE Ret'!T13 -> 0.00031996985
A12: SLOPE | B12: βητα | D12: ='GREECE Ret'!O14 -> 0.7745517 | E12: ='GREECE Ret'!P14 -> 0.89115049 | F12: ='GREECE Ret'!Q14 -> 1.3559992 | G12: ='GREECE Ret'!R14 -> 0.018000746 | H12: ='GREECE Ret'!S14 -> 1.0904794 | I12: ='GREECE Ret'!T14 -> 1.428388
B13: RFR | C13: ='ΟΜΟΛΟΓΑ ΧΑΑ'!C7 -> 0.0331
B14: CAPM 27/11/2025 | D14: =$C$13+(D12*7.67%) -> 0.092508116 | E14: =$C$13+(E12*7.67%) -> 0.10145124 | F14: =$C$13+(F12*7.67%) -> 0.13710514 | G14: =$C$13+(G12*7.67%) -> 0.034480657 | H14: =$C$13+(H12*7.67%) -> 0.11673977 | I14: =$C$13+(I12*7.67%) -> 0.14265736
B15: ΜΕΣΗ ΑΠΟΔΟΣΗ ΧΑΡΤΟΦΥΛΑΚΙΟΥ ΑΞΙΟΓΡΑΦΩΝ ΜΕ ΚΙΝΔΥΝΟ (RISK PORTFOLIO)
D16: w1 | E16: w2 | F16: w3 | G16: w4 | H16: w5 | I16: w6 | J16: ΣΥΝΟΛΑ
D17: {=TRANSPOSE(G29:G34)} -> 0.16666667 | E17: 0.16666667 | F17: 0.16666667 | G17: 0.16666667 | H17: 0.16666667 | I17: 0.16666667
B18: wi*Ri | D18: =D17*D4 -> 0.00010523748 | E18: =E17*E4 -> 0.00018093806 | F18: =F17*F4 -> 0.00061264401 | G18: =G17*G4 -> -0.00018511786 | H18: =H17*H4 -> 0.00019677844 | I18: =I17*I4 -> 0.00040843045 | J18: =SUM(D18:I18) -> 0.0013189106
B19: wi*bi | D19: =D17*D12 -> 0.12909195 | E19: =E17*E12 -> 0.14852508 | F19: =F17*F12 -> 0.22599986 | G19: =G17*G12 -> 0.0030001243 | H19: =H17*H12 -> 0.18174656 | I19: =I17*I12 -> 0.23806466 | J19: =SUM(D19:H19) -> 0.68836358
B20: wi*αi | D20: =D17*D11 -> -8.7318724e-05 | E20: =E17*E11 -> -4.0605005e-05 | F20: =F17*F11 -> 0.00029279089 | G20: =G17*G11 -> -0.00018959291 | H20: =H17*H11 -> -7.4318462e-05 | I20: =I17*I11 -> 5.3328308e-05 | J20: =SUM(D20:H20) -> -9.9044212e-05
B22: ΜΕΣΗ ΑΠΟΔΟΣΗ ΧΑΡΤΟΦΥΛΑΚΙΟΥ
D23: =J18 -> 0.0013189106 | E23: ΜΕΓΙΣΤΟΠΟΙΗΣΗ ΑΠΟΔΟΣΗΣ
E24: ΜΕ ΑΛΛΑΓΗ ΠΟΣΟΣΤΩΝ
B25: Μεσο σταθμ. βητα | C25: βp | D25: =J19 -> 0.68836358 | F25: MMULT(D12:I12;G29:G34)
B26: Μεσο σταθμ. Αλφα | C26: αp | D26: =J20 -> -9.9044212e-05
B27: ΔΙΑΚ. ΑΓΟΡΑΣ | C27: σ2m | D27: ='GREECE Ret'!N8 -> 0.00013844652 | G27: τιμες εκκινησης
B28: ΑΠΟΔΟΣΗ ΧΑΡΤ | C28: Rp | D28: =J18 -> 0.0013189106
B29: Συνολικός Κίνδυνος Χαρτοφυλακίου | G29: =1/6 -> 0.16666667 | H29: w1 | J29: Σημ.: Αριστοποιηση ερημην του επιπεδου κινδυνου του επενδυτου
B30: Διακυμανση | C30: σ2p | D30: =(D25^2)*VarRm -> 6.5602111e-05 | G30: =1/6 -> 0.16666667 | H30: w2
B31: Τυπ. Αποκλιση | C31: σp | D31: =SQRT(30) -> 5.4772256 | G31: =1/6 -> 0.16666667 | H31: w3
G32: =1/6 -> 0.16666667 | H32: w4
B33: Α | C33: ΕΛΑΧΙΣΤΟΠΟΙΗΣΗ ΚΙΝΔΥΝΟΥ | G33: =1/6 -> 0.16666667 | H33: w5
C34: ΜΕ ΑΛΛΑΓΗ ΠΟΣΟΣΤΩΝ | G34: =1/6 -> 0.16666667 | H34: w6
G35: =SUM(G29:G34) -> 1
J36: Όταν ο αριθμός των αξιογράφων (n) που περιλαμβάνονται στο χαρτοφυλάκιο είναι μεγάλος
C37: ΓΙΑ ΣΥΝΘΕΣΗ (W) ΠΟΥ ΕΛΑΧΙΣΤΟΠΟΙΕΙ | J37: τότε ο παραπάνω τύπος μετασχηματίζεται ως ακολούθως
C38: ΤΟΝ ΚΙΝΔΥΝΟ
C39: Εργαλεία/Προσθετα/Ανάλυση
D40: και Επίλυση
J42: σp=βp*σm
F46: Portfolio Scenarios | J46: ΕΛΑΧΙΣΤΟΠΟΙΗΣΗ ΚΙΝΔΥΝΟΥ | N46: ΜΕΓΙΣΤΟΠΟΙΗΣΗ ΚΕΡΔΟΥΣ
I47: Risk Minimized | N47: Return Maximized
G48: ΙΣΟΜΕΡΕΣ | I48: Min | J48: ΑΓΟΡΑ | K48: 0% to 25% | L48: 8% to 25% | N48: Long | O48: 0% to 25% | P48: 8% to 25%
G49: ΧΑΡΤΟΦΥΛΑΚΙΟ | I49: Var | J49: ΜΟΝΟ | K49: Weights | L49: Weights | N49: Only | O49: Weights | P49: Weights
F50: ΜΕΤΟΧΕΣ | H50: ΜΕΤΟΧΕΣ | I50: Portfolio | J50: Portfolio | K50: Portfolio | L50: Portfolio | M50: Stock | N50: Portfolio | O50: Portfolio | P50: Portfolio
F51: OPAr | G51: =1/6 -> 0.16666667 | H51: OPAr | I51: 12123451 | J51: =1/6 -> 0.16666667 | K51: =1/6 -> 0.16666667 | L51: =1/6 -> 0.16666667 | M51: OPAr | N51: =1/6 -> 0.16666667 | O51: =1/6 -> 0.16666667 | P51: 0.16666667
F52: AGNr | G52: =1/6 -> 0.16666667 | H52: AGNr | I52: -1334939.9 | J52: =1/6 -> 0.16666667 | K52: =1/6 -> 0.16666667 | L52: =1/6 -> 0.16666667 | M52: AGNr | N52: =1/6 -> 0.16666667 | O52: =1/6 -> 0.16666667 | P52: 0.16666667
F53: ACBr | G53: =1/6 -> 0.16666667 | H53: ACBr | I53: -8947848.4 | J53: =1/6 -> 0.16666667 | K53: =1/6 -> 0.16666667 | L53: =1/6 -> 0.16666667 | M53: ACBr | N53: =1/6 -> 0.16666667 | O53: =1/6 -> 0.16666667 | P53: 0.16666667
F54: HRMr | G54: =1/6 -> 0.16666667 | H54: HRMr | I54: 5120264.8 | J54: =1/6 -> 0.16666667 | K54: =1/6 -> 0.16666667 | L54: =1/6 -> 0.16666667 | M54: HRMr | N54: =1/6 -> 0.16666667 | O54: =1/6 -> 0.16666667 | P54: 0.16666667
F55: MTLNr | G55: =1/6 -> 0.16666667 | H55: MTLNr | I55: -1614276.8 | J55: =1/6 -> 0.16666667 | K55: =1/6 -> 0.16666667 | L55: =1/6 -> 0.16666667 | M55: MTLNr | N55: =1/6 -> 0.16666667 | O55: =1/6 -> 0.16666667 | P55: 0.16666667
F56: EURBr | G56: =1/6 -> 0.16666667 | H56: EURBr | I56: -5346649.4 | J56: =1/6 -> 0.16666667 | K56: =1/6 -> 0.16666667 | L56: =1/6 -> 0.16666667 | M56: EURBr | N56: =1/6 -> 0.16666667 | O56: =1/6 -> 0.16666667 | P56: 0.16666667
F57: Αθροισμα | G57: =SUM(G51:G56) -> 1 | H57: Αθροισμα | I57: =SUM(I51:I56) -> 1 | J57: =SUM(J51:J56) -> 1 | K57: =SUM(K51:K56) -> 1 | L57: =SUM(L51:L56) -> 1 | M57: Αθροισμα | N57: =SUM(N51:N56) -> 1 | O57: =SUM(O51:O56) -> 1 | P57: =SUM(P51:P56) -> 1
F59: Αναμενομενη Αποδοση | G59: {=MMULT($D$4:$I$4,G51:G56)} -> 0.0013189106 | H59: Expected Return | I59: {=MMULT($D$4:$I$4,I51:I56)} -> -47380.725 | J59: {=MMULT($D$4:$I$4,J51:J56)} -> 0.0013189106 | K59: {=MMULT($D$4:$I$4,K51:K56)} -> 0.0013189106 | M59: Expected Return | N59: {=MMULT($D$4:$I$4,N51:N56)} -> 0.0013189106 | O59: {=MMULT($D$4:$I$4,O51:O56)} -> 0.0013189106 | P59: {=MMULT($D$4:$I$4,P51:P56)} -> 0.0013189106
F61: Συντ. βητα (β) | G61: {=MMULT($D$12:$I$12,G51:G56)} -> 0.92642824 | H61: Συντ. βητα (β) | I61: {=MMULT($D$12:$I$12,I51:I56)} -> -13237925 | J61: {=MMULT($D$12:$I$12,J51:J56)} -> 0.92642824 | K61: {=MMULT($D$12:$I$12,K51:K56)} -> 0.92642824 | M61: Συντ. βητα (β) | N61: {=MMULT($D$12:$I$12,N51:N56)} -> 0.92642824 | O61: {=MMULT($D$12:$I$12,O51:O56)} -> 0.92642824 | P61: {=MMULT($D$12:$I$12,P51:P56)} -> 0.92642824
F62: Διακυμανση | G62: =(G61^2)*VarRm -> 0.0001188244 | H62: Διακυμανση | I62: =(I61^2)*VarRm -> 2.4261735e+10 | J62: =(J61^2)*VarRm -> 0.0001188244 | K62: =(K61^2)*VarRm -> 0.0001188244 | M62: Διακυμανση | N62: =(N61^2)*VarRm -> 0.0001188244 | O62: =(O61^2)*VarRm -> 0.0001188244 | P62: =(P61^2)*VarRm -> 0.0001188244
F64: Τυπ. Αποκλιση | G64: =SQRT(62) -> 7.8740079 | H64: Τυπ. Αποκλιση | I64: =SQRT(62) -> 7.8740079 | J64: =SQRT(62) -> 7.8740079 | K64: =SQRT(62) -> 7.8740079 | M64: Τυπ. Αποκλιση | N64: =SQRT(62) -> 7.8740079 | O64: =SQRT(62) -> 7.8740079 | P64: =SQRT(62) -> 7.8740079

Sheet USA Sharpe
A1: ΑΠΌ | B1: ΕΩΣ
A2: 43531 | B2: 43897
D3: R1 | E3: R2 | F3: R3 | G3: R4 | H3: R5 | I3: R6
B4: μ
B5: σ^2
B6: σ
B8: σ/μ
A9: Μέγεθος δείγματος | B9: n
A11: INTERCEPT | B11: αλφα
A12: SLOPE | B12: βητα
B15: ΜΕΣΗ ΑΠΟΔΟΣΗ ΧΑΡΤΟΦΥΛΑΚΙΟΥ ΑΞΙΟΓΡΑΦΩΝ ΜΕ ΚΙΝΔΥΝΟ (RISK PORTFOLIO)
D16: w1 | E16: w2 | F16: w3 | G16: w4 | H16: w5 | I16: w6 | J16: ΣΥΝΟΛΑ
B18: wi*Ri
B19: wi*bi
B20: wi*αi
B22: ΜΕΣΗ ΑΠΟΔΟΣΗ ΧΑΡΤΟΦΥΛΑΚΙΟΥ
E23: ΜΕΓΙΣΤΟΠΟΙΗΣΗ ΑΠΟΔΟΣΗΣ
E24: ΜΕ ΑΛΛΑΓΗ ΠΟΣΟΣΤΩΝ
B25: Μεσο σταθμ. βητα | C25: βp | F25: MMULT(D12:I12;G29:G34)
B26: Μεσο σταθμ. Αλφα | C26: αp
B27: ΔΙΑΚ. ΑΓΟΡΑΣ | C27: σ2m | G27: τιμες εκκινησης
B28: ΑΠΟΔΟΣΗ ΧΑΡΤ | C28: Rp
B29: Συνολικός Κίνδυνος Χαρτοφυλακίου | G29: =1/6 -> 0.16666667 | H29: w1 | J29: Σημ.: Αριστοποιηση ερημην του επιπεδου κινδυνου του επενδυτου
B30: Διακυμανση | C30: σ2p | G30: =1/6 -> 0.16666667 | H30: w2
B31: Τυπ. Αποκλιση | C31: σp | G31: =1/6 -> 0.16666667 | H31: w3
G32: =1/6 -> 0.16666667 | H32: w4
B33: Α | C33: ΕΛΑΧΙΣΤΟΠΟΙΗΣΗ ΚΙΝΔΥΝΟΥ | G33: =1/6 -> 0.16666667 | H33: w5
C34: ΜΕ ΑΛΛΑΓΗ ΠΟΣΟΣΤΩΝ | G34: =1/6 -> 0.16666667 | H34: w6
G35: =SUM(G29:G34) -> 1
J36: Όταν ο αριθμός των αξιογράφων (n) που περιλαμβάνονται στο χαρτοφυλάκιο είναι μεγάλος
C37: ΓΙΑ ΣΥΝΘΕΣΗ (W) ΠΟΥ ΕΛΑΧΙΣΤΟΠΟΙΕΙ | J37: τότε ο παραπάνω τύπος μετασχηματίζεται ως ακολούθως
C38: ΤΟΝ ΚΙΝΔΥΝΟ
C39: Εργαλεία/Προσθετα/Ανάλυση
D40: και Επίλυση
J42: σp=βp*σm
F46: Portfolio Scenarios | J46: ΕΛΑΧΙΣΤΟΠΟΙΗΣΗ ΚΙΝΔΥΝΟΥ | N46: ΜΕΓΙΣΤΟΠΟΙΗΣΗ ΚΕΡΔΟΥΣ
I47: Risk Minimized | N47: Return Maximized
G48: ΙΣΟΜΕΡΕΣ | I48: Min | J48: ΑΓΟΡΑ | K48: 0% to 25% | L48: 8% to 25% | N48: Long | O48: 0% to 25% | P48: 8% to 25%
G49: ΧΑΡΤΟΦΥΛΑΚΙΟ | I49: Var | J49: ΜΟΝΟ | K49: Weights | L49: Weights | N49: Only | O49: Weights | P49: Weights
F50: ΜΕΤΟΧΕΣ | H50: ΜΕΤΟΧΕΣ | I50: Portfolio | J50: Portfolio | K50: Portfolio | L50: Portfolio | M50: Stock | N50: Portfolio | O50: Portfolio | P50: Portfolio
F57: Αθροισμα | H57: Αθροισμα | M57: Αθροισμα
F59: Αναμενομενη Αποδοση | H59: Expected Return | M59: Expected Return
F61: Συντ. βητα (β) | H61: Συντ. βητα (β) | M61: Συντ. βητα (β)
F62: Διακυμανση | H62: Διακυμανση | M62: Διακυμανση
F64: Τυπ. Αποκλιση | H64: Τυπ. Αποκλιση | M64: Τυπ. Αποκλιση

Sheet Composite
B1: CAPITAL ASSET PRICING MODEL | D1: ΛΑΜΒΑΝΟΥΜΕ ΥΠΟΨΗ ΚΑΙ ΤΟ ΠΡΟΦΙΛ ΕΠΕΝΔΥΤΟΥ | J1: Efficient stock portfolio.
B2: CAPM | J2: Find the weightings of stocks in an efficient portfolio which maximizes the portfolio rate of
B3: ΑΝΑΛΥΣΗ ΑΠΟΔΟΣΗΣ-ΚΙΝΔΥΝΟΥ ΧΑΡΤΟΦΥΛΑΚΙΟΥ | J3: return for a given level of risk. This worksheet uses the Sharpe single-index model; you
B4: ΜΕ ΕΝΑ ΜΕΡΟΣ (%) ΕΠΕΝΔΥΜΕΝΟ ΣΕ ΧΡΕΟΓΡΑΦΑ ΜΕ ΚΙΝΔΥΝΟ ΚΑΙ ΤΟ ΥΠΟΛΟΙΠΟ ΣΕ ΧΡΕΟΓΡΑΦΑ ΜΗΔΕΝΙΚΟΥ ΚΙΝΔΥΝΟΥ | J4: can also use the Markowitz method if you have covariance terms available.
A5: ΓΙΑ Greece | B5: Rf | C5: =Ομολογα!C6 -> 0.03242 | D5: ετησιως | J5: (Covariances for n securities are difficult to calculate, so we use the Rm statistics)
B7: (Composite Portfolio) | C7: ΣΥΝΘΕΤΟ ΧΑΡΤΟΦ
L8: ΠΟΣΟΣΤΑ ΑΠΌ ΜΟΝΤΕΛΟ SHARP
A9: 1 | B9: Ριψοκίνδυνο Χαρτ (χρεόγραφα j) | E9: Wp | F9: w1
A10: 2 | B10: Rf | E10: Wf | F10: w2
F11: w3 | L11: ΥΠΟΛΟΓΙΣΜΕΝΑ ΒΑΣΗ
F12: w4
F13: w5
B14: ΑΠΌ ΒΑΣΗ ΔΕΔΟΜΕΝΩΝ | C14: ΑΠΌ ΒΑΣΗ ΔΕΔΟΜΕΝΩΝ | E14: ΏΣΤΕ | F14: w6
B15: ΑΠΟΔΟΣΗ ΣΕ ΗΜΕΡΗΣΙΑ ΒΑΣΗ | C15: ΑΠΟΔΟΣΗ ΣΕ ΕΤΗΣΙΑ ΒΑΣΗ | E15: ΝΑ ΙΣΟΥΤΑΙ ΜΕ
D16: ΑΠΌ ΕΡΩΤΗΜΑΤΟΛΟΓΙΟ
B19: E(Rp) | C19: ΜΕΤΑΦΟΡΑ ΑΠΌ SHARPE
B20: Var(p) | C20: ΜΕΤΑΦΟΡΑ ΑΠΌ SHARPE
B21: σ(p) | C21: ΜΕΤΑΦΟΡΑ ΑΠΌ SHARPE
B22: Var(c) | C22: YΠΟΛΟΓΙΣΜΕΝΑ
B23: σ[c] | C23: YΠΟΛΟΓΙΣΜΕΝΑ
B24: Ε(Rc) | C24: YΠΟΛΟΓΙΣΜΕΝΑ
B33: CAPITAL ASSET PRICING MODEL | D33: ΛΑΜΒΑΝΟΥΜΕ ΥΠΟΨΗ ΚΑΙ ΤΟ ΠΡΟΦΙΛ ΕΠΕΝΔΥΤΟΥ | J33: Efficient stock portfolio.
B34: CAPM | J34: Find the weightings of stocks in an efficient portfolio which maximizes the portfolio rate of
B35: ΑΝΑΛΥΣΗ ΑΠΟΔΟΣΗΣ-ΚΙΝΔΥΝΟΥ ΧΑΡΤΟΦΥΛΑΚΙΟΥ | J35: return for a given level of risk. This worksheet uses the Sharpe single-index model; you
B36: ΜΕ ΕΝΑ ΜΕΡΟΣ (%) ΕΠΕΝΔΥΜΕΝΟ ΣΕ ΧΡΕΟΓΡΑΦΑ ΜΕ ΚΙΝΔΥΝΟ ΚΑΙ ΤΟ ΥΠΟΛΟΙΠΟ ΣΕ ΧΡΕΟΓΡΑΦΑ ΜΗΔΕΝΙΚΟΥ ΚΙΝΔΥΝΟΥ | J36: can also use the Markowitz method if you have covariance terms available.
A37: ΓΙΑ USA | B37: Rf | C37: =Ομολογα!C7 -> 0.03983 | D37: ετησιως | J37: (Covariances for n securities are difficult to calculate, so we use the Rm statistics)
B39: (Composite Portfolio) | C39: ΣΥΝΘΕΤΟ ΧΑΡΤΟΦ
L40: ΠΟΣΟΣΤΑ ΑΠΌ ΜΟΝΤΕΛΟ SHARP
A41: 1 | B41: Ριψοκίνδυνο Χαρτ (χρεόγραφα j) | E41: Wp | F41: w1
A42: 2 | B42: Rf | E42: Wf | F42: w2
F43: w3 | L43: ΥΠΟΛΟΓΙΣΜΕΝΑ ΒΑΣΗ
F44: w4
F45: w5
B46: ΑΠΌ ΒΑΣΗ ΔΕΔΟΜΕΝΩΝ | C46: ΑΠΌ ΒΑΣΗ ΔΕΔΟΜΕΝΩΝ | E46: ΏΣΤΕ | F46: w6
B47: ΑΠΟΔΟΣΗ ΣΕ ΗΜΕΡΗΣΙΑ ΒΑΣΗ | C47: ΑΠΟΔΟΣΗ ΣΕ ΕΤΗΣΙΑ ΒΑΣΗ | E47: ΝΑ ΙΣΟΥΤΑΙ ΜΕ
D48: ΑΠΌ ΕΡΩΤΗΜΑΤΟΛΟΓΙΟ
B51: E(Rp) | C51: ΜΕΤΑΦΟΡΑ ΑΠΌ SHARPE
B52: Var(p) | C52: ΜΕΤΑΦΟΡΑ ΑΠΌ SHARPE
B53: σ(p) | C53: ΜΕΤΑΦΟΡΑ ΑΠΌ SHARPE
B54: Var(c) | C54: YΠΟΛΟΓΙΣΜΕΝΑ
B55: σ[c] | C55: YΠΟΛΟΓΙΣΜΕΝΑ
B56: Ε(Rc) | C56: YΠΟΛΟΓΙΣΜΕΝΑ

Sheet Investment
F2: =G10*H10 -> 0
A3: ΓΙΑ Greece | B3: ΑΡΧΙΚΗ ΔΟΜΗ XAPΤOΦYΛAKIOY | L3: ΔΟΜΗ XAPΤOΦYΛAKIOY ΤΕΛΟΣ ΕΞΑΜΗΝΟΥ | R3: ΔΟΜΗ XAPΤOΦYΛAKIOY ΈΝΑ ΕΤΟΣ ΜΕΤΑ
B4: 20000 | C4: ευρω | L4: 20000 | M4: ευρω | R4: 20000 | S4: ευρω
B5: 43897 | L5: 43601 | R5: 43601
B6: TITΛOΣ XPEΩΓPAΦOY | C6: ΣΥΜΒΟΛΟ | D6: ΒΑΘΜΟΣ ΚΙΝΔΥΝΟΥ (συντ. βητα) | E6: ΠOΣOΣTO ΣYMMETOXHΣ ΣΤΟ ΣΥΝΟΛΟ AΞIAΣ | F6: MONAΔA ΔIAΠPΑΓΜΑΤΕΥΣHΣ | G6: ΠOΣOTHTA [ΣΥΝΟΛΙΚΟ ΚΟΣΤΟΣ πριν /(ΜΟΝΑΔΑ ΔΙΑΠΡΑΓΜΑΤΕΣΥΣΗΣ x ΜΟΝΑΔΙΑΙΟ ΚΟΣΤΟΣ)] | H6: KOΣTOΣ MONAΔAΣ (ΑΠΌ ΒΑΣΗ ΔΕΔΟΜΕΝΩΝ) | I6: ΣYNOΛIKO KOΣTOΣ πριν ΤΗΝ ΣΤΡΟΓΓΥΛΟΠΟΙΗΣΗ | J6: ΣYNOΛIKO KOΣTOΣ μετα ΤΗΝ ΣΤΡΟΓΓΥΛΟΠΟΙΗΣΗ [ΠΟΣΟΤΗΤΑ x ΜΟΝΑΔΙΑΙΟ ΚΟΣΤΟΣ] | L6: MONAΔA ΔIAΠPΑΓΜΑΤΕΥΣHΣ | M6: ΠOΣOTHTA | N6: KOΣTOΣ MONAΔAΣ (ΑΠΌ ΒΑΣΗ ΔΕΔΟΜΕΝΩΝ) | O6: ΣYNOΛIKO KOΣTOΣ μετα ΤΗΝ ΣΤΡΟΓΓΥΛΟΠΟΙΗΣΗ [ΠΟΣΟΤΗΤΑ x ΜΟΝΑΔΙΑΙΟ ΚΟΣΤΟΣ] | P6: ΠOΣOΣTO ΑΠΟΔΟΣΗΣ | R6: MONAΔA ΔIAΠPΑΓΜΑΤΕΥΣHΣ | S6: ΠOΣOTHTA | T6: KOΣTOΣ MONAΔAΣ (ΑΠΌ ΒΑΣΗ ΔΕΔΟΜΕΝΩΝ) | U6: ΣYNOΛIKO KOΣTOΣ μετα ΤΗΝ ΣΤΡΟΓΓΥΛΟΠΟΙΗΣΗ [ΠΟΣΟΤΗΤΑ x ΜΟΝΑΔΙΑΙΟ ΚΟΣΤΟΣ] | V6: ΠOΣOΣTO ΑΠΟΔΟΣΗΣ
B8: ΜΕΤΟΧΗ 1 | F8: 1
B9: ΜΕΤΟΧΗ 2 | F9: 1
B10: ΜΕΤΟΧΗ 3 | F10: 1
B11: Αμοιβαίο 1 | F11: 1
B12: Αμοιβαίο 2 | F12: 1
B13: Αμοιβαίο 3 | F13: 1
B14: Risk-free rate | C14: ΟΜΟΛΟΓΟ | D14: ΜΗΔΕΝΙΚΟΥ | F14: 1000
B15: ΔΕΔΟΥΛΕΥΜΕΝΟΙ ΤΟΚΟΙ
B16: ΣΥΝΟΛΑ | O16: =SUM(O8:O15) -> 0 | U16: =SUM(U8:U15) -> 0
N17: ΑΡΧΙΚΟ ΠΟΣΟ | O17: =J16 -> 0 | T17: ΑΡΧΙΚΟ ΠΟΣΟ | U17: =J16 -> 0
B18: ΣΥΝΟΛΙΚΑ ΑΔΙΑΘΕΤΑ ΤΑΜΕΙΑΚΑ ΥΠΟΛΟΙΠΑ | I18: ΥΠΟΛΟΙΠΟ | J18: =$B$4-J16 -> 20000 | N18: ΥΠΟΛΟΙΠΟ | O18: =J18 -> 20000 | T18: ΥΠΟΛΟΙΠΟ | U18: =O18 -> 20000
E19: ΔΑΝΕΙΣΜΟΣ
E20: ΚΑΙ ΑΓΟΡΑ | N20: ΑΠΟΔΟΣΗ ΧΑΡΤΟΦΥΛΑΚΙΟΥ | P20: =LN(O16/O17) -> #DIV/0! | T20: ΑΠΟΔΟΣΗ ΧΑΡΤΟΦΥΛΑΚΙΟΥ | V20: =LN(U16/U17) -> #DIV/0!
E21: ΜΕΤΟΧΩΝ | F21: ΔΕΔΟΜΕΝΟ | H21: ΠΡΑΓΜΑΤΙΚΕΣ
F22: ΑΓΟΡΑΣ | H22: ΤΙΜΕΣ ΑΓΟΡΑΣ | N22: ΠΡΑΓΜΑΤΙΚΕΣ | T22: ΕΚΤΙΜΗΜΕΝΕΣ
E23: ΑΡΧΙΚΑ % | H23: =B5 -> 43897 | N23: ΤΙΜΕΣ ΑΓΟΡΑΣ | T23: ΤΙΜΕΣ ΑΓΟΡΑΣ
E24: ΜΕΧΡΙ ΝΑ ΒΡΟΥΜΕ | N24: =L5 -> 43601 | T24: =R5 -> 43601
E25: ΤΑ ΑΡΙΣΤΑ
A32: ΓΙΑ USA | B32: ΑΡΧΙΚΗ ΔΟΜΗ XAPΤOΦYΛAKIOY | L32: ΔΟΜΗ XAPΤOΦYΛAKIOY ΤΕΛΟΣ ΕΞΑΜΗΝΟΥ | R32: ΔΟΜΗ XAPΤOΦYΛAKIOY ΈΝΑ ΕΤΟΣ ΜΕΤΑ
B33: 20000 | C33: $ | L33: 20000 | R33: 20000 | S33: $
B34: 43897 | L34: =L5 -> 43601 | R34: =R5 -> 43601
B35: TITΛOΣ XPEΩΓPAΦOY | C35: ΣΥΜΒΟΛΟ | D35: ΒΑΘΜΟΣ ΚΙΝΔΥΝΟΥ (συντ. βητα) | E35: ΠOΣOΣTO ΣYMMETOXHΣ ΣΤΟ ΣΥΝΟΛΟ AΞIAΣ | F35: MONAΔA ΔIAΠPΑΓΜΑΤΕΥΣHΣ | G35: ΠOΣOTHTA [ΣΥΝΟΛΙΚΟ ΚΟΣΤΟΣ πριν /(ΜΟΝΑΔΑ ΔΙΑΠΡΑΓΜΑΤΕΣΥΣΗΣ x ΜΟΝΑΔΙΑΙΟ ΚΟΣΤΟΣ)] | H35: KOΣTOΣ MONAΔAΣ (ΑΠΌ ΒΑΣΗ ΔΕΔΟΜΕΝΩΝ) | I35: ΣYNOΛIKO KOΣTOΣ πριν ΤΗΝ ΣΤΡΟΓΓΥΛΟΠΟΙΗΣΗ | J35: ΣYNOΛIKO KOΣTOΣ μετα ΤΗΝ ΣΤΡΟΓΓΥΛΟΠΟΙΗΣΗ [ΠΟΣΟΤΗΤΑ x ΜΟΝΑΔΙΑΙΟ ΚΟΣΤΟΣ] | L35: MONAΔA ΔIAΠPΑΓΜΑΤΕΥΣHΣ | M35: ΠOΣOTHTA | N35: KOΣTOΣ MONAΔAΣ (ΑΠΌ ΒΑΣΗ ΔΕΔΟΜΕΝΩΝ) | O35: ΣYNOΛIKO KOΣTOΣ μετα ΤΗΝ ΣΤΡΟΓΓΥΛΟΠΟΙΗΣΗ [ΠΟΣΟΤΗΤΑ x ΜΟΝΑΔΙΑΙΟ ΚΟΣΤΟΣ] | P35: ΠOΣOΣTO ΑΠΟΔΟΣΗΣ | R35: MONAΔA ΔIAΠPΑΓΜΑΤΕΥΣHΣ | S35: ΠOΣOTHTA | T35: KOΣTOΣ MONAΔAΣ (ΑΠΌ ΒΑΣΗ ΔΕΔΟΜΕΝΩΝ) | U35: ΣYNOΛIKO KOΣTOΣ μετα ΤΗΝ ΣΤΡΟΓΓΥΛΟΠΟΙΗΣΗ [ΠΟΣΟΤΗΤΑ x ΜΟΝΑΔΙΑΙΟ ΚΟΣΤΟΣ] | V35: ΠOΣOΣTO ΑΠΟΔΟΣΗΣ
B37: ΜΕΤΟΧΗ 1 | F37: 1
B38: ΜΕΤΟΧΗ 2 | F38: 1
B39: ΜΕΤΟΧΗ 3 | F39: 1
B40: ΜΕΤΟΧΗ 4 | F40: 1
B41: ΜΕΤΟΧΗ 5 | F41: 1
B42: ΜΕΤΟΧΗ 6 | F42: 1
B43: Risk-free rate | D43: ΜΗΔΕΝΙΚΟΥ | E43: =Composite!D10 -> 0 | F43: 1000
B44: ΔΕΔΟΥΛΕΥΜΕΝΟΙ ΤΟΚΟΙ
B45: ΣΥΝΟΛΑ | E45: =SUM(E37:E44) -> 0
N46: ΑΡΧΙΚΟ ΠΟΣΟ | O46: =J45 -> 0 | T46: ΑΡΧΙΚΟ ΠΟΣΟ | U46: =J45 -> 0
B47: ΣΥΝΟΛΙΚΑ ΑΔΙΑΘΕΤΑ ΤΑΜΕΙΑΚΑ ΥΠΟΛΟΙΠΑ | I47: ΥΠΟΛΟΙΠΟ | J47: =$B$4-J45 -> 20000 | N47: ΥΠΟΛΟΙΠΟ | O47: =J47 -> 20000 | T47: ΥΠΟΛΟΙΠΟ | U47: =O47 -> 20000
E48: ΔΑΝΕΙΣΜΟΣ
E49: ΚΑΙ ΑΓΟΡΑ | N49: ΑΠΟΔΟΣΗ ΧΑΡΤΟΦΥΛΑΚΙΟΥ | P49: =LN(O45/O46) -> #DIV/0! | T49: ΑΠΟΔΟΣΗ ΧΑΡΤΟΦΥΛΑΚΙΟΥ | V49: =LN(U45/U46) -> #DIV/0!
E50: ΜΕΤΟΧΩΝ | F50: ΔΕΔΟΜΕΝΟ | H50: ΠΡΑΓΜΑΤΙΚΕΣ
F51: ΑΓΟΡΑΣ | H51: ΤΙΜΕΣ ΑΓΟΡΑΣ | N51: ΠΡΑΓΜΑΤΙΚΕΣ | T51: ΕΚΤΙΜΗΜΕΝΕΣ
E52: ΑΡΧΙΚΑ % | H52: =B34 -> 43897 | N52: ΤΙΜΕΣ ΑΓΟΡΑΣ | T52: ΤΙΜΕΣ ΑΓΟΡΑΣ
E53: ΜΕΧΡΙ ΝΑ ΒΡΟΥΜΕ | N53: =L34 -> 43601 | T53: =R34 -> 43601
E54: ΤΑ ΑΡΙΣΤΑ

Sheet Forecasts Greece
A1: ΟΙΚΟΝΟΜΕΤΡΙΚΗ ΑΝΑΛΥΣΗ | B1: Greece
A3: ΑΠΌ | B3: /10/2023 | C3: ΕΩΣ | D3: /1/2024
C5: Rm | D5: R1 | E5: R2 | F5: R3 | G5: R4 | H5: R5 | I5: R6
A6: ΑΡΙΘΜΟΣ ΠΑΡΑΤΗΡΗΣΕΩΝ | B6: n
A7: ΜΕΣΗ ΑΠΟΔΟΣΗ | B7: Ri
A8: INTERCEPT | B8: αλφα
A9: SLOPE | B9: βητα
A11: ΠΡΟΒΛΕΨΕΙΣ ΒΑΣΕΙ ΕΚΤΙΜΗΣΕΩΝ ΑΓΟΡΑΣ ΚΑΙ ΕΡΕΥΝΗΤΗ
A13: ΑΠΌ | B13: =D3 -> /1/2024 | C13: ΕΩΣ | D13: =B13+365 -> #VALUE! | K13: ΔΤ ΧΑΑ
K14: ΠΙΘΑΝΟΤΗΤΑ | L14: ΑΠΟΔΟΣΗ
B15: ΑΠΟΔΟΣΗ ΔΤ ΧΑΑ | E15: r=(1+R)(1/mn)-1
B16: ΈΝΑ ΕΤΟΣ ΜΕΤΑ
B17: ΜΕΣΗ ΗΜΕΡΗΣΙΑ ΑΠΟΔΟΣΗ ΔΤΧΑΑ | D17: ή
B19: ΑΠΟΔΟΣΗ ΟΜΟΛΟΓΟΥ | D19: ΑΓΟΡΑ
B20: ΈΝΑ ΕΤΟΣ ΜΕΤΑ
B21: ΜΕΣΗ ΗΜΕΡΗΣΙΑ ΑΠΟΔΟΣΗ ΟΜΟΛΟΓΟΥ | D21: `
B23: ΤΙΜΕΣ ΚΑΙ ΑΠΟΔΟΣΗ ΧΡΕΟΓΡΑΦΩΝ | K23: ΑΠΟΔΟΣΗ ΕΤΗΣΙΟΥ ΟΜΟΛΟΓΟΥ
B24: ΈΝΑ ΕΤΟΣ ΜΕΤΑ | K24: ΠΙΘΑΝΟΤΗΤΑ | L24: ΑΠΟΔΟΣΗ
B26: ΑΝΑΜΕΝΟΜΕΝΗ ΗΜΕΡΗΣΙΑ ΑΠΟΔΟΣΗ
B27: ΑΝΑΜΕΝΟΜΕΝΗ ΕΤΗΣΙΑ ΑΠΟΔΟΣΗ | C27: R=(1+r)mn-1
B29: ΤΙΜΕΣ ΧΡΕΟΓΡΑΦΩΝ
B30: =B13 -> /1/2024
B32: ΤΙΜΕΣ ΧΡΕΟΓΡΑΦΩΝ
B33: =D13 -> #VALUE!

Sheet Forecasts USA
A1: ΟΙΚΟΝΟΜΕΤΡΙΚΗ ΑΝΑΛΥΣΗ | B1: USA
A3: ΑΠΌ | B3: /10/2023 | C3: ΕΩΣ | D3: /1/2024
C5: Rm | D5: R1 | E5: R2 | F5: R3 | G5: R4 | H5: R5 | I5: R6
A6: ΑΡΙΘΜΟΣ ΠΑΡΑΤΗΡΗΣΕΩΝ | B6: n
A7: ΜΕΣΗ ΑΠΟΔΟΣΗ | B7: Ri
A8: INTERCEPT | B8: αλφα
A9: SLOPE | B9: βητα
A11: ΠΡΟΒΛΕΨΕΙΣ ΒΑΣΕΙ ΕΚΤΙΜΗΣΕΩΝ ΑΓΟΡΑΣ ΚΑΙ ΕΡΕΥΝΗΤΗ
A13: ΑΠΌ | B13: =D3 -> /1/2024 | C13: ΕΩΣ | D13: =B13+365 -> #VALUE! | K13: ΔΤ ΧΑΑ
K14: ΠΙΘΑΝΟΤΗΤΑ | L14: ΑΠΟΔΟΣΗ
B15: ΑΠΟΔΟΣΗ ΔΤ ΧΑΑ | E15: r=(1+R)(1/mn)-1
B16: ΈΝΑ ΕΤΟΣ ΜΕΤΑ
B17: ΜΕΣΗ ΗΜΕΡΗΣΙΑ ΑΠΟΔΟΣΗ ΔΤΧΑΑ | D17: ή
B19: ΑΠΟΔΟΣΗ ΟΜΟΛΟΓΟΥ | D19: ΑΓΟΡΑ
B20: ΈΝΑ ΕΤΟΣ ΜΕΤΑ
B21: ΜΕΣΗ ΗΜΕΡΗΣΙΑ ΑΠΟΔΟΣΗ ΟΜΟΛΟΓΟΥ | D21: `
B23: ΤΙΜΕΣ ΚΑΙ ΑΠΟΔΟΣΗ ΧΡΕΟΓΡΑΦΩΝ | K23: ΑΠΟΔΟΣΗ ΕΤΗΣΙΟΥ ΟΜΟΛΟΓΟΥ
B24: ΈΝΑ ΕΤΟΣ ΜΕΤΑ | K24: ΠΙΘΑΝΟΤΗΤΑ | L24: ΑΠΟΔΟΣΗ
B26: ΑΝΑΜΕΝΟΜΕΝΗ ΗΜΕΡΗΣΙΑ ΑΠΟΔΟΣΗ
B27: ΑΝΑΜΕΝΟΜΕΝΗ ΕΤΗΣΙΑ ΑΠΟΔΟΣΗ | C27: R=(1+r)mn-1
B29: ΤΙΜΕΣ ΧΡΕΟΓΡΑΦΩΝ
B30: =B13 -> /1/2024
B32: ΤΙΜΕΣ ΧΡΕΟΓΡΑΦΩΝ
B33: =D13 -> #VALUE!
